SPI2APB_Bridge/apb_monitor.v
module apb_monitor#(
                        parameter BANK_ADDR		= 	2,
						parameter DATA_WIDTH 	= 	8,
						parameter ADDR_WIDTH	=	3
                        )(
                        output		[DATA_WIDTH-1 : 0]		m_prdata,
                        output		reg						m_pready,
                        input								m_pclk,
                        input								m_presetn,
                        input		[DATA_WIDTH-1 : 0]		m_pwdata,
                        input								m_pwrite,
                        input		[BANK_ADDR-1	:	0]	m_psel,
                        input								m_penable,
                        input		[ADDR_WIDTH-1 : 0]		m_paddr
                        );


initial begin
        $display("Module %m");
        $monitor($time, "\n pwrite=%h psel=%h, paddr=%h,pwdata=%h, penable=%h, pready=%h \n", m_pwrite, m_psel, m_paddr, m_pwdata, m_penable, m_pready);
end

always @(posedge m_pclk) begin
	if(m_penable)
		m_pready <= 1'b1;
	else
		m_pready <= 1'b0;
end 

endmodule

SPI2APB_Bridge/spi2apb_bridge.v
module spi2apb_bridge #(
						parameter BANK_ADDR		= 	2,
						parameter DATA_WIDTH 	= 	8,
						parameter ADDR_WIDTH	=	3
						)(
                        input 			sclk,
                        input 			resetn,
                        input 			mosi,
                        input 			ss,
                        output 			miso,

                        input		[DATA_WIDTH-1 : 0]		b_prdata,
                        input								b_pready,
                        output								b_pclk,
                        output								b_presetn,
                        output		[DATA_WIDTH-1 : 0]		b_pwdata,
                        output	reg							b_pwrite,
                        output	reg	[BANK_ADDR-1	:	0]	b_psel,
                        output	reg							b_penable,
                        output	reg	[ADDR_WIDTH-1 : 0]		b_paddr
                        );

reg	[15: 0]	reg_mosi;
reg [15: 0]	reg_miso;

reg [3 : 0] counter_spi;
reg	[3 : 0] counter_apb;

wire en_pwrite;
wire en_paddr;
wire en_psel;
wire en_penable_w;
wire en_penable_r;
reg en_pwdata;
reg en_sclk;

//spi interface
always @(posedge sclk or negedge resetn) begin
	if(!resetn) begin
		reg_miso 	<=	16'hdf3f;
		reg_mosi	<=	16'h0000;
        counter_spi	<=  4'b0000;
	end else begin
		if(!ss) begin
		 	reg_mosi [0] 	<= mosi;
		 	counter_spi 	<= counter_spi + 1'b1;
		end else 
			counter_spi <= 4'b0000;
	end
end

always @(negedge sclk) begin
	if(!ss && (counter_spi != 4'b0000)) begin
		reg_mosi	<= reg_mosi << 1'b1;
		reg_miso	<= reg_miso << 1'b1;
	end
end

assign miso = reg_miso[15];

// apb interface
always @(negedge sclk or negedge resetn or posedge b_pready) begin
	if(!resetn) begin
		b_pwrite <= 1'b0; 
		b_paddr	 <= 7'h0;
		b_psel	 <= 8'h0;
	end else begin
		if(b_pready) begin
			b_psel	<= 'b0;
		end else begin
			b_pwrite <= (en_pwrite)? reg_mosi[0] : b_pwrite;
			b_paddr	 <= (en_paddr)?  reg_mosi[2:0] : b_paddr;
			b_psel	 <= (en_psel)?	 reg_mosi[BANK_ADDR-1:0] : b_psel; 
		end
	end
end

always @(posedge sclk or negedge resetn or posedge b_pready) begin
	if(!resetn) begin
		b_penable <= 1'b0;
	end else begin
		if(b_pready) begin
			b_penable <= 1'b0;
		end else begin 
			b_penable <= (en_penable_w || en_penable_r)?  1'b1 : b_penable;
		end
	end
end

assign 	b_pclk			= sclk;
assign	en_pwrite		= (counter_spi == 4'h1)? 1'b1 : 1'b0;
assign  en_paddr		= (counter_spi == 4'h6)? 1'b1 : 1'b0;
assign  en_psel			= (counter_spi == 4'h3)? 1'b1 : 1'b0;		
assign  en_prdata		= (counter_spi == 4'h8)? 1'b1 : 1'b0;

assign	en_penable_w	= ((counter_spi == 4'h0 || counter_spi == 4'hf) && b_pwrite && !ss)? 1'b1 : 1'b0;
assign	en_penable_r	= ((counter_spi == 4'h6 || counter_spi == 4'h7) && !b_pwrite)? 1'b1 : 1'b0;	

assign  b_presetn 	= resetn; 
assign  b_pwdata    = reg_mosi[7:0];

always @(negedge sclk or negedge resetn) begin
	//if(!b_pwrite && counter_spi == 4'h8)
	if(!b_pwrite && b_penable)
		reg_miso [15:8] <= b_prdata; 
end


endmodule

SPI2APB_Bridge/bridge_tb.v
`timescale 1ns/1ps
`include "spi2apb_bridge.v"
`include "apb_monitor.v"

module bridge_tb#(
			        parameter BANK_NUM      = 	2,
					parameter DATA_WIDTH 	= 	16,
                 	parameter PDATA_WIDTH 	=  	8,
					parameter ADDR_WIDTH	=	7,
                  	parameter PADDR_WIDTH   = 	3
				)(
				);
reg     clk;
reg     sclk;
reg     resetn;

wire    mosi;
reg     ss;
wire	miso;

wire tb_pclk_a;
wire tb_pclk_b;
wire tb_presetn;
wire tb_pwrite;
wire tb_penable;
wire [BANK_NUM-1   : 0]  tb_psel;
wire [PDATA_WIDTH-1 : 0] tb_pwdata;
wire [PADDR_WIDTH-1 : 0] tb_paddr;
wire [PDATA_WIDTH-1 : 0] tb_prdata;
wire tb_pready;

reg [15:0] reg_mosi_tb;
reg [15:0] reg_miso_tb;

spi2apb_bridge i0(  .sclk(sclk),	        .resetn(resetn),        .mosi(mosi), 	         .miso(miso),		.ss(ss),
                    .b_pready(tb_pready),    .b_pclk(tb_pclk_a),        .b_presetn(tb_presetn),  
                    .b_pwrite(tb_pwrite),    .b_psel(tb_psel),        .b_penable(tb_penable),       
                    .b_pwdata(tb_pwdata),    .b_paddr(tb_paddr),      .b_prdata(tb_prdata));

apb_monitor i1(     .m_pready(tb_pready),    .m_pclk(tb_pclk_b),        .m_presetn(tb_presetn),  
                    .m_pwrite(tb_pwrite),    .m_psel(tb_psel),        .m_penable(tb_penable),       
                    .m_pwdata(tb_pwdata),    .m_paddr(tb_paddr),      .m_prdata(tb_prdata));

assign #(3) tb_pclk_b = tb_pclk_a;

function automatic reg [15:0] spi_xfer;
input [DATA_WIDTH-1:0] data_in;
reg [15:0] rd_mosi;
        begin
                reg_mosi_tb = data_in << 1;
                rd_mosi[15:1] = 'h0;
                rd_mosi[0] = miso;
                spi_xfer = rd_mosi;
        end

endfunction

assign mosi = reg_mosi_tb[15];
task write_reg(input [ADDR_WIDTH-1:0] addr, input [PDATA_WIDTH-1:0] data);
integer i;
        begin

             @(posedge clk);
                ss = 0;
                reg_mosi_tb [15] = 1;  
                reg_mosi_tb [14:8] = addr;
                reg_mosi_tb [7:0] = data;  
              /*  $display("mosi   = %b, = %h", reg_mosi_tb, reg_mosi_tb);
                $display("addr   = %b", addr);
                $display("data   = %b", data);
                */

                for(i = 0; i < 16; i = i + 1) begin
                        @(posedge clk);
                        sclk = !sclk;
                        reg_miso_tb = reg_miso_tb << 1;
                        #10
                        reg_miso_tb =  reg_miso_tb + spi_xfer(reg_mosi_tb);
                        @(posedge clk);
                        sclk = !sclk;
                end
                @(posedge clk);
                ss = 1;
        end
endtask



 
task read_reg();
        begin

        end
endtask

initial begin
        clk = 0;
        sclk = 0;
        resetn = 1;
        ss = 1;
        reg_mosi_tb = 16'h0000;
        reg_miso_tb = 16'h0000;
end

initial begin
        $dumpfile("bridge_tb.vcd");
        $dumpvars(0, bridge_tb);
        $display("Module %m") ;
        #3 resetn = 0;
        #3 resetn = 1;
        #100
        write_reg(7'h7f, 8'hff);
        #500 $finish;
end


always #10 clk = !clk; 

endmodule

SPI2APB_Bridge/bridge_tb.vcd
$date
	Sat Mar 05 22:30:38 2022
$end
$version
	Icarus Verilog
$end
$timescale
	1ps
$end
$scope module bridge_tb $end
$var wire 1 ! tb_pclk_b $end
$var wire 8 " tb_prdata [7:0] $end
$var wire 1 # tb_pwrite $end
$var wire 8 $ tb_pwdata [7:0] $end
$var wire 2 % tb_psel [1:0] $end
$var wire 1 & tb_presetn $end
$var wire 1 ' tb_pready $end
$var wire 1 ( tb_penable $end
$var wire 1 ) tb_pclk_a $end
$var wire 3 * tb_paddr [2:0] $end
$var wire 1 + mosi $end
$var wire 1 , miso $end
$var reg 1 - clk $end
$var reg 16 . reg_miso_tb [15:0] $end
$var reg 16 / reg_mosi_tb [15:0] $end
$var reg 1 0 resetn $end
$var reg 1 1 sclk $end
$var reg 1 2 ss $end
$scope function spi_xfer $end
$upscope $end
$scope module i0 $end
$var wire 1 ) b_pclk $end
$var wire 8 3 b_prdata [7:0] $end
$var wire 1 & b_presetn $end
$var wire 1 + mosi $end
$var wire 1 0 resetn $end
$var wire 1 1 sclk $end
$var wire 1 2 ss $end
$var wire 1 , miso $end
$var wire 1 4 en_pwrite $end
$var wire 1 5 en_psel $end
$var wire 1 6 en_prdata $end
$var wire 1 7 en_penable_w $end
$var wire 1 8 en_penable_r $end
$var wire 1 9 en_paddr $end
$var wire 8 : b_pwdata [7:0] $end
$var wire 1 ' b_pready $end
$var reg 3 ; b_paddr [2:0] $end
$var reg 1 ( b_penable $end
$var reg 2 < b_psel [1:0] $end
$var reg 1 # b_pwrite $end
$var reg 4 = counter_spi [3:0] $end
$var reg 16 > reg_miso [15:0] $end
$var reg 16 ? reg_mosi [15:0] $end
$upscope $end
$scope module i1 $end
$var wire 3 @ m_paddr [2:0] $end
$var wire 1 ! m_pclk $end
$var wire 1 ( m_penable $end
$var wire 8 A m_prdata [7:0] $end
$var wire 1 & m_presetn $end
$var wire 2 B m_psel [1:0] $end
$var wire 8 C m_pwdata [7:0] $end
$var wire 1 # m_pwrite $end
$var reg 1 ' m_pready $end
$upscope $end
$scope task read_reg $end
$upscope $end
$scope task write_reg $end
$var reg 7 D addr [6:0] $end
$var reg 8 E data [7:0] $end
$var integer 32 F i [31:0] $end
$upscope $end
$upscope $end
$enddefinitions $end
#0
$dumpvars
bx F
bx E
bx D
bx C
bx B
bz A
bx @
bx ?
bx >
bx =
bx <
bx ;
bx :
x9
x8
07
x6
x5
x4
bz 3
12
01
10
b0 /
b0 .
0-
x,
0+
bx *
0)
x(
x'
1&
bx %
bx $
x#
bz "
x!
$end
#3000
08
04
09
05
06
b0 $
b0 :
b0 C
1,
0(
b0 %
b0 <
b0 B
b0 *
b0 ;
b0 @
0#
b0 =
b0 ?
b1101111100111111 >
0&
00
0!
#6000
1&
10
#10000
1-
#20000
0-
#30000
1-
#40000
0-
#50000
1-
#60000
0-
#70000
1-
#80000
0-
#90000
1-
#100000
0-
#106000
b11111111 E
b1111111 D
#110000
1+
b0 F
b1111111111111111 /
02
1-
#120000
0-
#130000
14
b1 $
b1 :
b1 C
b1 =
b1 ?
1)
11
1-
#133000
0'
1!
#140000
b1 .
b1111111111111110 /
0-
#150000
b10 $
b10 :
b10 C
1#
b1011111001111110 >
b10 ?
b1 F
0)
01
1-
#153000
0!
#160000
0-
#170000
04
b11 $
b11 :
b11 C
b10 =
b11 ?
b10 .
1)
11
1-
#173000
1!
#180000
b11 .
b1111111111111100 /
0-
#190000
0,
b110 $
b110 :
b110 C
b111110011111100 >
b110 ?
b10 F
0)
01
1-
#193000
0!
#200000
0-
#210000
15
b111 $
b111 :
b111 C
b11 =
b111 ?
b110 .
1)
11
1-
#213000
1!
#220000
b1111111111111000 /
0-
#230000
1,
b1110 $
b1110 :
b1110 C
b11 %
b11 <
b11 B
b1111100111111000 >
b1110 ?
b11 F
0)
01
1-
#233000
0!
#240000
0-
#250000
05
b1111 $
b1111 :
b1111 C
b100 =
b1111 ?
b1100 .
1)
11
1-
#253000
1!
#260000
b1101 .
b1111111111110000 /
0-
#270000
b11110 $
b11110 :
b11110 C
b1111001111110000 >
b11110 ?
b100 F
0)
01
1-
#273000
0!
#280000
0-
#290000
b11111 $
b11111 :
b11111 C
b101 =
b11111 ?
b11010 .
1)
11
1-
#293000
1!
#300000
b11011 .
b1111111111100000 /
0-
#310000
b111110 $
b111110 :
b111110 C
b1110011111100000 >
b111110 ?
b101 F
0)
01
1-
#313000
0!
#320000
0-
#330000
19
b111111 $
b111111 :
b111111 C
b110 =
b111111 ?
b110110 .
1)
11
1-
#333000
1!
#340000
b110111 .
b1111111111000000 /
0-
#350000
b1111110 $
b1111110 :
b1111110 C
b111 *
b111 ;
b111 @
b1100111111000000 >
b1111110 ?
b110 F
0)
01
1-
#353000
0!
#360000
0-
#370000
09
b1111111 $
b1111111 :
b1111111 C
b111 =
b1111111 ?
b1101110 .
1)
11
1-
#373000
1!
#380000
b1101111 .
b1111111110000000 /
0-
#390000
b11111110 $
b11111110 :
b11111110 C
b1001111110000000 >
b11111110 ?
b111 F
0)
01
1-
#393000
0!
#400000
0-
#410000
16
b11111111 $
b11111111 :
b11111111 C
b1000 =
b11111111 ?
b11011110 .
1)
11
1-
#413000
1!
#420000
b11011111 .
b1111111100000000 /
0-
#430000
0,
b11111110 $
b11111110 :
b11111110 C
b11111100000000 >
b111111110 ?
b1000 F
0)
01
1-
#433000
0!
#440000
0-
#450000
06
b11111111 $
b11111111 :
b11111111 C
b1001 =
b111111111 ?
b110111110 .
1)
11
1-
#453000
1!
#460000
b1111111000000000 /
0-
#470000
b11111110 $
b11111110 :
b11111110 C
b111111000000000 >
b1111111110 ?
b1001 F
0)
01
1-
#473000
0!
#480000
0-
#490000
b11111111 $
b11111111 :
b11111111 C
b1010 =
b1111111111 ?
b1101111100 .
1)
11
1-
#493000
1!
#500000
b1111110000000000 /
0-
#510000
1,
b11111110 $
b11111110 :
b11111110 C
b1111110000000000 >
b11111111110 ?
b1010 F
0)
01
1-
#513000
0!
#520000
0-
#530000
b11111111 $
b11111111 :
b11111111 C
b1011 =
b11111111111 ?
b11011111000 .
1)
11
1-
#533000
1!
#540000
b11011111001 .
b1111100000000000 /
0-
#550000
b11111110 $
b11111110 :
b11111110 C
b1111100000000000 >
b111111111110 ?
b1011 F
0)
01
1-
#553000
0!
#560000
0-
#570000
b11111111 $
b11111111 :
b11111111 C
b1100 =
b111111111111 ?
b110111110010 .
1)
11
1-
#573000
1!
#580000
b110111110011 .
b1111000000000000 /
0-
#590000
b11111110 $
b11111110 :
b11111110 C
b1111000000000000 >
b1111111111110 ?
b1100 F
0)
01
1-
#593000
0!
#600000
0-
#610000
b11111111 $
b11111111 :
b11111111 C
b1101 =
b1111111111111 ?
b1101111100110 .
1)
11
1-
#613000
1!
#620000
b1101111100111 .
b1110000000000000 /
0-
#630000
b11111110 $
b11111110 :
b11111110 C
b1110000000000000 >
b11111111111110 ?
b1101 F
0)
01
1-
#633000
0!
#640000
0-
#650000
b11111111 $
b11111111 :
b11111111 C
b1110 =
b11111111111111 ?
b11011111001110 .
1)
11
1-
#653000
1!
#660000
b11011111001111 .
b1100000000000000 /
0-
#670000
b11111110 $
b11111110 :
b11111110 C
b1100000000000000 >
b111111111111110 ?
b1110 F
0)
01
1-
#673000
0!
#680000
0-
#690000
17
b11111111 $
b11111111 :
b11111111 C
b1111 =
b111111111111111 ?
b110111110011110 .
1)
11
1-
#693000
1!
#700000
b110111110011111 .
b1000000000000000 /
0-
#710000
b11111110 $
b11111110 :
b11111110 C
b1000000000000000 >
b1111111111111110 ?
b1111 F
0)
01
1-
#713000
0!
#720000
0-
#730000
b11111111 $
b11111111 :
b11111111 C
1(
b0 =
b1111111111111111 ?
b1101111100111110 .
1)
11
1-
#733000
0(
b0 %
b0 <
b0 B
1'
1!
#740000
0+
b1101111100111111 .
b0 /
0-
#750000
b10000 F
0)
01
1-
#753000
0!
#760000
0-
#770000
07
12
1-
