SPI2APB_Bridge/apb_monitor.v
module apb_monitor#(
                        parameter BANK_ADDR		= 	2,
						parameter DATA_WIDTH 	= 	8,
						parameter ADDR_WIDTH	=	3
                        )(
                        output		[DATA_WIDTH-1 : 0]		m_prdata,
                        output		reg						m_pready,
                        input								m_pclk,
                        input								m_presetn,
                        input		[DATA_WIDTH-1 : 0]		m_pwdata,
                        input								m_pwrite,
                        input		[BANK_ADDR-1	:	0]	m_psel,
                        input								m_penable,
                        input		[ADDR_WIDTH-1 : 0]		m_paddr
                        );


initial begin
        $display("Module %m");
        $monitor($time, "\n pwrite=%h psel=%h, paddr=%h,pwdata=%h, penable=%h, pready=%h \n", m_pwrite, m_psel, m_paddr, m_pwdata, m_penable, m_pready);
end

always @(posedge m_pclk) begin
	if(m_penable)
		m_pready <= 1'b1;
	else
		m_pready <= 1'b0;
end 

endmodule

SPI2APB_Bridge/spi2apb_bridge.v
module spi2apb_bridge #(
						parameter BANK_ADDR		= 	2,
						parameter DATA_WIDTH 	= 	8,
						parameter ADDR_WIDTH	=	3
						)(
                        input 			sclk,
                        input 			resetn,
                        input 			mosi,
                        input 			ss,
                        output 			miso,

                        input		[DATA_WIDTH-1 : 0]		b_prdata,
                        input								b_pready,
                        output								b_pclk,
                        output								b_presetn,
                        output		[DATA_WIDTH-1 : 0]		b_pwdata,
                        output	reg							b_pwrite,
                        output	reg	[BANK_ADDR-1	:	0]	b_psel,
                        output	reg							b_penable,
                        output	reg	[ADDR_WIDTH-1 : 0]		b_paddr
                        );

reg	[15: 0]	reg_mosi;
reg [15: 0]	reg_miso;

reg [3 : 0] counter_spi;
reg	[3 : 0] counter_apb;
reg [BANK_ADDR-1 : 0] reg_psel;
wire en_pwrite;
wire en_paddr;
wire en_psel;
wire en_penable_w;
wire en_penable_r;
reg en_pwdata;
reg en_sclk;
reg off_penable;
//spi interface
always @(posedge sclk or negedge resetn) begin
	if(!resetn) begin
		reg_miso 	<=	'h0;
		reg_mosi	<=	'h0;
        counter_spi	<=  'b00;
	end else begin
		if(!ss) begin
		 	reg_mosi [0] 	<= mosi;
		 	counter_spi 	<= counter_spi + 1'b1;
		end else 
			counter_spi <= 4'b0000;
	end
end

always @(negedge sclk) begin
	if(!ss && (counter_spi != 4'b0000)) begin
		reg_mosi	<= reg_mosi << 1'b1;
		reg_miso	<= reg_miso << 1'b1;
	end
end

assign miso = reg_miso[15];

// apb interface
always @(negedge sclk or negedge resetn or posedge b_pready) begin
	if(!resetn) begin
		b_pwrite <= 1'b0; 
		b_paddr	 <= 7'h0;
		reg_psel  <= 'h0;
	end else begin
			b_pwrite <= (en_pwrite)? reg_mosi[0] : b_pwrite;
			b_paddr	 <= (en_paddr)?  reg_mosi[2:0] : b_paddr;
			reg_psel <=	(en_reg_psel)?  reg_mosi[1:0] : reg_psel;
	end
end

always @(posedge sclk or negedge resetn or negedge b_pready) begin
	if(!resetn) begin
		b_penable <= 1'b0;
		b_psel	  <= 8'h0;
	end else begin 

		if(ss) begin
			b_penable <= (!b_pready)? 1'b0 : b_penable;
			b_psel <= (!b_pready)? 1'b0 : b_penable;
		end else begin 
			b_penable <= (en_penable_w || en_penable_r)?  1'b1 : (off_signal)? 1'b0 : b_penable;
			b_psel	 <= (en_psel_r || en_psel_w)? reg_psel : (off_signal)? 'h0 : b_psel;
		end
	end
end

 reg off_signal;
 wire en_psel_w;
 wire en_psel_r;


always @(posedge sclk or negedge resetn or posedge b_pready) begin
	if(!resetn) begin
		off_signal <= 1'b0;
	end else begin
		off_signal <= (b_pready)? 1'b1 : 1'b0; 
	end
end


assign 	b_pclk			= sclk;
assign	en_pwrite		= (counter_spi == 4'h1)? 1'b1 : 1'b0;
assign  en_paddr		= (counter_spi == 4'h6)? 1'b1 : 1'b0;		
assign  en_prdata		= (counter_spi == 4'h9)? 1'b1 : 1'b0;
assign 	en_reg_psel		= (counter_spi == 4'h3)? 1'b1 : 1'b0;

assign  en_psel_w			= (counter_spi == 4'he && b_pwrite)? 1'b1 : 1'b0;
assign  en_psel_r			= (counter_spi == 4'h6 && !b_pwrite)? 1'b1 : 1'b0;

assign	en_penable_w	= (counter_spi == 4'hf && b_pwrite && !ss)? 1'b1 : 1'b0;
assign	en_penable_r	= ((counter_spi == 4'h7) && !b_pwrite)? 1'b1 : 1'b0;	

assign  b_presetn 	= resetn; 
assign  b_pwdata    = reg_mosi[7:0];


always @(negedge sclk or negedge resetn) begin
	if(!b_pwrite && b_penable)
		reg_miso [15:8] <= b_prdata; 
end


endmodule

SPI2APB_Bridge/bridge_tb.v
`timescale 1ns/1ps
`include "spi2apb_bridge.v"
`include "apb_monitor.v"

module bridge_tb#(
			        parameter BANK_NUM      = 	2,
					parameter DATA_WIDTH 	= 	16,
                 	parameter PDATA_WIDTH 	=  	8,
					parameter ADDR_WIDTH	=	7,
                  	parameter PADDR_WIDTH   = 	3
				)(
				);
reg     clk;
reg     sclk;
reg     resetn;

wire    mosi;
reg     ss;
wire	miso;

wire tb_pclk_a;
wire tb_pclk_b;
wire tb_presetn;
wire tb_pwrite;
wire tb_penable;
wire [BANK_NUM-1   : 0]  tb_psel;
wire [PDATA_WIDTH-1 : 0] tb_pwdata;
wire [PADDR_WIDTH-1 : 0] tb_paddr;
wire [PDATA_WIDTH-1 : 0] tb_prdata;
wire tb_pready;

reg [15:0] reg_mosi_tb;
reg [15:0] reg_miso_tb;

spi2apb_bridge i0(  .sclk(sclk),	        .resetn(resetn),        .mosi(mosi), 	         .miso(miso),		.ss(ss),
                    .b_pready(tb_pready),    .b_pclk(tb_pclk_a),        .b_presetn(tb_presetn),  
                    .b_pwrite(tb_pwrite),    .b_psel(tb_psel),        .b_penable(tb_penable),       
                    .b_pwdata(tb_pwdata),    .b_paddr(tb_paddr),      .b_prdata(tb_prdata));

apb_monitor i1(     .m_pready(tb_pready),    .m_pclk(tb_pclk_a),        .m_presetn(tb_presetn),  
                    .m_pwrite(tb_pwrite),    .m_psel(tb_psel),        .m_penable(tb_penable),       
                    .m_pwdata(tb_pwdata),    .m_paddr(tb_paddr),      .m_prdata(tb_prdata));


function automatic reg [15:0] spi_xfer;
input [DATA_WIDTH-1:0] data_in;
reg [15:0] rd_mosi;
        begin
                reg_mosi_tb = data_in << 1;
                rd_mosi[15:1] = 'h0;
                rd_mosi[0] = miso;
                spi_xfer = rd_mosi;
        end

endfunction

assign mosi = reg_mosi_tb[15];
task write_reg(input [ADDR_WIDTH-1:0] addr, input [PDATA_WIDTH-1:0] data);
integer i;
        begin

             @(posedge clk);
                ss = 0;
                reg_mosi_tb [15] = 1;  
                reg_mosi_tb [14:8] = addr;
                reg_mosi_tb [7:0] = data;  

                for(i = 0; i < 16; i = i + 1) begin
                        @(posedge clk);
                        sclk = !sclk;
                        reg_miso_tb = reg_miso_tb << 1;
                        #10
                        reg_miso_tb =  reg_miso_tb + spi_xfer(reg_mosi_tb);
                        @(posedge clk);
                        sclk = !sclk;
                end
                @(posedge clk);
                ss = 1;
        end
endtask



 
task read_reg(input [ADDR_WIDTH-1:0] addr);
integer i;
        begin

             @(posedge clk);
                ss = 0;
                reg_mosi_tb [15] = 0;  
                reg_mosi_tb [14:8] = addr;
                reg_mosi_tb [7:0] = 'h0;  

                for(i = 0; i < 16; i = i + 1) begin
                        @(posedge clk);
                        sclk = !sclk;
                        reg_miso_tb = reg_miso_tb << 1;
                        #10
                        reg_miso_tb =  reg_miso_tb + spi_xfer(reg_mosi_tb);
                        @(posedge clk);
                        sclk = !sclk;
                end
                @(posedge clk);
                ss = 1;
        end
endtask

initial begin
        clk = 0;
        sclk = 0;
        resetn = 1;
        ss = 1;
        reg_mosi_tb = 16'h0000;
        reg_miso_tb = 16'h0000;
end

initial begin
        $dumpfile("bridge_tb.vcd");
        $dumpvars(0, bridge_tb);
        $display("Module %m") ;
        #3 resetn = 0;
        #3 resetn = 1;
        #100
        $display("Write: ") ;
        write_reg(7'h6c, 8'hf3);
        #100
        $display("Read: ") ;
        read_reg(7'h55);
        #500 $finish;
end


always #10 clk = !clk; 

endmodule

SPI2APB_Bridge/bridge_tb.vcd
$date
	Sun Mar 06 18:39:40 2022
$end
$version
	Icarus Verilog
$end
$timescale
	1ps
$end
$scope module bridge_tb $end
$var wire 1 ! tb_pwrite $end
$var wire 8 " tb_pwdata [7:0] $end
$var wire 2 # tb_psel [1:0] $end
$var wire 1 $ tb_presetn $end
$var wire 1 % tb_pready $end
$var wire 8 & tb_prdata [7:0] $end
$var wire 1 ' tb_penable $end
$var wire 1 ( tb_pclk_a $end
$var wire 3 ) tb_paddr [2:0] $end
$var wire 1 * mosi $end
$var wire 1 + miso $end
$var reg 1 , clk $end
$var reg 16 - reg_miso_tb [15:0] $end
$var reg 16 . reg_mosi_tb [15:0] $end
$var reg 1 / resetn $end
$var reg 1 0 sclk $end
$var reg 1 1 ss $end
$scope function spi_xfer $end
$upscope $end
$scope module i0 $end
$var wire 1 ( b_pclk $end
$var wire 1 $ b_presetn $end
$var wire 1 * mosi $end
$var wire 1 / resetn $end
$var wire 1 0 sclk $end
$var wire 1 1 ss $end
$var wire 1 + miso $end
$var wire 1 2 en_reg_psel $end
$var wire 1 3 en_pwrite $end
$var wire 1 4 en_psel_w $end
$var wire 1 5 en_psel_r $end
$var wire 1 6 en_prdata $end
$var wire 1 7 en_penable_w $end
$var wire 1 8 en_penable_r $end
$var wire 1 9 en_paddr $end
$var wire 8 : b_pwdata [7:0] $end
$var wire 1 % b_pready $end
$var wire 8 ; b_prdata [7:0] $end
$var reg 3 < b_paddr [2:0] $end
$var reg 1 ' b_penable $end
$var reg 2 = b_psel [1:0] $end
$var reg 1 ! b_pwrite $end
$var reg 4 > counter_spi [3:0] $end
$var reg 1 ? off_signal $end
$var reg 16 @ reg_miso [15:0] $end
$var reg 16 A reg_mosi [15:0] $end
$var reg 2 B reg_psel [1:0] $end
$upscope $end
$scope module i1 $end
$var wire 3 C m_paddr [2:0] $end
$var wire 1 ( m_pclk $end
$var wire 1 ' m_penable $end
$var wire 1 $ m_presetn $end
$var wire 2 D m_psel [1:0] $end
$var wire 8 E m_pwdata [7:0] $end
$var wire 1 ! m_pwrite $end
$var wire 8 F m_prdata [7:0] $end
$var reg 1 % m_pready $end
$upscope $end
$scope task read_reg $end
$var reg 7 G addr [6:0] $end
$var integer 32 H i [31:0] $end
$upscope $end
$scope task write_reg $end
$var reg 7 I addr [6:0] $end
$var reg 8 J data [7:0] $end
$var integer 32 K i [31:0] $end
$upscope $end
$upscope $end
$enddefinitions $end
#0
$dumpvars
bx K
bx J
bx I
bx H
bx G
b0 F
bx E
b0 D
bx C
bx B
bx A
bx @
x?
bx >
b0 =
bx <
b0 ;
bx :
x9
x8
07
x6
x5
x4
x3
x2
11
00
1/
b0 .
b0 -
0,
x+
0*
bx )
0(
0'
b0 &
0%
1$
b0 #
bx "
x!
$end
#3000
04
05
08
03
09
06
02
b0 "
b0 :
b0 E
0+
0?
b0 B
b0 )
b0 <
b0 C
0!
b0 >
b0 A
b0 @
0$
0/
#6000
1$
1/
#10000
1,
#20000
0,
#30000
1,
#40000
0,
#50000
1,
#60000
0,
#70000
1,
#80000
0,
#90000
1,
#100000
0,
#106000
b11110011 J
b1101100 I
#110000
1*
b0 K
b1110110011110011 .
01
1,
#120000
0,
#130000
13
b1 "
b1 :
b1 E
b1 >
b1 A
1(
10
1,
#140000
b1101100111100110 .
0,
#150000
b10 "
b10 :
b10 E
1!
b10 A
b1 K
0(
00
1,
#160000
0,
#170000
03
b11 "
b11 :
b11 E
b10 >
b11 A
1(
10
1,
#180000
b1011001111001100 .
0,
#190000
b110 "
b110 :
b110 E
b110 A
b10 K
0(
00
1,
#200000
0,
#210000
12
b111 "
b111 :
b111 E
b11 >
b111 A
1(
10
1,
#220000
0*
b110011110011000 .
0,
#230000
b1110 "
b1110 :
b1110 E
b11 B
b1110 A
b11 K
0(
00
1,
#240000
0,
#250000
02
b100 >
1(
10
1,
#260000
1*
b1100111100110000 .
0,
#270000
b11100 "
b11100 :
b11100 E
b11100 A
b100 K
0(
00
1,
#280000
0,
#290000
b11101 "
b11101 :
b11101 E
b101 >
b11101 A
1(
10
1,
#300000
b1001111001100000 .
0,
#310000
b111010 "
b111010 :
b111010 E
b111010 A
b101 K
0(
00
1,
#320000
0,
#330000
19
b111011 "
b111011 :
b111011 E
b110 >
b111011 A
1(
10
1,
#340000
0*
b11110011000000 .
0,
#350000
b1110110 "
b1110110 :
b1110110 E
b11 )
b11 <
b11 C
b1110110 A
b110 K
0(
00
1,
#360000
0,
#370000
09
b111 >
1(
10
1,
#380000
b111100110000000 .
0,
#390000
b11101100 "
b11101100 :
b11101100 E
b11101100 A
b111 K
0(
00
1,
#400000
0,
#410000
b1000 >
1(
10
1,
#420000
1*
b1111001100000000 .
0,
#430000
b11011000 "
b11011000 :
b11011000 E
b111011000 A
b1000 K
0(
00
1,
#440000
0,
#450000
16
b11011001 "
b11011001 :
b11011001 E
b1001 >
b111011001 A
1(
10
1,
#460000
b1110011000000000 .
0,
#470000
b10110010 "
b10110010 :
b10110010 E
b1110110010 A
b1001 K
0(
00
1,
#480000
0,
#490000
06
b10110011 "
b10110011 :
b10110011 E
b1010 >
b1110110011 A
1(
10
1,
#500000
b1100110000000000 .
0,
#510000
b1100110 "
b1100110 :
b1100110 E
b11101100110 A
b1010 K
0(
00
1,
#520000
0,
#530000
b1100111 "
b1100111 :
b1100111 E
b1011 >
b11101100111 A
1(
10
1,
#540000
b1001100000000000 .
0,
#550000
b11001110 "
b11001110 :
b11001110 E
b111011001110 A
b1011 K
0(
00
1,
#560000
0,
#570000
b11001111 "
b11001111 :
b11001111 E
b1100 >
b111011001111 A
1(
10
1,
#580000
0*
b11000000000000 .
0,
#590000
b10011110 "
b10011110 :
b10011110 E
b1110110011110 A
b1100 K
0(
00
1,
#600000
0,
#610000
b1101 >
1(
10
1,
#620000
b110000000000000 .
0,
#630000
b111100 "
b111100 :
b111100 E
b11101100111100 A
b1101 K
0(
00
1,
#640000
0,
#650000
14
b1110 >
1(
10
1,
#660000
1*
b1100000000000000 .
0,
#670000
b1111000 "
b1111000 :
b1111000 E
b111011001111000 A
b1110 K
0(
00
1,
#680000
0,
#690000
17
04
b1111001 "
b1111001 :
b1111001 E
b11 #
b11 =
b11 D
b1111 >
b111011001111001 A
1(
10
1,
#700000
b1000000000000000 .
0,
#710000
b11110010 "
b11110010 :
b11110010 E
b1110110011110010 A
b1111 K
0(
00
1,
#720000
0,
#730000
1?
07
1%
b11110011 "
b11110011 :
b11110011 E
1'
b0 >
b1110110011110011 A
1(
10
1,
#740000
0*
b0 .
0,
#750000
b10000 K
0(
00
1,
#760000
0,
#770000
b0 #
b0 =
b0 D
0'
11
1,
0%
#780000
0,
#790000
1,
#800000
0,
#810000
1,
#820000
0,
#830000
1,
#840000
0,
#850000
1,
#860000
0,
#870000
b0 H
b101010100000000 .
01
1,
b1010101 G
#880000
0,
#890000
13
b11110010 "
b11110010 :
b11110010 E
0?
b1 >
b1110110011110010 A
1(
10
1,
#900000
1*
b1010101000000000 .
0,
#910000
b11100100 "
b11100100 :
b11100100 E
0!
b1101100111100100 A
b1 H
0(
00
1,
#920000
0,
#930000
03
b11100101 "
b11100101 :
b11100101 E
b10 >
b1101100111100101 A
1(
10
1,
#940000
0*
b101010000000000 .
0,
#950000
b11001010 "
b11001010 :
b11001010 E
b1011001111001010 A
b10 H
0(
00
1,
#960000
0,
#970000
12
b11 >
1(
10
1,
#980000
1*
b1010100000000000 .
0,
#990000
b10010100 "
b10010100 :
b10010100 E
b10 B
b110011110010100 A
b11 H
0(
00
1,
#1000000
0,
#1010000
02
b10010101 "
b10010101 :
b10010101 E
b100 >
b110011110010101 A
1(
10
1,
#1020000
0*
b101000000000000 .
0,
#1030000
b101010 "
b101010 :
b101010 E
b1100111100101010 A
b100 H
0(
00
1,
#1040000
0,
#1050000
b101 >
1(
10
1,
#1060000
1*
b1010000000000000 .
0,
#1070000
b1010100 "
b1010100 :
b1010100 E
b1001111001010100 A
b101 H
0(
00
1,
#1080000
0,
#1090000
15
19
b1010101 "
b1010101 :
b1010101 E
b110 >
b1001111001010101 A
1(
10
1,
#1100000
0*
b100000000000000 .
0,
#1110000
b10101010 "
b10101010 :
b10101010 E
b101 )
b101 <
b101 C
b11110010101010 A
b110 H
0(
00
1,
#1120000
0,
#1130000
05
18
09
b10 #
b10 =
b10 D
b111 >
1(
10
1,
#1140000
1*
b1000000000000000 .
0,
#1150000
b1010100 "
b1010100 :
b1010100 E
b111100101010100 A
b111 H
0(
00
1,
#1160000
0,
#1170000
1?
b11111001 &
b11111001 ;
b11111001 F
08
1%
b1010101 "
b1010101 :
b1010101 E
1'
b1000 >
b111100101010101 A
1(
10
1,
#1180000
0*
b0 .
0,
#1190000
1+
b10101010 "
b10101010 :
b10101010 E
b1111100100000000 @
b1111001010101010 A
b1000 H
0(
00
1,
#1200000
0,
#1210000
b0 &
b0 ;
b0 F
16
0?
b1001 >
b0 #
b0 =
b0 D
0'
1(
10
1,
0%
#1220000
b1 -
0,
#1230000
b1010100 "
b1010100 :
b1010100 E
b1111001000000000 @
b1110010101010100 A
b1001 H
0(
00
1,
#1240000
0,
#1250000
06
b1010 >
b10 -
1(
10
1,
#1260000
b11 -
0,
#1270000
b10101000 "
b10101000 :
b10101000 E
b1110010000000000 @
b1100101010101000 A
b1010 H
0(
00
1,
#1280000
0,
#1290000
b1011 >
b110 -
1(
10
1,
#1300000
b111 -
0,
#1310000
b1010000 "
b1010000 :
b1010000 E
b1100100000000000 @
b1001010101010000 A
b1011 H
0(
00
1,
#1320000
0,
#1330000
b1100 >
b1110 -
1(
10
1,
#1340000
b1111 -
0,
#1350000
b10100000 "
b10100000 :
b10100000 E
b1001000000000000 @
b10101010100000 A
b1100 H
0(
00
1,
#1360000
0,
#1370000
b1101 >
b11110 -
1(
10
1,
#1380000
b11111 -
0,
#1390000
0+
b1000000 "
b1000000 :
b1000000 E
b10000000000000 @
b101010101000000 A
b1101 H
0(
00
1,
#1400000
0,
#1410000
b1110 >
b111110 -
1(
10
1,
#1420000
0,
#1430000
b10000000 "
b10000000 :
b10000000 E
b100000000000000 @
b1010101010000000 A
b1110 H
0(
00
1,
#1440000
0,
#1450000
b1111 >
b1111100 -
1(
10
1,
#1460000
0,
#1470000
1+
b0 "
b0 :
b0 E
b1000000000000000 @
b101010100000000 A
b1111 H
0(
00
1,
#1480000
0,
#1490000
b0 >
b11111000 -
1(
10
1,
#1500000
b11111001 -
0,
#1510000
b10000 H
0(
00
1,
#1520000
0,
#1530000
11
1,
