SPI2APB_Bridge/spi2apb_bridge.v
module spi2apb_bridge #(
						parameter BANK_NUM 		= 	2,
						parameter DATA_WIDTH 	= 	8,
						parameter ADDR_WIDTH	=	3
						)(
                        input 			sclk,
                        input 			resetn,
                        input 			mosi,
                        input 			ss,
                        output 			miso,

                        input		[DATA_WIDTH-1 : 0]		b_prdata,
                        input								b_pready,
                        output								b_pclk,
                        output								b_resetn,
                        output	reg	[DATA_WIDTH-1 : 0]		b_pwdata,
                        output	reg							b_pwrite,
                        output	reg	[BANK_NUM-1	:	0]		b_psel,
                        output	reg							b_penable,
                        output	reg	[ADDR_WIDTH-1 : 0]		b_paddr
                        );

reg	[15: 0]	reg_mosi;
reg [15: 0]	reg_miso;

reg [3 : 0] counter_spi;
reg	[3 : 0] counter_apb;

wire en_pwrite;
wire en_paddr;
wire en_pwdata;
wire en_psel;
wire en_penable;

reg en_sclk;

//spi interface
always @(posedge sclk or negedge resetn) begin
	if(!resetn) begin
		reg_miso 	<=	16'hf001;
		reg_mosi	<=	16'h0000;
        counter_spi	<=  4'b0000;
	end else begin
		if(!ss) begin
		 	reg_mosi [0] 	<= mosi;
		 	counter_spi 	<= counter_spi + 1'b1;
		 	reg_miso		<= reg_miso << 1'b1;
		end else 
			counter_spi <= 4'b0000;
	end
end

always @(negedge sclk) begin
	if(!ss && (counter_spi != 4'b0000)) begin
		reg_mosi	<= reg_mosi << 1'b1;
	end
end

assign miso = reg_miso[15];

assign sclk = b_pclk;

// apb interface
always @(negedge sclk or negedge resetn) begin
	if(!resetn) begin
		b_pwrite <= 1'b0; 
		b_paddr	 <= 7'h0;
		b_pwdata <= 8'h0;
		b_psel	 <= 8'h0;
		b_penable <= 1'b0;
	end else begin
		b_pwrite <= (en_pwrite)? reg_mosi[0] : b_pwrite;
		b_paddr	 <= (en_paddr)?  reg_mosi[2:0] : b_paddr;
		b_pwdata <= (en_pwdata)? reg_mosi[7:0] : b_pwdata;
		b_psel	 <= (en_psel)?	 reg_mosi[BANK_NUM-1:0] : b_psel; 
		b_penable <= (en_penable)?  1'b1 : b_penable;
	end
end


assign	en_pwrite	= (counter_spi == 4'h1)? 1'b1 : 1'b0;
assign  en_paddr	= (counter_spi == 4'h8)? 1'b1 : 1'b0;
assign	en_pwdata	= (counter_spi == 4'h0)? 1'b1 : 1'b0;
assign  en_psel		= (counter_spi == 4'h3)? 1'b1 : 1'b0;	
assign	en_penable	= (counter_spi == 4'hd)? 1'b1 : 1'b0;	//доделать
assign b_resetn = resetn; 


endmodule

SPI2APB_Bridge/spi2apb_bridge_tb.v
`timescale 1ns/1ps
`include "spi2apb_bridge.v"

module spi2apb_bridge_tb#(
			        parameter BANK_NUM      = 	3,
				parameter DATA_WIDTH 	= 	8,
				parameter ADDR_WIDTH	=	7
				)
                                ();
reg     clk;
reg     sclk;
reg     resetn;
reg     mosi;
reg     ss;
wire	miso;

reg b_pready;
wire b_pclk;
wire b_resetn;
wire b_pwrite;
wire b_penable;
wire [BANK_NUM-1   : 0] b_psel;
wire [DATA_WIDTH-1 : 0] b_pwdata;
wire [ADDR_WIDTH-1 : 0] b_paddr;
reg  [DATA_WIDTH-1 : 0] b_prdata;

reg [15:0] reg_mosi_tb;
reg [15:0] reg_miso_tb;

spi2apb_bridge i0(.sclk(sclk), .resetn(resetn), .mosi(mosi), .miso(miso), .ss(ss));

initial begin
        clk = 0;
        sclk = 0;
        resetn = 1;
        ss = 1;
        reg_mosi_tb = 16'h0000;
        reg_miso_tb = 16'h0000;
end

task en_trans(input [15:0] data_mosi);
integer i;
        begin
                @(posedge clk);
                ss = 0;
                reg_mosi_tb = data_mosi;
                mosi = reg_mosi_tb[15];
                reg_miso_tb[0] = miso;

                for(i = 0; i < 16; i = i + 1) begin
                        @(posedge clk);
                        sclk = !sclk;
                        reg_miso_tb = reg_miso_tb << 1'b1;
                        @(posedge clk);
                        reg_mosi_tb = reg_mosi_tb << 1'b1;
                        @(posedge clk);
                        sclk = !sclk;
                        mosi = reg_mosi_tb[15];
                        reg_miso_tb[0] = (i != 15)? miso : reg_miso_tb[0];
                        @(posedge clk);
                end
                @(posedge clk);
                ss = 1;
        end
endtask

initial begin
        $dumpfile("spi2apb_bridge_tb.vcd");
        $dumpvars(0, spi2apb_bridge_tb);
        $display("Module %m") ;
        #3 resetn = 0;
        #3 resetn = 1;
        #100
        en_trans(16'hffff);
       /* #100
        en_trans(16'h1234);
        #100
        en_trans(16'h7645);
        #100
        $display("Test complet");
        */
        #500 $finish;
end

//assign miso = (!ss)? reg_miso_tb[15] : 1'b0;

always #10 clk = !clk; 

endmodule

SPI2APB_Bridge/spi2apb_bridge_tb.vcd
$date
	Thu Mar 03 02:01:56 2022
$end
$version
	Icarus Verilog
$end
$timescale
	1ps
$end
$scope module spi2apb_bridge_tb $end
$var wire 1 ! miso $end
$var reg 1 " clk $end
$var reg 1 # mosi $end
$var reg 16 $ reg_miso_tb [15:0] $end
$var reg 16 % reg_mosi_tb [15:0] $end
$var reg 1 & resetn $end
$var reg 1 ' sclk $end
$var reg 1 ( ss $end
$scope module i0 $end
$var wire 1 ) b_pclk $end
$var wire 8 * b_prdata [7:0] $end
$var wire 1 + b_pready $end
$var wire 1 , b_resetn $end
$var wire 1 # mosi $end
$var wire 1 & resetn $end
$var wire 1 - sclk $end
$var wire 1 ( ss $end
$var wire 1 ! miso $end
$var wire 1 . en_pwrite $end
$var wire 1 / en_pwdata $end
$var wire 1 0 en_psel $end
$var wire 1 1 en_penable $end
$var wire 1 2 en_paddr $end
$var reg 3 3 b_paddr [2:0] $end
$var reg 1 4 b_penable $end
$var reg 2 5 b_psel [1:0] $end
$var reg 8 6 b_pwdata [7:0] $end
$var reg 1 7 b_pwrite $end
$var reg 4 8 counter_spi [3:0] $end
$var reg 16 9 reg_miso [15:0] $end
$var reg 16 : reg_mosi [15:0] $end
$upscope $end
$scope task en_trans $end
$var reg 16 ; data_mosi [15:0] $end
$var integer 32 < i [31:0] $end
$upscope $end
$upscope $end
$enddefinitions $end
#0
$dumpvars
bx <
bx ;
bx :
bx 9
bx 8
x7
bx 6
bx 5
x4
bx 3
x2
x1
x0
x/
x.
0-
1,
z+
bz *
z)
1(
0'
1&
b0 %
b0 $
x#
0"
x!
$end
#3000
0.
02
1/
00
01
1!
04
b0 5
b0 6
b0 3
07
b0 8
b0 :
b1111000000000001 9
0,
0&
#6000
1,
1&
#10000
1"
#20000
0"
#30000
1"
#40000
0"
#50000
1"
#60000
0"
#70000
1"
#80000
0"
#90000
1"
#100000
0"
#106000
b1111111111111111 ;
#110000
b0 <
b1 $
1#
b1111111111111111 %
0(
1"
#120000
0"
#130000
1.
0/
b1110000000000010 9
b1 8
b1 :
b10 $
1-
1'
1"
#140000
0"
#150000
b1111111111111110 %
1"
#160000
0"
#170000
17
b10 :
b11 $
0-
0'
1"
#180000
0"
#190000
b1 <
1"
#200000
0"
#210000
0.
b1100000000000100 9
b10 8
b11 :
b110 $
1-
1'
1"
#220000
0"
#230000
b1111111111111100 %
1"
#240000
0"
#250000
b110 :
b111 $
0-
0'
1"
#260000
0"
#270000
b10 <
1"
#280000
0"
#290000
10
b1000000000001000 9
b11 8
b111 :
b1110 $
1-
1'
1"
#300000
0"
#310000
b1111111111111000 %
1"
#320000
0"
#330000
b11 5
b1110 :
b1111 $
0-
0'
1"
#340000
0"
#350000
b11 <
1"
#360000
0"
#370000
0!
00
b10000 9
b100 8
b1111 :
b11110 $
1-
1'
1"
#380000
0"
#390000
b1111111111110000 %
1"
#400000
0"
#410000
b11110 :
0-
0'
1"
#420000
0"
#430000
b100 <
1"
#440000
0"
#450000
b100000 9
b101 8
b11111 :
b111100 $
1-
1'
1"
#460000
0"
#470000
b1111111111100000 %
1"
#480000
0"
#490000
b111110 :
0-
0'
1"
#500000
0"
#510000
b101 <
1"
#520000
0"
#530000
b1000000 9
b110 8
b111111 :
b1111000 $
1-
1'
1"
#540000
0"
#550000
b1111111111000000 %
1"
#560000
0"
#570000
b1111110 :
0-
0'
1"
#580000
0"
#590000
b110 <
1"
#600000
0"
#610000
b10000000 9
b111 8
b1111111 :
b11110000 $
1-
1'
1"
#620000
0"
#630000
b1111111110000000 %
1"
#640000
0"
#650000
b11111110 :
0-
0'
1"
#660000
0"
#670000
b111 <
1"
#680000
0"
#690000
12
b100000000 9
b1000 8
b11111111 :
b111100000 $
1-
1'
1"
#700000
0"
#710000
b1111111100000000 %
1"
#720000
0"
#730000
b111 3
b111111110 :
0-
0'
1"
#740000
0"
#750000
b1000 <
1"
#760000
0"
#770000
02
b1000000000 9
b1001 8
b111111111 :
b1111000000 $
1-
1'
1"
#780000
0"
#790000
b1111111000000000 %
1"
#800000
0"
#810000
b1111111110 :
0-
0'
1"
#820000
0"
#830000
b1001 <
1"
#840000
0"
#850000
b10000000000 9
b1010 8
b1111111111 :
b11110000000 $
1-
1'
1"
#860000
0"
#870000
b1111110000000000 %
1"
#880000
0"
#890000
b11111111110 :
0-
0'
1"
#900000
0"
#910000
b1010 <
1"
#920000
0"
#930000
b100000000000 9
b1011 8
b11111111111 :
b111100000000 $
1-
1'
1"
#940000
0"
#950000
b1111100000000000 %
1"
#960000
0"
#970000
b111111111110 :
0-
0'
1"
#980000
0"
#990000
b1011 <
1"
#1000000
0"
#1010000
b1000000000000 9
b1100 8
b111111111111 :
b1111000000000 $
1-
1'
1"
#1020000
0"
#1030000
b1111000000000000 %
1"
#1040000
0"
#1050000
b1111111111110 :
0-
0'
1"
#1060000
0"
#1070000
b1100 <
1"
#1080000
0"
#1090000
11
b10000000000000 9
b1101 8
b1111111111111 :
b11110000000000 $
1-
1'
1"
#1100000
0"
#1110000
b1110000000000000 %
1"
#1120000
0"
#1130000
14
b11111111111110 :
0-
0'
1"
#1140000
0"
#1150000
b1101 <
1"
#1160000
0"
#1170000
01
b100000000000000 9
b1110 8
b11111111111111 :
b111100000000000 $
1-
1'
1"
#1180000
0"
#1190000
b1100000000000000 %
1"
#1200000
0"
#1210000
b111111111111110 :
0-
0'
1"
#1220000
0"
#1230000
b1110 <
1"
#1240000
0"
#1250000
1!
b1000000000000000 9
b1111 8
b111111111111111 :
b1111000000000000 $
1-
1'
1"
#1260000
0"
#1270000
b1000000000000000 %
1"
#1280000
0"
#1290000
b1111111111111110 :
b1111000000000001 $
0-
0'
1"
#1300000
0"
#1310000
b1111 <
1"
#1320000
0"
#1330000
0!
1/
b0 9
b0 8
b1111111111111111 :
b1110000000000010 $
1-
1'
1"
#1340000
0"
#1350000
b0 %
1"
#1360000
0"
#1370000
b11111111 6
0#
0-
0'
1"
#1380000
0"
#1390000
b10000 <
1"
#1400000
0"
#1410000
1(
1"
