SPI2APB_Bridge/spi2apb_bridge.v
module spi2apb_bridge #(
						parameter BANK_ADDR		= 	2,
						parameter DATA_WIDTH 	= 	8,
						parameter ADDR_WIDTH	=	3
						)(
                        input 			sclk,
                        input 			resetn,
                        input 			mosi,
                        input 			ss,
                        output 			miso,

                        input		[DATA_WIDTH-1 : 0]		b_prdata,
                        input								b_pready,
                        output								b_pclk,
                        output								b_presetn,
                        output		[DATA_WIDTH-1 : 0]		b_pwdata,
                        output	reg							b_pwrite,
                        output	reg	[BANK_ADDR-1	:	0]	b_psel,
                        output	reg							b_penable,
                        output	reg	[ADDR_WIDTH-1 : 0]		b_paddr
                        );

reg	[15: 0]	reg_mosi;
reg [15: 0]	reg_miso;

reg [3 : 0] counter_spi;
reg	[3 : 0] counter_apb;

wire en_pwrite;
wire en_paddr;
wire en_psel;
wire en_penable_w;
wire en_penable_r;
reg en_pwdata;
reg en_sclk;

//spi interface
always @(posedge sclk or negedge resetn) begin
	if(!resetn) begin
		reg_miso 	<=	16'hdf3f;
		reg_mosi	<=	16'h0000;
        counter_spi	<=  4'b0000;
	end else begin
		if(!ss) begin
		 	reg_mosi [0] 	<= mosi;
		 	counter_spi 	<= counter_spi + 1'b1;
		end else 
			counter_spi <= 4'b0000;
	end
end

always @(negedge sclk) begin
	if(!ss && (counter_spi != 4'b0000)) begin
		reg_mosi	<= reg_mosi << 1'b1;
		reg_miso	<= reg_miso << 1'b1;
	end
end

assign miso = reg_miso[15];

// apb interface
always @(negedge sclk or negedge resetn or posedge b_pready) begin
	if(!resetn) begin
		b_pwrite <= 1'b0; 
		b_paddr	 <= 7'h0;
		b_psel	 <= 8'h0;
	end else begin
		if(b_pready) begin
			b_psel	<= 'b0;
		end else begin
			b_pwrite <= (en_pwrite)? reg_mosi[0] : b_pwrite;
			b_paddr	 <= (en_paddr)?  reg_mosi[2:0] : b_paddr;
			b_psel	 <= (en_psel)?	 reg_mosi[BANK_ADDR-1:0] : b_psel; 
		end
	end
end

always @(posedge sclk or negedge resetn or posedge b_pready) begin
	if(!resetn) begin
		b_penable <= 1'b0;
	end else begin
		if(b_pready) begin
			b_penable <= 1'b0;
		end else begin 
			b_penable <= (en_penable_w || en_penable_r)?  1'b1 : b_penable;
		end
	end
end

assign 	b_pclk			= sclk;
assign	en_pwrite		= (counter_spi == 4'h1)? 1'b1 : 1'b0;
assign  en_paddr		= (counter_spi == 4'h6)? 1'b1 : 1'b0;
assign  en_psel			= (counter_spi == 4'h3)? 1'b1 : 1'b0;		
assign  en_prdata		= (counter_spi == 4'h8)? 1'b1 : 1'b0;

assign	en_penable_w	= ((counter_spi == 4'h0 || counter_spi == 4'hf) && b_pwrite && !ss)? 1'b1 : 1'b0;
assign	en_penable_r	= ((counter_spi == 4'h6 || counter_spi == 4'h7) && !b_pwrite)? 1'b1 : 1'b0;	

assign  b_presetn 	= resetn; 
assign  b_pwdata    = reg_mosi[7:0];

always @(negedge sclk or negedge resetn) begin
	//if(!b_pwrite && counter_spi == 4'h8)
	if(!b_pwrite && b_penable)
		reg_miso [15:8] <= b_prdata; 
end


endmodule

SPI2APB_Bridge/spi2apb_bridge_tb.v
`timescale 1ns/1ps
`include "spi2apb_bridge.v"

module spi2apb_bridge_tb#(
			        parameter BANK_NUM      = 	2,
				parameter DATA_WIDTH 	= 	8,
				parameter ADDR_WIDTH	=	3
				)
                                ();
reg     clk;
reg     sclk;
reg     resetn;
//reg     [DATA_WIDTH-1 : 0] b_reg1;
//reg     [DATA_WIDTH-1 : 0] b_reg2 = 8'hf9;
wire    mosi;
reg     ss;
wire	miso;

reg b_pready;
wire b_pclk;
wire b_presetn;
wire b_pwrite;
wire b_penable;
wire [BANK_NUM-1   : 0] b_psel;
wire [DATA_WIDTH-1 : 0] b_pwdata;
wire [ADDR_WIDTH-1 : 0] b_paddr;
reg  [DATA_WIDTH-1 : 0] b_prdata;

reg [15:0] reg_mosi_tb;
reg [15:0] reg_miso_tb;

spi2apb_bridge i0(      .sclk(sclk),            .resetn(resetn),        .mosi(mosi),            .miso(miso),            .ss(ss),
                        .b_pready(b_pready),    .b_pclk(b_pclk),        .b_presetn(b_presetn),  .b_pwrite(b_pwrite),     .b_penable(b_penable),
                        .b_psel(b_psel),        .b_pwdata(b_pwdata),    .b_paddr(b_paddr),      .b_prdata(b_prdata));


task en_trans(input [15:0] data_mosi, input [7:0] prdata);
integer i;
reg                        rw;
reg     [DATA_WIDTH-1 : 0] tb_reg_pwdata;
reg     [DATA_WIDTH-1 : 0] tb_reg_prdata;

        begin
                tb_reg_pwdata = 'h0;
                tb_reg_prdata = prdata;
                rw = data_mosi[15];
                reg_mosi_tb = data_mosi;
                $display("mosi    = %h", reg_mosi_tb);
                @(posedge clk);
                ss = 0;
                //reg_miso_tb[0] = miso;
                
                for(i = 0; i < 16; i = i + 1) begin
                        @(posedge clk);
                        sclk = !sclk;
                        reg_miso_tb[0] = (i != 16)? miso : reg_miso_tb[0];
                        tb_reg_pwdata = (i == 15 && rw)? b_pwdata : tb_reg_pwdata;
                        b_prdata = (i == 7 && !rw)? tb_reg_prdata : b_prdata;
                        if(rw && i == 15)
                                b_pready = 1'b1;
                        else if(!rw && i == 7)
                               b_pready = 1'b1;
                        else 
                                b_pready = 1'b0;
                        @(posedge clk);
                        @(posedge clk);
                        sclk = !sclk;
                        reg_miso_tb = (i != 15)? reg_miso_tb << 1'b1 : reg_miso_tb;
                        reg_mosi_tb = reg_mosi_tb << 1'b1; 
                        if(i == 15) begin
                                b_pready = 1'b0;
                        end
                        @(posedge clk);
                end
                @(posedge clk);
                ss = 1;

                if(rw)  begin
                        $display($time, " ns");
                        $display("mosi    = %h", reg_mosi_tb);
                        $display("pwrite = %b", b_pwrite);
                        $display("psel = %b", b_psel);
                        $display("paddr = %b", b_paddr);
                        $display("penable = %b", b_penable);
                        $display("pwdata  = %h \n", b_pwdata);
                end else begin
                        $display($time, " ns");
                        $display("miso = %h", reg_miso_tb);
                        $display("pwrite = %b", b_pwrite);
                        $display("psel = %b", b_psel);
                        $display("paddr = %b", b_paddr);
                        $display("penable = %b", b_penable);
                        $display("prdata  = %h \n", b_prdata);
                end

        end
endtask

assign mosi = reg_mosi_tb[15];

initial begin
        clk = 0;
        sclk = 0;
        resetn = 1;
        ss = 1;
        reg_mosi_tb = 16'h0000;
        reg_miso_tb = 16'h0000;
        b_pready    = 1'b0;
        b_prdata    = 'h0;
end

initial begin
        $dumpfile("spi2apb_bridge_tb.vcd");
        $dumpvars(0, spi2apb_bridge_tb);
        $display("Module %m") ;
        #3 resetn = 0;
        #3 resetn = 1;
        #100
        $display("Write: \n");
        en_trans(16'hffff,8'h00);
        #1000
         $display("Read: \n");
        en_trans(16'h55f9, 8'hf9);
       /* #100
        en_trans(16'h1234);
        #100
        en_trans(16'h7645);
        #100
        $display("Test complet");
        */
        #500 $finish;
end

//assign miso = (!ss)? reg_miso_tb[15] : 1'b0;

always #10 clk = !clk; 

endmodule

SPI2APB_Bridge/spi2apb_bridge_tb.vcd
$date
	Sat Mar 05 22:30:10 2022
$end
$version
	Icarus Verilog
$end
$timescale
	1ps
$end
$scope module spi2apb_bridge_tb $end
$var wire 1 ! mosi $end
$var wire 1 " miso $end
$var wire 1 # b_pwrite $end
$var wire 8 $ b_pwdata [7:0] $end
$var wire 2 % b_psel [1:0] $end
$var wire 1 & b_presetn $end
$var wire 1 ' b_penable $end
$var wire 1 ( b_pclk $end
$var wire 3 ) b_paddr [2:0] $end
$var reg 8 * b_prdata [7:0] $end
$var reg 1 + b_pready $end
$var reg 1 , clk $end
$var reg 16 - reg_miso_tb [15:0] $end
$var reg 16 . reg_mosi_tb [15:0] $end
$var reg 1 / resetn $end
$var reg 1 0 sclk $end
$var reg 1 1 ss $end
$scope module i0 $end
$var wire 1 ( b_pclk $end
$var wire 8 2 b_prdata [7:0] $end
$var wire 1 + b_pready $end
$var wire 1 & b_presetn $end
$var wire 1 ! mosi $end
$var wire 1 / resetn $end
$var wire 1 0 sclk $end
$var wire 1 1 ss $end
$var wire 1 " miso $end
$var wire 1 3 en_pwrite $end
$var wire 1 4 en_psel $end
$var wire 1 5 en_prdata $end
$var wire 1 6 en_penable_w $end
$var wire 1 7 en_penable_r $end
$var wire 1 8 en_paddr $end
$var wire 8 9 b_pwdata [7:0] $end
$var reg 3 : b_paddr [2:0] $end
$var reg 1 ' b_penable $end
$var reg 2 ; b_psel [1:0] $end
$var reg 1 # b_pwrite $end
$var reg 4 < counter_spi [3:0] $end
$var reg 16 = reg_miso [15:0] $end
$var reg 16 > reg_mosi [15:0] $end
$upscope $end
$scope task en_trans $end
$var reg 16 ? data_mosi [15:0] $end
$var reg 8 @ prdata [7:0] $end
$var reg 1 A rw $end
$var reg 8 B tb_reg_prdata [7:0] $end
$var reg 8 C tb_reg_pwdata [7:0] $end
$var integer 32 D i [31:0] $end
$upscope $end
$upscope $end
$enddefinitions $end
#0
$dumpvars
bx D
bx C
bx B
xA
bx @
bx ?
bx >
bx =
bx <
bx ;
bx :
bx 9
x8
x7
x6
x5
x4
x3
b0 2
11
00
1/
b0 .
b0 -
0,
0+
b0 *
bx )
0(
0'
1&
bx %
bx $
x#
x"
0!
$end
#3000
07
06
03
08
04
05
b0 $
b0 9
1"
b0 %
b0 ;
b0 )
b0 :
0#
b0 <
b0 >
b1111111111111111 =
0&
0/
#6000
1&
1/
#10000
1,
#20000
0,
#30000
1,
#40000
0,
#50000
1,
#60000
0,
#70000
1,
#80000
0,
#90000
1,
#100000
0,
#106000
1!
b1111111111111111 .
1A
b0 B
b0 C
b0 @
b1111111111111111 ?
#110000
b0 D
01
1,
#120000
0,
#130000
13
b1 $
b1 9
b1 <
b1 >
b1 -
1(
10
1,
#140000
0,
#150000
1,
#160000
0,
#170000
b10 $
b10 9
1#
b1111111111111110 =
b10 >
b1111111111111110 .
b10 -
0(
00
1,
#180000
0,
#190000
b1 D
1,
#200000
0,
#210000
03
b11 $
b11 9
b10 <
b11 >
b11 -
1(
10
1,
#220000
0,
#230000
1,
#240000
0,
#250000
b110 $
b110 9
b1111111111111100 =
b110 >
b1111111111111100 .
b110 -
0(
00
1,
#260000
0,
#270000
b10 D
1,
#280000
0,
#290000
14
b111 $
b111 9
b11 <
b111 >
b111 -
1(
10
1,
#300000
0,
#310000
1,
#320000
0,
#330000
b1110 $
b1110 9
b11 %
b11 ;
b1111111111111000 =
b1110 >
b1111111111111000 .
b1110 -
0(
00
1,
#340000
0,
#350000
b11 D
1,
#360000
0,
#370000
04
b1111 $
b1111 9
b100 <
b1111 >
b1111 -
1(
10
1,
#380000
0,
#390000
1,
#400000
0,
#410000
b11110 $
b11110 9
b1111111111110000 =
b11110 >
b1111111111110000 .
b11110 -
0(
00
1,
#420000
0,
#430000
b100 D
1,
#440000
0,
#450000
b11111 $
b11111 9
b101 <
b11111 >
b11111 -
1(
10
1,
#460000
0,
#470000
1,
#480000
0,
#490000
b111110 $
b111110 9
b1111111111100000 =
b111110 >
b1111111111100000 .
b111110 -
0(
00
1,
#500000
0,
#510000
b101 D
1,
#520000
0,
#530000
18
b111111 $
b111111 9
b110 <
b111111 >
b111111 -
1(
10
1,
#540000
0,
#550000
1,
#560000
0,
#570000
b1111110 $
b1111110 9
b111 )
b111 :
b1111111111000000 =
b1111110 >
b1111111111000000 .
b1111110 -
0(
00
1,
#580000
0,
#590000
b110 D
1,
#600000
0,
#610000
08
b1111111 $
b1111111 9
b111 <
b1111111 >
b1111111 -
1(
10
1,
#620000
0,
#630000
1,
#640000
0,
#650000
b11111110 $
b11111110 9
b1111111110000000 =
b11111110 >
b1111111110000000 .
b11111110 -
0(
00
1,
#660000
0,
#670000
b111 D
1,
#680000
0,
#690000
15
b11111111 $
b11111111 9
b1000 <
b11111111 >
b11111111 -
1(
10
1,
#700000
0,
#710000
1,
#720000
0,
#730000
b11111110 $
b11111110 9
b1111111100000000 =
b111111110 >
b1111111100000000 .
b111111110 -
0(
00
1,
#740000
0,
#750000
b1000 D
1,
#760000
0,
#770000
05
b11111111 $
b11111111 9
b1001 <
b111111111 >
b111111111 -
1(
10
1,
#780000
0,
#790000
1,
#800000
0,
#810000
b11111110 $
b11111110 9
b1111111000000000 =
b1111111110 >
b1111111000000000 .
b1111111110 -
0(
00
1,
#820000
0,
#830000
b1001 D
1,
#840000
0,
#850000
b11111111 $
b11111111 9
b1010 <
b1111111111 >
b1111111111 -
1(
10
1,
#860000
0,
#870000
1,
#880000
0,
#890000
b11111110 $
b11111110 9
b1111110000000000 =
b11111111110 >
b1111110000000000 .
b11111111110 -
0(
00
1,
#900000
0,
#910000
b1010 D
1,
#920000
0,
#930000
b11111111 $
b11111111 9
b1011 <
b11111111111 >
b11111111111 -
1(
10
1,
#940000
0,
#950000
1,
#960000
0,
#970000
b11111110 $
b11111110 9
b1111100000000000 =
b111111111110 >
b1111100000000000 .
b111111111110 -
0(
00
1,
#980000
0,
#990000
b1011 D
1,
#1000000
0,
#1010000
b11111111 $
b11111111 9
b1100 <
b111111111111 >
b111111111111 -
1(
10
1,
#1020000
0,
#1030000
1,
#1040000
0,
#1050000
b11111110 $
b11111110 9
b1111000000000000 =
b1111111111110 >
b1111000000000000 .
b1111111111110 -
0(
00
1,
#1060000
0,
#1070000
b1100 D
1,
#1080000
0,
#1090000
b11111111 $
b11111111 9
b1101 <
b1111111111111 >
b1111111111111 -
1(
10
1,
#1100000
0,
#1110000
1,
#1120000
0,
#1130000
b11111110 $
b11111110 9
b1110000000000000 =
b11111111111110 >
b1110000000000000 .
b11111111111110 -
0(
00
1,
#1140000
0,
#1150000
b1101 D
1,
#1160000
0,
#1170000
b11111111 $
b11111111 9
b1110 <
b11111111111111 >
b11111111111111 -
1(
10
1,
#1180000
0,
#1190000
1,
#1200000
0,
#1210000
b11111110 $
b11111110 9
b1100000000000000 =
b111111111111110 >
b1100000000000000 .
b111111111111110 -
0(
00
1,
#1220000
0,
#1230000
b1110 D
1,
#1240000
0,
#1250000
16
b11111111 $
b11111111 9
b1111 <
b111111111111111 >
b111111111111111 -
1(
10
1,
#1260000
0,
#1270000
1,
#1280000
0,
#1290000
b11111110 $
b11111110 9
b1000000000000000 =
b1111111111111110 >
b1000000000000000 .
b1111111111111110 -
0(
00
1,
#1300000
0,
#1310000
b1111 D
1,
#1320000
0,
#1330000
b11111111 $
b11111111 9
b0 %
b0 ;
1'
b0 <
b1111111111111111 >
1+
b11111110 C
b1111111111111111 -
1(
10
1,
#1340000
0,
#1350000
1,
#1360000
0,
#1370000
0'
0!
0+
b0 .
0(
00
1,
#1380000
0,
#1390000
b10000 D
1,
#1400000
0,
#1410000
11
1,
