SPI2APB_Bridge/spi2apb_bridge.v
module spi2apb_bridge(
                        input 			sclk,
                        input 			resetn,
                        input 			mosi,
                        input 			ss,
                        output 			miso,

                        input			b_prdata,
                        input			b_pready,
                        output			b_pclk,
                        output			b_resetn,
                        output			b_pwdata,
                        output			b_pwrite,
                        output			b_psel,
                        output			b_penable,
                        output			b_paddr
                        );

reg	[15: 0]	reg_mosi;
reg [15: 0]	reg_miso;
reg [3 : 0] counter;

always @(posedge sclk or negedge resetn) begin
	if(!resetn) begin
		reg_miso 	<=	16'hffff;
		reg_mosi	<=	16'h0000;
        counter     <=  4'b0000;
	end else begin
		if(!ss) begin
		 	reg_mosi [15] 	<= mosi;
		 	counter 		<= counter + 1'b1;
		 	//reg_mosi	<= reg_mosi >> 1'b1;
		 	reg_miso	<= reg_miso << 1'b1;
		end else 
			counter <= 4'b0000;
	end
end

always @(negedge sclk) begin
	if(!ss && (counter != 4'b0000)) begin
		reg_mosi	<= reg_mosi >> 1'b1;
	end
end

assign miso = reg_miso[15];

endmodule

SPI2APB_Bridge/spi2apb_bridge_tb.v
`timescale 1ns/1ps
`include "spi2apb_bridge.v"

module spi2apb_bridge_tb();
reg     clk;
reg     sclk;
reg     resetn;
reg     mosi;
reg     ss;
wire	miso;

reg [15:0] reg_mosi_tb;
reg [15:0] reg_miso_tb;

spi2apb_bridge i0(.sclk(sclk), .resetn(resetn), .mosi(mosi), .miso(miso), .ss(ss));

initial begin
        clk = 0;
        sclk = 0;
        resetn = 1;
        ss = 1;
        reg_mosi_tb = 16'hffff;
        reg_miso_tb = 16'h0000;
end

task en_transmit(); 
integer i;
        begin
                @(posedge clk);
                ss = 0;
                reg_mosi_tb = 16'hffff;

                mosi = reg_mosi_tb[0];
                reg_miso_tb [15] = miso;

                for(i = 0; i < 32; i = i + 1) begin
                        @(posedge clk);
                        sclk = !sclk;
                        if(!sclk) begin 
                            reg_mosi_tb = reg_mosi_tb >> 1'b1;
                            mosi = reg_mosi_tb[0];
                            reg_miso_tb [15] = (i < 30)? miso : reg_miso_tb [15];
                        end
                        @(posedge clk);
                        if(i < 30)
                                reg_miso_tb = (sclk)? (reg_miso_tb >> 1'b1) : reg_miso_tb;
                end

                @(posedge clk);
                ss = 1;
        end
endtask


initial begin
        $dumpfile("spi2apb_bridge_tb.vcd");
        $dumpvars(0, spi2apb_bridge_tb);
        $display("Module %m") ;
        #3 resetn = 0;
        #3 resetn = 1;
        en_transmit();
        $display("Test complet");
        #100 $finish;
end

always #10 clk = !clk; 

endmodule

SPI2APB_Bridge/spi2apb_bridge_tb.vcd
$date
	Wed Mar 02 11:47:28 2022
$end
$version
	Icarus Verilog
$end
$timescale
	1ps
$end
$scope module spi2apb_bridge_tb $end
$var wire 1 ! miso $end
$var reg 1 " clk $end
$var reg 1 # mosi $end
$var reg 16 $ reg_miso_tb [15:0] $end
$var reg 16 % reg_mosi_tb [15:0] $end
$var reg 1 & resetn $end
$var reg 1 ' sclk $end
$var reg 1 ( ss $end
$scope module i0 $end
$var wire 1 ) b_paddr $end
$var wire 1 * b_pclk $end
$var wire 1 + b_penable $end
$var wire 1 , b_prdata $end
$var wire 1 - b_pready $end
$var wire 1 . b_psel $end
$var wire 1 / b_pwdata $end
$var wire 1 0 b_pwrite $end
$var wire 1 1 b_resetn $end
$var wire 1 # mosi $end
$var wire 1 & resetn $end
$var wire 1 ' sclk $end
$var wire 1 ( ss $end
$var wire 1 ! miso $end
$var reg 4 2 counter [3:0] $end
$var reg 16 3 reg_miso [15:0] $end
$var reg 16 4 reg_mosi [15:0] $end
$upscope $end
$scope task en_transmit $end
$var integer 32 5 i [31:0] $end
$upscope $end
$upscope $end
$enddefinitions $end
#0
$dumpvars
bx 5
bx 4
bx 3
bx 2
z1
z0
z/
z.
z-
z,
z+
z*
z)
1(
0'
1&
b1111111111111111 %
b0 $
x#
0"
x!
$end
#3000
1!
b0 2
b0 4
b1111111111111111 3
0&
#6000
1&
#10000
b0 5
b1000000000000000 $
1#
0(
1"
#20000
0"
#30000
b1111111111111110 3
b1 2
b1000000000000000 4
1'
1"
#40000
0"
#50000
b1 5
b100000000000000 $
1"
#60000
0"
#70000
b100000000000000 4
b1100000000000000 $
b111111111111111 %
0'
1"
#80000
0"
#90000
b10 5
1"
#100000
0"
#110000
b1111111111111100 3
b10 2
b1100000000000000 4
1'
1"
#120000
0"
#130000
b11 5
b110000000000000 $
1"
#140000
0"
#150000
b110000000000000 4
b1110000000000000 $
b11111111111111 %
0'
1"
#160000
0"
#170000
b100 5
1"
#180000
0"
#190000
b1111111111111000 3
b11 2
b1110000000000000 4
1'
1"
#200000
0"
#210000
b101 5
b111000000000000 $
1"
#220000
0"
#230000
b111000000000000 4
b1111000000000000 $
b1111111111111 %
0'
1"
#240000
0"
#250000
b110 5
1"
#260000
0"
#270000
b1111111111110000 3
b100 2
b1111000000000000 4
1'
1"
#280000
0"
#290000
b111 5
b111100000000000 $
1"
#300000
0"
#310000
b111100000000000 4
b1111100000000000 $
b111111111111 %
0'
1"
#320000
0"
#330000
b1000 5
1"
#340000
0"
#350000
b1111111111100000 3
b101 2
b1111100000000000 4
1'
1"
#360000
0"
#370000
b1001 5
b111110000000000 $
1"
#380000
0"
#390000
b111110000000000 4
b1111110000000000 $
b11111111111 %
0'
1"
#400000
0"
#410000
b1010 5
1"
#420000
0"
#430000
b1111111111000000 3
b110 2
b1111110000000000 4
1'
1"
#440000
0"
#450000
b1011 5
b111111000000000 $
1"
#460000
0"
#470000
b111111000000000 4
b1111111000000000 $
b1111111111 %
0'
1"
#480000
0"
#490000
b1100 5
1"
#500000
0"
#510000
b1111111110000000 3
b111 2
b1111111000000000 4
1'
1"
#520000
0"
#530000
b1101 5
b111111100000000 $
1"
#540000
0"
#550000
b111111100000000 4
b1111111100000000 $
b111111111 %
0'
1"
#560000
0"
#570000
b1110 5
1"
#580000
0"
#590000
b1111111100000000 3
b1000 2
b1111111100000000 4
1'
1"
#600000
0"
#610000
b1111 5
b111111110000000 $
1"
#620000
0"
#630000
b111111110000000 4
b1111111110000000 $
b11111111 %
0'
1"
#640000
0"
#650000
b10000 5
1"
#660000
0"
#670000
b1111111000000000 3
b1001 2
b1111111110000000 4
1'
1"
#680000
0"
#690000
b10001 5
b111111111000000 $
1"
#700000
0"
#710000
b111111111000000 4
b1111111111000000 $
b1111111 %
0'
1"
#720000
0"
#730000
b10010 5
1"
#740000
0"
#750000
b1111110000000000 3
b1010 2
b1111111111000000 4
1'
1"
#760000
0"
#770000
b10011 5
b111111111100000 $
1"
#780000
0"
#790000
b111111111100000 4
b1111111111100000 $
b111111 %
0'
1"
#800000
0"
#810000
b10100 5
1"
#820000
0"
#830000
b1111100000000000 3
b1011 2
b1111111111100000 4
1'
1"
#840000
0"
#850000
b10101 5
b111111111110000 $
1"
#860000
0"
#870000
b111111111110000 4
b1111111111110000 $
b11111 %
0'
1"
#880000
0"
#890000
b10110 5
1"
#900000
0"
#910000
b1111000000000000 3
b1100 2
b1111111111110000 4
1'
1"
#920000
0"
#930000
b10111 5
b111111111111000 $
1"
#940000
0"
#950000
b111111111111000 4
b1111111111111000 $
b1111 %
0'
1"
#960000
0"
#970000
b11000 5
1"
#980000
0"
#990000
b1110000000000000 3
b1101 2
b1111111111111000 4
1'
1"
#1000000
0"
#1010000
b11001 5
b111111111111100 $
1"
#1020000
0"
#1030000
b111111111111100 4
b1111111111111100 $
b111 %
0'
1"
#1040000
0"
#1050000
b11010 5
1"
#1060000
0"
#1070000
b1100000000000000 3
b1110 2
b1111111111111100 4
1'
1"
#1080000
0"
#1090000
b11011 5
b111111111111110 $
1"
#1100000
0"
#1110000
b111111111111110 4
b1111111111111110 $
b11 %
0'
1"
#1120000
0"
#1130000
b11100 5
1"
#1140000
0"
#1150000
b1000000000000000 3
b1111 2
b1111111111111110 4
1'
1"
#1160000
0"
#1170000
b11101 5
b111111111111111 $
1"
#1180000
0"
#1190000
b111111111111111 4
b1111111111111111 $
b1 %
0'
1"
#1200000
0"
#1210000
b11110 5
1"
#1220000
0"
#1230000
0!
b0 3
b0 2
b1111111111111111 4
1'
1"
#1240000
0"
#1250000
b11111 5
1"
#1260000
0"
#1270000
0#
b0 %
0'
1"
#1280000
0"
#1290000
b100000 5
1"
#1300000
0"
#1310000
1(
1"
