SPI2APB_Bridge/spi2apb_bridge.v
module spi2apb_bridge(
                        input 			sclk,
                        input 			resetn,
                        input 			mosi,
                        input 			ss,
                        output 			miso,

                        input			b_prdata,
                        input			b_pready,
                        output			b_pclk,
                        output			b_resetn,
                        output			b_pwdata,
                        output			b_pwrite,
                        output			b_psel,
                        output			b_penable,
                        output			b_paddr
                        );

reg	[15: 0]	reg_mosi;
reg [15: 0]	reg_miso;
reg [3 : 0] counter;

always @(posedge sclk or negedge resetn) begin
	if(!resetn) begin
		reg_miso 	<=	16'hffff;
		reg_mosi	<=	16'h0000;
        counter     <=  4'b0000;
	end else begin
		if(!ss) begin
		 	reg_mosi [15] 	<= mosi;
		 	counter 		<= counter + 1'b1;
		 	//reg_mosi	<= reg_mosi >> 1'b1;
		 	reg_miso	<= reg_miso << 1'b1;
		end else 
			counter <= 4'b0000;
	end
end

always @(negedge sclk) begin
	if(!ss && (counter != 4'b0000)) begin
		reg_mosi	<= reg_mosi >> 1'b1;
	end
end

assign miso = reg_miso[15];

endmodule

SPI2APB_Bridge/spi2apb_bridge_tb.v
`timescale 1ns/1ps
`include "spi2apb_bridge.v"

module spi2apb_bridge_tb();
reg     clk;
reg     sclk;
reg     resetn;
reg     mosi;
reg     ss;
wire	miso;

reg [15:0] reg_mosi_tb;
reg [15:0] reg_miso_tb;

spi2apb_bridge i0(.sclk(sclk), .resetn(resetn), .mosi(mosi), .miso(miso), .ss(ss));

initial begin
        clk = 0;
        sclk = 0;
        resetn = 1;
        ss = 1;
        reg_mosi_tb = 16'h0000;
        reg_miso_tb = 16'h0000;
end

task en_trans(input [15:0] data_mosi);
integer i;
        begin
                @(posedge clk);
                ss = 0;
                reg_mosi_tb = data_mosi;
                mosi = reg_mosi_tb[15];
                reg_miso_tb[0] = miso;

                for(i = 0; i < 16; i = i + 1) begin
                        @(posedge clk);
                        sclk = !sclk;
                        reg_miso_tb = reg_miso_tb << 1'b1;
                        @(posedge clk);
                        reg_mosi_tb = reg_mosi_tb << 1'b1;
                        @(posedge clk);
                        sclk = !sclk;
                        mosi = reg_mosi_tb[15];
                        reg_miso_tb[0] = (i != 15)? miso : reg_miso_tb[0];
                        @(posedge clk);
                end
                @(posedge clk);
                ss = 1;
        end
endtask

initial begin
        $dumpfile("spi2apb_bridge_tb.vcd");
        $dumpvars(0, spi2apb_bridge_tb);
        $display("Module %m") ;
        #3 resetn = 0;
        #3 resetn = 1;
        #100
        en_trans(16'hfcfc);
        #100
        en_trans(16'h1234);
        #100
        en_trans(16'h7645);
        #100
        $display("Test complet");
        #100 $finish;
end

//assign miso = (!ss)? reg_miso_tb[15] : 1'b0;

always #10 clk = !clk; 

endmodule

SPI2APB_Bridge/spi2apb_bridge_tb.vcd
$date
	Wed Mar 02 16:07:43 2022
$end
$version
	Icarus Verilog
$end
$timescale
	1ps
$end
$scope module spi2apb_bridge_tb $end
$var wire 1 ! miso $end
$var reg 1 " clk $end
$var reg 1 # mosi $end
$var reg 16 $ reg_miso_tb [15:0] $end
$var reg 16 % reg_mosi_tb [15:0] $end
$var reg 1 & resetn $end
$var reg 1 ' sclk $end
$var reg 1 ( ss $end
$scope module i0 $end
$var wire 1 ) b_paddr $end
$var wire 1 * b_pclk $end
$var wire 1 + b_penable $end
$var wire 1 , b_prdata $end
$var wire 1 - b_pready $end
$var wire 1 . b_psel $end
$var wire 1 / b_pwdata $end
$var wire 1 0 b_pwrite $end
$var wire 1 1 b_resetn $end
$var wire 1 # mosi $end
$var wire 1 & resetn $end
$var wire 1 ' sclk $end
$var wire 1 ( ss $end
$var wire 1 ! miso $end
$var reg 4 2 counter [3:0] $end
$var reg 16 3 reg_miso [15:0] $end
$var reg 16 4 reg_mosi [15:0] $end
$upscope $end
$scope task en_transmit $end
$var integer 32 5 i [31:0] $end
$upscope $end
$scope task en_transmit2 $end
$var reg 16 6 data_mosi [15:0] $end
$var integer 32 7 i [31:0] $end
$upscope $end
$upscope $end
$enddefinitions $end
#0
$dumpvars
bx 7
bx 6
bx 5
bx 4
bx 3
bx 2
z1
z0
z/
z.
z-
z,
z+
z*
z)
1(
0'
1&
b0 %
b0 $
x#
0"
x!
$end
#3000
1!
b0 2
b0 4
b1111000000000001 3
0&
#6000
1&
#10000
1"
#20000
0"
#30000
1"
#40000
0"
#50000
1"
#60000
0"
#70000
1"
#80000
0"
#90000
1"
#100000
0"
#106000
b1111110011111100 6
#110000
b0 7
b1 $
1#
b1111110011111100 %
0(
1"
#120000
0"
#130000
b1110000000000010 3
b1 2
b1 4
b10 $
1'
1"
#140000
0"
#150000
b1111100111111000 %
1"
#160000
0"
#170000
b10 4
b11 $
0'
1"
#180000
0"
#190000
b1 7
1"
#200000
0"
#210000
b1100000000000100 3
b10 2
b11 4
b110 $
1'
1"
#220000
0"
#230000
b1111001111110000 %
1"
#240000
0"
#250000
b110 4
b111 $
0'
1"
#260000
0"
#270000
b10 7
1"
#280000
0"
#290000
b1000000000001000 3
b11 2
b111 4
b1110 $
1'
1"
#300000
0"
#310000
b1110011111100000 %
1"
#320000
0"
#330000
b1110 4
b1111 $
0'
1"
#340000
0"
#350000
b11 7
1"
#360000
0"
#370000
0!
b10000 3
b100 2
b1111 4
b11110 $
1'
1"
#380000
0"
#390000
b1100111111000000 %
1"
#400000
0"
#410000
b11110 4
0'
1"
#420000
0"
#430000
b100 7
1"
#440000
0"
#450000
b100000 3
b101 2
b11111 4
b111100 $
1'
1"
#460000
0"
#470000
b1001111110000000 %
1"
#480000
0"
#490000
b111110 4
0'
1"
#500000
0"
#510000
b101 7
1"
#520000
0"
#530000
b1000000 3
b110 2
b111111 4
b1111000 $
1'
1"
#540000
0"
#550000
b11111100000000 %
1"
#560000
0"
#570000
b1111110 4
0#
0'
1"
#580000
0"
#590000
b110 7
1"
#600000
0"
#610000
b10000000 3
b111 2
b11110000 $
1'
1"
#620000
0"
#630000
b111111000000000 %
1"
#640000
0"
#650000
b11111100 4
0'
1"
#660000
0"
#670000
b111 7
1"
#680000
0"
#690000
b100000000 3
b1000 2
b111100000 $
1'
1"
#700000
0"
#710000
b1111110000000000 %
1"
#720000
0"
#730000
b111111000 4
1#
0'
1"
#740000
0"
#750000
b1000 7
1"
#760000
0"
#770000
b1000000000 3
b1001 2
b111111001 4
b1111000000 $
1'
1"
#780000
0"
#790000
b1111100000000000 %
1"
#800000
0"
#810000
b1111110010 4
0'
1"
#820000
0"
#830000
b1001 7
1"
#840000
0"
#850000
b10000000000 3
b1010 2
b1111110011 4
b11110000000 $
1'
1"
#860000
0"
#870000
b1111000000000000 %
1"
#880000
0"
#890000
b11111100110 4
0'
1"
#900000
0"
#910000
b1010 7
1"
#920000
0"
#930000
b100000000000 3
b1011 2
b11111100111 4
b111100000000 $
1'
1"
#940000
0"
#950000
b1110000000000000 %
1"
#960000
0"
#970000
b111111001110 4
0'
1"
#980000
0"
#990000
b1011 7
1"
#1000000
0"
#1010000
b1000000000000 3
b1100 2
b111111001111 4
b1111000000000 $
1'
1"
#1020000
0"
#1030000
b1100000000000000 %
1"
#1040000
0"
#1050000
b1111110011110 4
0'
1"
#1060000
0"
#1070000
b1100 7
1"
#1080000
0"
#1090000
b10000000000000 3
b1101 2
b1111110011111 4
b11110000000000 $
1'
1"
#1100000
0"
#1110000
b1000000000000000 %
1"
#1120000
0"
#1130000
b11111100111110 4
0'
1"
#1140000
0"
#1150000
b1101 7
1"
#1160000
0"
#1170000
b100000000000000 3
b1110 2
b11111100111111 4
b111100000000000 $
1'
1"
#1180000
0"
#1190000
b0 %
1"
#1200000
0"
#1210000
b111111001111110 4
0#
0'
1"
#1220000
0"
#1230000
b1110 7
1"
#1240000
0"
#1250000
1!
b1000000000000000 3
b1111 2
b1111000000000000 $
1'
1"
#1260000
0"
#1270000
1"
#1280000
0"
#1290000
b1111110011111100 4
b1111000000000001 $
0'
1"
#1300000
0"
#1310000
b1111 7
1"
#1320000
0"
#1330000
0!
b0 3
b0 2
b1110000000000010 $
1'
1"
#1340000
0"
#1350000
1"
#1360000
0"
#1370000
0'
1"
#1380000
0"
#1390000
b10000 7
1"
#1400000
0"
#1410000
1(
1"
#1420000
0"
#1430000
1"
#1440000
0"
#1450000
1"
#1460000
0"
#1470000
1"
#1480000
0"
#1490000
1"
#1500000
0"
#1510000
b0 7
b1001000110100 %
0(
1"
b1001000110100 6
#1520000
0"
#1530000
b1 2
b1100000000000100 $
1'
1"
#1540000
0"
#1550000
b10010001101000 %
1"
#1560000
0"
#1570000
b1111100111111000 4
0'
1"
#1580000
0"
#1590000
b1 7
1"
#1600000
0"
#1610000
b10 2
b1000000000001000 $
1'
1"
#1620000
0"
#1630000
b100100011010000 %
1"
#1640000
0"
#1650000
b1111001111110000 4
0'
1"
#1660000
0"
#1670000
b10 7
1"
#1680000
0"
#1690000
b11 2
b10000 $
1'
1"
#1700000
0"
#1710000
b1001000110100000 %
1"
#1720000
0"
#1730000
b1110011111100000 4
1#
0'
1"
#1740000
0"
#1750000
b11 7
1"
#1760000
0"
#1770000
b100 2
b1110011111100001 4
b100000 $
1'
1"
#1780000
0"
#1790000
b10001101000000 %
1"
#1800000
0"
#1810000
b1100111111000010 4
0#
0'
1"
#1820000
0"
#1830000
b100 7
1"
#1840000
0"
#1850000
b101 2
b1000000 $
1'
1"
#1860000
0"
#1870000
b100011010000000 %
1"
#1880000
0"
#1890000
b1001111110000100 4
0'
1"
#1900000
0"
#1910000
b101 7
1"
#1920000
0"
#1930000
b110 2
b10000000 $
1'
1"
#1940000
0"
#1950000
b1000110100000000 %
1"
#1960000
0"
#1970000
b11111100001000 4
1#
0'
1"
#1980000
0"
#1990000
b110 7
1"
#2000000
0"
#2010000
b111 2
b11111100001001 4
b100000000 $
1'
1"
#2020000
0"
#2030000
b1101000000000 %
1"
#2040000
0"
#2050000
b111111000010010 4
0#
0'
1"
#2060000
0"
#2070000
b111 7
1"
#2080000
0"
#2090000
b1000 2
b1000000000 $
1'
1"
#2100000
0"
#2110000
b11010000000000 %
1"
#2120000
0"
#2130000
b1111110000100100 4
0'
1"
#2140000
0"
#2150000
b1000 7
1"
#2160000
0"
#2170000
b1001 2
b10000000000 $
1'
1"
#2180000
0"
#2190000
b110100000000000 %
1"
#2200000
0"
#2210000
b1111100001001000 4
0'
1"
#2220000
0"
#2230000
b1001 7
1"
#2240000
0"
#2250000
b1010 2
b100000000000 $
1'
1"
#2260000
0"
#2270000
b1101000000000000 %
1"
#2280000
0"
#2290000
b1111000010010000 4
1#
0'
1"
#2300000
0"
#2310000
b1010 7
1"
#2320000
0"
#2330000
b1011 2
b1111000010010001 4
b1000000000000 $
1'
1"
#2340000
0"
#2350000
b1010000000000000 %
1"
#2360000
0"
#2370000
b1110000100100010 4
0'
1"
#2380000
0"
#2390000
b1011 7
1"
#2400000
0"
#2410000
b1100 2
b1110000100100011 4
b10000000000000 $
1'
1"
#2420000
0"
#2430000
b100000000000000 %
1"
#2440000
0"
#2450000
b1100001001000110 4
0#
0'
1"
#2460000
0"
#2470000
b1100 7
1"
#2480000
0"
#2490000
b1101 2
b100000000000000 $
1'
1"
#2500000
0"
#2510000
b1000000000000000 %
1"
#2520000
0"
#2530000
b1000010010001100 4
1#
0'
1"
#2540000
0"
#2550000
b1101 7
1"
#2560000
0"
#2570000
b1110 2
b1000010010001101 4
b1000000000000000 $
1'
1"
#2580000
0"
#2590000
b0 %
1"
#2600000
0"
#2610000
b100100011010 4
0#
0'
1"
#2620000
0"
#2630000
b1110 7
1"
#2640000
0"
#2650000
b1111 2
b0 $
1'
1"
#2660000
0"
#2670000
1"
#2680000
0"
#2690000
b1001000110100 4
0'
1"
#2700000
0"
#2710000
b1111 7
1"
#2720000
0"
#2730000
b0 2
1'
1"
#2740000
0"
#2750000
1"
#2760000
0"
#2770000
0'
1"
#2780000
0"
#2790000
b10000 7
1"
#2800000
0"
#2810000
1(
1"
#2820000
0"
#2830000
1"
#2840000
0"
#2850000
1"
#2860000
0"
#2870000
1"
#2880000
0"
#2890000
1"
#2900000
0"
#2910000
b0 7
b111011001000101 %
0(
1"
b111011001000101 6
#2920000
0"
#2930000
b1 2
1'
1"
#2940000
0"
#2950000
b1110110010001010 %
1"
#2960000
0"
#2970000
b10010001101000 4
1#
0'
1"
#2980000
0"
#2990000
b1 7
1"
#3000000
0"
#3010000
b10 2
b10010001101001 4
1'
1"
#3020000
0"
#3030000
b1101100100010100 %
1"
#3040000
0"
#3050000
b100100011010010 4
0'
1"
#3060000
0"
#3070000
b10 7
1"
#3080000
0"
#3090000
b11 2
b100100011010011 4
1'
1"
#3100000
0"
#3110000
b1011001000101000 %
1"
#3120000
0"
#3130000
b1001000110100110 4
0'
1"
#3140000
0"
#3150000
b11 7
1"
#3160000
0"
#3170000
b100 2
b1001000110100111 4
1'
1"
#3180000
0"
#3190000
b110010001010000 %
1"
#3200000
0"
#3210000
b10001101001110 4
0#
0'
1"
#3220000
0"
#3230000
b100 7
1"
#3240000
0"
#3250000
b101 2
1'
1"
#3260000
0"
#3270000
b1100100010100000 %
1"
#3280000
0"
#3290000
b100011010011100 4
1#
0'
1"
#3300000
0"
#3310000
b101 7
1"
#3320000
0"
#3330000
b110 2
b100011010011101 4
1'
1"
#3340000
0"
#3350000
b1001000101000000 %
1"
#3360000
0"
#3370000
b1000110100111010 4
0'
1"
#3380000
0"
#3390000
b110 7
1"
#3400000
0"
#3410000
b111 2
b1000110100111011 4
1'
1"
#3420000
0"
#3430000
b10001010000000 %
1"
#3440000
0"
#3450000
b1101001110110 4
0#
0'
1"
#3460000
0"
#3470000
b111 7
1"
#3480000
0"
#3490000
b1000 2
1'
1"
#3500000
0"
#3510000
b100010100000000 %
1"
#3520000
0"
#3530000
b11010011101100 4
0'
1"
#3540000
0"
#3550000
b1000 7
1"
#3560000
0"
#3570000
b1001 2
1'
1"
#3580000
0"
#3590000
b1000101000000000 %
1"
#3600000
0"
#3610000
b110100111011000 4
1#
0'
1"
#3620000
0"
#3630000
b1001 7
1"
#3640000
0"
#3650000
b1010 2
b110100111011001 4
1'
1"
#3660000
0"
#3670000
b1010000000000 %
1"
#3680000
0"
#3690000
b1101001110110010 4
0#
0'
1"
#3700000
0"
#3710000
b1010 7
1"
#3720000
0"
#3730000
b1011 2
1'
1"
#3740000
0"
#3750000
b10100000000000 %
1"
#3760000
0"
#3770000
b1010011101100100 4
0'
1"
#3780000
0"
#3790000
b1011 7
1"
#3800000
0"
#3810000
b1100 2
1'
1"
#3820000
0"
#3830000
b101000000000000 %
1"
#3840000
0"
#3850000
b100111011001000 4
0'
1"
#3860000
0"
#3870000
b1100 7
1"
#3880000
0"
#3890000
b1101 2
1'
1"
#3900000
0"
#3910000
b1010000000000000 %
1"
#3920000
0"
#3930000
b1001110110010000 4
1#
0'
1"
#3940000
0"
#3950000
b1101 7
1"
#3960000
0"
#3970000
b1110 2
b1001110110010001 4
1'
1"
#3980000
0"
#3990000
b100000000000000 %
1"
#4000000
0"
#4010000
b11101100100010 4
0#
0'
1"
#4020000
0"
#4030000
b1110 7
1"
#4040000
0"
#4050000
b1111 2
1'
1"
#4060000
0"
#4070000
b1000000000000000 %
1"
#4080000
0"
#4090000
b111011001000100 4
1#
0'
1"
#4100000
0"
#4110000
b1111 7
1"
#4120000
0"
#4130000
b0 2
b111011001000101 4
1'
1"
#4140000
0"
#4150000
b0 %
1"
#4160000
0"
#4170000
0#
0'
1"
#4180000
0"
#4190000
b10000 7
1"
#4200000
0"
#4210000
1(
1"
