SPI2APB_Bridge/spi2apb_bridge.v
module spi2apb_bridge #(
						parameter BANK_NUM 		= 	3,
						parameter DATA_WIDTH 	= 	8,
						parameter ADDR_WIDTH	=	7
						)(
                        input 			sclk,
                        input 			resetn,
                        input 			mosi,
                        input 			ss,
                        output 			miso,

                        input		[DATA_WIDTH-1 : 0]		b_prdata,
                        input								b_pready,
                        output								b_pclk,
                        output								b_resetn,
                        output		[DATA_WIDTH-1 : 0]		b_pwdata,
                        output	reg							b_pwrite,
                        output		[BANK_NUM-1	:	0]		b_psel,
                        output								b_penable,
                        output		[ADDR_WIDTH-1 : 0]		b_paddr
                        );

reg	[15: 0]	reg_mosi;
reg [15: 0]	reg_miso;

reg [3 : 0] counter_spi;
reg	[3 : 0] counter_apb;

//spi interface
always @(posedge sclk or negedge resetn) begin
	if(!resetn) begin
		reg_miso 	<=	16'hf001;
		reg_mosi	<=	16'h0000;
        counter_spi	<=  4'b0000;
	end else begin
		if(!ss) begin
		 	reg_mosi [0] 	<= mosi;
		 	counter_spi 	<= counter_spi + 1'b1;
		 	reg_miso		<= reg_miso << 1'b1;
		end else 
			counter_spi <= 4'b0000;
	end
end

always @(negedge sclk) begin
	if(!ss && (counter_spi != 4'b0000)) begin
		reg_mosi	<= reg_mosi << 1'b1;
	end
end

assign miso = reg_miso[15];

assign sclk = b_pclk;

assign trans_apb = ((counter_spi == 4'b1111) || b_pready)? !trans_apb : 1'b0;


// apb interface
always @(posedge sclk or negedge resetn) begin
	if(!resetn) begin
		b_pwrite <= 1'b0; 
	end else begin
		b_pwrite <= (en_pwrite)? reg_mosi[0] : b_pwrite;
	end
end

assign	en_pwrite	= (counter_spi == 4'b0001)? 1'b1 : 1'b0;

/*
always @(posedge sclk or negedge resetn) begin
	if(resetn) begin
		counter_apb <= 4'b0000;
	end else begin
		if(trans_apb) begin
			counter_apb <= counter_apb + 1'b1; 
		end
	end
end


assign	b_paddr		= (counter_apb == 4'b0001)? reg_mosi[10:8] : 8'h00;
assign	b_psel		= (counter_apb == 4'b0001)? reg_mosi[14:12] : 2'b00;
assign	b_pwdata	= (counter_apb == 4'b0001 && reg_mosi[15])? reg_mosi[7:0] : 8'h00;
assign	b_penable	= (counter_apb == 4'b0010)? 1'b1 : 1'b0;
*/

endmodule

SPI2APB_Bridge/spi2apb_bridge_tb.v
`timescale 1ns/1ps
`include "spi2apb_bridge.v"

module spi2apb_bridge_tb#(
			        parameter BANK_NUM      = 	3,
				parameter DATA_WIDTH 	= 	8,
				parameter ADDR_WIDTH	=	7
				)
                                ();
reg     clk;
reg     sclk;
reg     resetn;
reg     mosi;
reg     ss;
wire	miso;

reg b_pready;
wire b_pclk;
wire b_resetn;
wire b_pwrite;
wire b_penable;
wire [BANK_NUM-1   : 0] b_psel;
wire [DATA_WIDTH-1 : 0] b_pwdata;
wire [ADDR_WIDTH-1 : 0] b_paddr;
reg  [DATA_WIDTH-1 : 0] b_prdata;

reg [15:0] reg_mosi_tb;
reg [15:0] reg_miso_tb;

spi2apb_bridge i0(.sclk(sclk), .resetn(resetn), .mosi(mosi), .miso(miso), .ss(ss));

initial begin
        clk = 0;
        sclk = 0;
        resetn = 1;
        ss = 1;
        reg_mosi_tb = 16'h0000;
        reg_miso_tb = 16'h0000;
end

task en_trans(input [15:0] data_mosi);
integer i;
        begin
                @(posedge clk);
                ss = 0;
                reg_mosi_tb = data_mosi;
                mosi = reg_mosi_tb[15];
                reg_miso_tb[0] = miso;

                for(i = 0; i < 16; i = i + 1) begin
                        @(posedge clk);
                        sclk = !sclk;
                        reg_miso_tb = reg_miso_tb << 1'b1;
                        @(posedge clk);
                        reg_mosi_tb = reg_mosi_tb << 1'b1;
                        @(posedge clk);
                        sclk = !sclk;
                        mosi = reg_mosi_tb[15];
                        reg_miso_tb[0] = (i != 15)? miso : reg_miso_tb[0];
                        @(posedge clk);
                end
                @(posedge clk);
                ss = 1;
        end
endtask

initial begin
        $dumpfile("spi2apb_bridge_tb.vcd");
        $dumpvars(0, spi2apb_bridge_tb);
        $display("Module %m") ;
        #3 resetn = 0;
        #3 resetn = 1;
        #100
        en_trans(16'hffff);
        #100
        en_trans(16'h1234);
        #100
        en_trans(16'h7645);
        #100
        $display("Test complet");
        #100 $finish;
end

//assign miso = (!ss)? reg_miso_tb[15] : 1'b0;

always #10 clk = !clk; 

endmodule

SPI2APB_Bridge/spi2apb_bridge_tb.vcd
$date
	Wed Mar 02 22:10:30 2022
$end
$version
	Icarus Verilog
$end
$timescale
	1ps
$end
$scope module spi2apb_bridge_tb $end
$var wire 1 ! miso $end
$var reg 1 " clk $end
$var reg 1 # mosi $end
$var reg 16 $ reg_miso_tb [15:0] $end
$var reg 16 % reg_mosi_tb [15:0] $end
$var reg 1 & resetn $end
$var reg 1 ' sclk $end
$var reg 1 ( ss $end
$scope module i0 $end
$var wire 7 ) b_paddr [6:0] $end
$var wire 1 * b_pclk $end
$var wire 1 + b_penable $end
$var wire 8 , b_prdata [7:0] $end
$var wire 1 - b_pready $end
$var wire 3 . b_psel [2:0] $end
$var wire 8 / b_pwdata [7:0] $end
$var wire 1 0 b_resetn $end
$var wire 1 # mosi $end
$var wire 1 & resetn $end
$var wire 1 1 sclk $end
$var wire 1 ( ss $end
$var wire 1 2 trans_apb $end
$var wire 1 ! miso $end
$var reg 1 3 b_pwrite $end
$var reg 4 4 counter_spi [3:0] $end
$var reg 16 5 reg_miso [15:0] $end
$var reg 16 6 reg_mosi [15:0] $end
$upscope $end
$scope task en_trans $end
$var reg 16 7 data_mosi [15:0] $end
$var integer 32 8 i [31:0] $end
$upscope $end
$upscope $end
$enddefinitions $end
#0
$dumpvars
bx 8
bx 7
bx 6
bx 5
bx 4
x3
x2
01
z0
bz /
bz .
z-
bz ,
z+
z*
bz )
1(
0'
1&
b0 %
b0 $
x#
0"
x!
$end
#3000
1!
b0 4
b0 6
b1111000000000001 5
03
0&
#6000
1&
#10000
1"
#20000
0"
#30000
1"
#40000
0"
#50000
1"
#60000
0"
#70000
1"
#80000
0"
#90000
1"
#100000
0"
#106000
b1111111111111111 7
#110000
b0 8
b1 $
1#
b1111111111111111 %
0(
1"
#120000
0"
#130000
b1110000000000010 5
b1 4
b1 6
b10 $
11
1'
1"
#140000
0"
#150000
b1111111111111110 %
1"
#160000
0"
#170000
b10 6
b11 $
01
0'
1"
#180000
0"
#190000
b1 8
1"
#200000
0"
#210000
b1100000000000100 5
b10 4
b11 6
b110 $
11
1'
1"
#220000
0"
#230000
b1111111111111100 %
1"
#240000
0"
#250000
b110 6
b111 $
01
0'
1"
#260000
0"
#270000
b10 8
1"
#280000
0"
#290000
b1000000000001000 5
b11 4
b111 6
b1110 $
11
1'
1"
#300000
0"
#310000
b1111111111111000 %
1"
#320000
0"
#330000
b1110 6
b1111 $
01
0'
1"
#340000
0"
#350000
b11 8
1"
#360000
0"
#370000
0!
b10000 5
b100 4
b1111 6
b11110 $
11
1'
1"
#380000
0"
#390000
b1111111111110000 %
1"
#400000
0"
#410000
b11110 6
01
0'
1"
#420000
0"
#430000
b100 8
1"
#440000
0"
#450000
b100000 5
b101 4
b11111 6
b111100 $
11
1'
1"
#460000
0"
#470000
b1111111111100000 %
1"
#480000
0"
#490000
b111110 6
01
0'
1"
#500000
0"
#510000
b101 8
1"
#520000
0"
#530000
b1000000 5
b110 4
b111111 6
b1111000 $
11
1'
1"
#540000
0"
#550000
b1111111111000000 %
1"
#560000
0"
#570000
b1111110 6
01
0'
1"
#580000
0"
#590000
b110 8
1"
#600000
0"
#610000
b10000000 5
b111 4
b1111111 6
b11110000 $
11
1'
1"
#620000
0"
#630000
b1111111110000000 %
1"
#640000
0"
#650000
b11111110 6
01
0'
1"
#660000
0"
#670000
b111 8
1"
#680000
0"
#690000
b100000000 5
b1000 4
b11111111 6
b111100000 $
11
1'
1"
#700000
0"
#710000
b1111111100000000 %
1"
#720000
0"
#730000
b111111110 6
01
0'
1"
#740000
0"
#750000
b1000 8
1"
#760000
0"
#770000
b1000000000 5
b1001 4
b111111111 6
b1111000000 $
11
1'
1"
#780000
0"
#790000
b1111111000000000 %
1"
#800000
0"
#810000
b1111111110 6
01
0'
1"
#820000
0"
#830000
b1001 8
1"
#840000
0"
#850000
b10000000000 5
b1010 4
b1111111111 6
b11110000000 $
11
1'
1"
#860000
0"
#870000
b1111110000000000 %
1"
#880000
0"
#890000
b11111111110 6
01
0'
1"
#900000
0"
#910000
b1010 8
1"
#920000
0"
#930000
b100000000000 5
b1011 4
b11111111111 6
b111100000000 $
11
1'
1"
#940000
0"
#950000
b1111100000000000 %
1"
#960000
0"
#970000
b111111111110 6
01
0'
1"
#980000
0"
#990000
b1011 8
1"
#1000000
0"
#1010000
b1000000000000 5
b1100 4
b111111111111 6
b1111000000000 $
11
1'
1"
#1020000
0"
#1030000
b1111000000000000 %
1"
#1040000
0"
#1050000
b1111111111110 6
01
0'
1"
#1060000
0"
#1070000
b1100 8
1"
#1080000
0"
#1090000
b10000000000000 5
b1101 4
b1111111111111 6
b11110000000000 $
11
1'
1"
#1100000
0"
#1110000
b1110000000000000 %
1"
#1120000
0"
#1130000
b11111111111110 6
01
0'
1"
#1140000
0"
#1150000
b1101 8
1"
#1160000
0"
#1170000
b100000000000000 5
b1110 4
b11111111111111 6
b111100000000000 $
11
1'
1"
#1180000
0"
#1190000
b1100000000000000 %
1"
#1200000
0"
#1210000
b111111111111110 6
01
0'
1"
#1220000
0"
#1230000
b1110 8
1"
#1240000
0"
#1250000
1!
b1000000000000000 5
b1111 4
b111111111111111 6
b1111000000000000 $
11
1'
1"
#1260000
0"
#1270000
b1000000000000000 %
1"
#1280000
0"
#1290000
b1111111111111110 6
b1111000000000001 $
01
0'
1"
#1300000
0"
#1310000
b1111 8
1"
#1320000
0"
#1330000
0!
b0 5
b0 4
b1111111111111111 6
b1110000000000010 $
11
1'
1"
#1340000
0"
#1350000
b0 %
1"
#1360000
0"
#1370000
0#
01
0'
1"
#1380000
0"
#1390000
b10000 8
1"
#1400000
0"
#1410000
1(
1"
#1420000
0"
#1430000
1"
#1440000
0"
#1450000
1"
#1460000
0"
#1470000
1"
#1480000
0"
#1490000
1"
#1500000
0"
#1510000
b0 8
b1001000110100 %
0(
1"
b1001000110100 7
#1520000
0"
#1530000
b1 4
b1111111111111110 6
b1100000000000100 $
11
1'
1"
#1540000
0"
#1550000
b10010001101000 %
1"
#1560000
0"
#1570000
b1111111111111100 6
01
0'
1"
#1580000
0"
#1590000
b1 8
1"
#1600000
0"
#1610000
b10 4
b1000000000001000 $
11
1'
1"
#1620000
0"
#1630000
b100100011010000 %
1"
#1640000
0"
#1650000
b1111111111111000 6
01
0'
1"
#1660000
0"
#1670000
b10 8
1"
#1680000
0"
#1690000
b11 4
b10000 $
11
1'
1"
#1700000
0"
#1710000
b1001000110100000 %
1"
#1720000
0"
#1730000
b1111111111110000 6
1#
01
0'
1"
#1740000
0"
#1750000
b11 8
1"
#1760000
0"
#1770000
b100 4
b1111111111110001 6
b100000 $
11
1'
1"
#1780000
0"
#1790000
b10001101000000 %
1"
#1800000
0"
#1810000
b1111111111100010 6
0#
01
0'
1"
#1820000
0"
#1830000
b100 8
1"
#1840000
0"
#1850000
b101 4
b1000000 $
11
1'
1"
#1860000
0"
#1870000
b100011010000000 %
1"
#1880000
0"
#1890000
b1111111111000100 6
01
0'
1"
#1900000
0"
#1910000
b101 8
1"
#1920000
0"
#1930000
b110 4
b10000000 $
11
1'
1"
#1940000
0"
#1950000
b1000110100000000 %
1"
#1960000
0"
#1970000
b1111111110001000 6
1#
01
0'
1"
#1980000
0"
#1990000
b110 8
1"
#2000000
0"
#2010000
b111 4
b1111111110001001 6
b100000000 $
11
1'
1"
#2020000
0"
#2030000
b1101000000000 %
1"
#2040000
0"
#2050000
b1111111100010010 6
0#
01
0'
1"
#2060000
0"
#2070000
b111 8
1"
#2080000
0"
#2090000
b1000 4
b1000000000 $
11
1'
1"
#2100000
0"
#2110000
b11010000000000 %
1"
#2120000
0"
#2130000
b1111111000100100 6
01
0'
1"
#2140000
0"
#2150000
b1000 8
1"
#2160000
0"
#2170000
b1001 4
b10000000000 $
11
1'
1"
#2180000
0"
#2190000
b110100000000000 %
1"
#2200000
0"
#2210000
b1111110001001000 6
01
0'
1"
#2220000
0"
#2230000
b1001 8
1"
#2240000
0"
#2250000
b1010 4
b100000000000 $
11
1'
1"
#2260000
0"
#2270000
b1101000000000000 %
1"
#2280000
0"
#2290000
b1111100010010000 6
1#
01
0'
1"
#2300000
0"
#2310000
b1010 8
1"
#2320000
0"
#2330000
b1011 4
b1111100010010001 6
b1000000000000 $
11
1'
1"
#2340000
0"
#2350000
b1010000000000000 %
1"
#2360000
0"
#2370000
b1111000100100010 6
01
0'
1"
#2380000
0"
#2390000
b1011 8
1"
#2400000
0"
#2410000
b1100 4
b1111000100100011 6
b10000000000000 $
11
1'
1"
#2420000
0"
#2430000
b100000000000000 %
1"
#2440000
0"
#2450000
b1110001001000110 6
0#
01
0'
1"
#2460000
0"
#2470000
b1100 8
1"
#2480000
0"
#2490000
b1101 4
b100000000000000 $
11
1'
1"
#2500000
0"
#2510000
b1000000000000000 %
1"
#2520000
0"
#2530000
b1100010010001100 6
1#
01
0'
1"
#2540000
0"
#2550000
b1101 8
1"
#2560000
0"
#2570000
b1110 4
b1100010010001101 6
b1000000000000000 $
11
1'
1"
#2580000
0"
#2590000
b0 %
1"
#2600000
0"
#2610000
b1000100100011010 6
0#
01
0'
1"
#2620000
0"
#2630000
b1110 8
1"
#2640000
0"
#2650000
b1111 4
b0 $
11
1'
1"
#2660000
0"
#2670000
1"
#2680000
0"
#2690000
b1001000110100 6
01
0'
1"
#2700000
0"
#2710000
b1111 8
1"
#2720000
0"
#2730000
b0 4
11
1'
1"
#2740000
0"
#2750000
1"
#2760000
0"
#2770000
01
0'
1"
#2780000
0"
#2790000
b10000 8
1"
#2800000
0"
#2810000
1(
1"
#2820000
0"
#2830000
1"
#2840000
0"
#2850000
1"
#2860000
0"
#2870000
1"
#2880000
0"
#2890000
1"
#2900000
0"
#2910000
b0 8
b111011001000101 %
0(
1"
b111011001000101 7
#2920000
0"
#2930000
b1 4
11
1'
1"
#2940000
0"
#2950000
b1110110010001010 %
1"
#2960000
0"
#2970000
b10010001101000 6
1#
01
0'
1"
#2980000
0"
#2990000
b1 8
1"
#3000000
0"
#3010000
b10 4
b10010001101001 6
11
1'
1"
#3020000
0"
#3030000
b1101100100010100 %
1"
#3040000
0"
#3050000
b100100011010010 6
01
0'
1"
#3060000
0"
#3070000
b10 8
1"
#3080000
0"
#3090000
b11 4
b100100011010011 6
11
1'
1"
#3100000
0"
#3110000
b1011001000101000 %
1"
#3120000
0"
#3130000
b1001000110100110 6
01
0'
1"
#3140000
0"
#3150000
b11 8
1"
#3160000
0"
#3170000
b100 4
b1001000110100111 6
11
1'
1"
#3180000
0"
#3190000
b110010001010000 %
1"
#3200000
0"
#3210000
b10001101001110 6
0#
01
0'
1"
#3220000
0"
#3230000
b100 8
1"
#3240000
0"
#3250000
b101 4
11
1'
1"
#3260000
0"
#3270000
b1100100010100000 %
1"
#3280000
0"
#3290000
b100011010011100 6
1#
01
0'
1"
#3300000
0"
#3310000
b101 8
1"
#3320000
0"
#3330000
b110 4
b100011010011101 6
11
1'
1"
#3340000
0"
#3350000
b1001000101000000 %
1"
#3360000
0"
#3370000
b1000110100111010 6
01
0'
1"
#3380000
0"
#3390000
b110 8
1"
#3400000
0"
#3410000
b111 4
b1000110100111011 6
11
1'
1"
#3420000
0"
#3430000
b10001010000000 %
1"
#3440000
0"
#3450000
b1101001110110 6
0#
01
0'
1"
#3460000
0"
#3470000
b111 8
1"
#3480000
0"
#3490000
b1000 4
11
1'
1"
#3500000
0"
#3510000
b100010100000000 %
1"
#3520000
0"
#3530000
b11010011101100 6
01
0'
1"
#3540000
0"
#3550000
b1000 8
1"
#3560000
0"
#3570000
b1001 4
11
1'
1"
#3580000
0"
#3590000
b1000101000000000 %
1"
#3600000
0"
#3610000
b110100111011000 6
1#
01
0'
1"
#3620000
0"
#3630000
b1001 8
1"
#3640000
0"
#3650000
b1010 4
b110100111011001 6
11
1'
1"
#3660000
0"
#3670000
b1010000000000 %
1"
#3680000
0"
#3690000
b1101001110110010 6
0#
01
0'
1"
#3700000
0"
#3710000
b1010 8
1"
#3720000
0"
#3730000
b1011 4
11
1'
1"
#3740000
0"
#3750000
b10100000000000 %
1"
#3760000
0"
#3770000
b1010011101100100 6
01
0'
1"
#3780000
0"
#3790000
b1011 8
1"
#3800000
0"
#3810000
b1100 4
11
1'
1"
#3820000
0"
#3830000
b101000000000000 %
1"
#3840000
0"
#3850000
b100111011001000 6
01
0'
1"
#3860000
0"
#3870000
b1100 8
1"
#3880000
0"
#3890000
b1101 4
11
1'
1"
#3900000
0"
#3910000
b1010000000000000 %
1"
#3920000
0"
#3930000
b1001110110010000 6
1#
01
0'
1"
#3940000
0"
#3950000
b1101 8
1"
#3960000
0"
#3970000
b1110 4
b1001110110010001 6
11
1'
1"
#3980000
0"
#3990000
b100000000000000 %
1"
#4000000
0"
#4010000
b11101100100010 6
0#
01
0'
1"
#4020000
0"
#4030000
b1110 8
1"
#4040000
0"
#4050000
b1111 4
11
1'
1"
#4060000
0"
#4070000
b1000000000000000 %
1"
#4080000
0"
#4090000
b111011001000100 6
1#
01
0'
1"
#4100000
0"
#4110000
b1111 8
1"
#4120000
0"
#4130000
b0 4
b111011001000101 6
11
1'
1"
#4140000
0"
#4150000
b0 %
1"
#4160000
0"
#4170000
0#
01
0'
1"
#4180000
0"
#4190000
b10000 8
1"
#4200000
0"
#4210000
1(
1"
