GPIO_Expander/gpio_pad.v
module gpio_pad(
				inout 	pad,	
				input 	a,
				input	oe,				//driver enable signal
				input	pu,				//enabling the built-in resistive power pull-up
				input	pd,				//enabling the built-in resistive pull-up to ground
				output	y				//receiver output
				);			

assign (pull0, pull1) pad = (oe)? a : 1'bz;
assign (weak1, weak0) pad = (pu)? 1'b1 : 1'bz;
assign (weak1, weak0) pad = (pd)? 1'b0 : 1'bz;
assign y = pad;

endmodule

GPIO_Expander/gbas.v
 module gbas#(
				parameter DATA_WIDTH = 8,
				parameter ADDR_WIDTH = 3,
				parameter PREADY_DEL = 0
				)(
				input 							pclk,
				input 							presetn,
				input 		[ADDR_WIDTH-1 : 0]	paddr,
				input 							pwrite,
				input 							pselx,
				input 							penable,
				input 		[DATA_WIDTH-1 : 0]	pwdata,
				output  reg	[DATA_WIDTH-1 : 0]	prdata,
				output 							pready,

				input		[7 : 0]            	y,
				output		[7 : 0]            	oe,
				output		[7 : 0]            	pu,
				output		[7 : 0]            	pd,
				output		[7 : 0]            	a
				);

reg [7:0] reg_oe;
reg [7:0] reg_pu;
reg [7:0] reg_pd;
reg [7:0] reg_a;
reg [7:0] reg_y;


reg 	[1:0] 	 counter;
wire 	[7:0]	 wire_y;
wire 			 r_counter_en;
wire 			 w_counter_en;
reg 			 pready_reg;
wire 			 write_en;
wire 			 read_en;

assign write_en = 	 pwrite & pselx;
assign read_en	=	!pwrite & pselx;

always @(posedge pclk or negedge presetn) begin
	if(!presetn) begin
		reg_oe	<= 8'h00;
		reg_pd	<= 8'h00;
		reg_pu	<= 8'h00;
		reg_a	<= 8'h00;
	end 
	else begin
		if(write_en & pready) begin
			case (paddr)
				8'h00 : reg_oe	<= pwdata;
				8'h01 : reg_pu	<= pwdata;
				8'h02 : reg_pd	<= pwdata;
				8'h03 : reg_a 	<= pwdata;
			endcase
		end
	end
end

always @(*) begin
	if(read_en & penable & pready) begin
		case (paddr)
			8'h00 : prdata <= reg_oe;
			8'h01 : prdata <= reg_pu;
			8'h02 : prdata <= reg_pd;
			8'h03 : prdata <= reg_a;
			8'h04 : prdata <= reg_y;
			default : prdata <= 8'h00;
		endcase
	end else 
		prdata <= 8'h00;
end

always @(posedge pclk or negedge presetn) begin
	if(!presetn) begin
		counter <= 2'b0;
		pready_reg <= 1'b0;
	end else begin
		if(read_en || write_en) begin
			pready_reg <= (PREADY_DEL == 0)? 1'b1 : (counter == PREADY_DEL)? 1'b1 : 1'b0;
			counter <= (pready_reg)? 2'b00 : counter + 1'b1;
		end else 
			pready_reg <= 1'b0; 
	end
end

always @(posedge pclk or  negedge presetn) begin
	if(!presetn)
		reg_y <= 1'b0;
	else 
		reg_y <= y;
end

assign pready = ((read_en && penable) || (write_en && penable))? pready_reg : 1'b0;

assign oe = reg_oe;
assign pu = reg_pu;
assign pd = reg_pd;
assign a  = reg_a;

endmodule

GPIO_Expander/spi2apb_bridge.v
module spi2apb_bridge #(
						parameter BANK_ADDR		= 	2,
						parameter DATA_WIDTH 	= 	8,
						parameter ADDR_WIDTH	=	3
						)(
                        input 			sclk,
                        input 			resetn,
                        input 			mosi,
                        input 			ss,
                        output 			miso,

                        input		[DATA_WIDTH-1 : 0]		b_prdata,
                        input								b_pready,
                        output								b_pclk,
                        output								b_presetn,
                        output	reg	[DATA_WIDTH-1 : 0]		b_pwdata,
                        output	reg							b_pwrite,
                        output		[BANK_ADDR-1	:	0]	b_psel,
                        output								b_penable,
                        output	reg	[ADDR_WIDTH-1 : 0]		b_paddr
                        );

reg	[15: 0]	reg_mosi;
reg [15: 0]	reg_miso;

reg [3 : 0] counter_spi;
reg	[3 : 0] counter_apb;
reg [BANK_ADDR-1 : 0] reg_psel;
wire en_pwrite;
wire en_paddr;
wire en_psel;
wire en_penable_w;
wire en_penable_r;
wire en_psel_w;
wire en_psel_r;
reg off_signal;
wire en_pwdata;
reg en_sclk;
reg off_penable;
reg start;

//spi interface
always @(posedge sclk or negedge resetn) begin
	if(!resetn) begin
		reg_mosi	<=	'h0;
        counter_spi	<=  'b00;
	end else begin
		if(!ss) begin
		 	reg_mosi [0] 	<= mosi;
		 	counter_spi 	<= counter_spi + 1'b1;
		end else 
			counter_spi <= 4'b0000;
	end
end

always @(negedge sclk or negedge resetn) begin
	if(!resetn) begin
		reg_miso 	<=	'h0;
	end else begin
		if(!ss && (counter_spi != 4'b0000)) begin
		reg_mosi	<= reg_mosi << 1'b1;
		reg_miso	<= reg_miso << 1'b1;
		end
	end
end

assign miso = reg_miso[15];

// apb interface
always @(negedge sclk or negedge resetn or posedge b_pready) begin
	if(!resetn) begin
		b_pwrite <= 1'b0; 
		b_paddr	 <= 7'h0;
		reg_psel  <= 'h0;
	end else begin
			b_pwrite <= (en_pwrite)? reg_mosi[0] : b_pwrite;
			b_paddr	 <= (en_paddr)?  reg_mosi[2:0] : b_paddr;
			reg_psel <=	(en_reg_psel)?  reg_mosi[1:0] : reg_psel;
	end
end


always @(posedge sclk or negedge resetn or posedge b_pready) begin
	if(!resetn) begin
		off_signal <= 1'b0;
	end else begin
		off_signal <= (b_pready)? 1'b1 : 1'b0; 
	end
end


assign 	b_pclk			= sclk;
assign	en_pwrite		= (counter_spi == 4'h1)? 1'b1 : 1'b0;
assign  en_paddr		= (counter_spi == 4'h6)? 1'b1 : 1'b0;		
assign  en_prdata		= (counter_spi == 4'h9)? 1'b1 : 1'b0;
assign 	en_reg_psel		= (counter_spi == 4'h3)? 1'b1 : 1'b0;

assign  en_psel_w			= ((counter_spi == 4'hf || counter_spi == 4'h0) && b_pwrite && !ss)? 1'b1 : 1'b0;
assign  en_psel_r			= ((counter_spi == 4'h7 || counter_spi == 4'h8) && !b_pwrite)? 1'b1 : 1'b0;

assign	en_penable_w	= (counter_spi == 4'h0 && b_pwrite && !ss)? 1'b1 : 1'b0;
assign	en_penable_r	= ((counter_spi == 4'h8) && !b_pwrite)? 1'b1 : 1'b0;	

assign  b_presetn 	= resetn; 
assign  en_pwdata    = (counter_spi == 4'h0 && !ss)? 1'b1 : 1'b0;

assign b_psel = (en_psel_w & start)? reg_psel : (en_psel_r)? reg_psel : 'b0;
assign b_penable = (b_pwrite & start)? en_penable_w : en_penable_r;

always @(posedge sclk or negedge resetn or posedge ss) begin
	if(~resetn) begin
		start <= 'b0;
	end else begin
		if(!ss)
			start <= (counter_spi == 4'h1)? 1'b1 : start;
		else 
			start <= 1'b0;
	end
end

always @(*) begin
	if(b_pwrite) 
		b_pwdata <= (en_pwdata)? reg_mosi[7:0] : b_pwdata;
	else
		b_pwdata <= 'h0;
end

always @(negedge sclk) begin
	if(!b_pwrite && b_penable)
		reg_miso [15:8] <= b_prdata; 
end


endmodule

GPIO_Expander/gpio_expander.v
`include "gpio_pad.v"
`include "gbas.v"
`include "spi2apb_bridge.v"

module gpio_expander#(
						parameter BANK_NUM = 2,
						parameter ADDR_WIDTH = 7,
						parameter PADDR_WIDTH = 3,
						parameter DATA_WIDTH = 8
						)(
						input	sclk,
						input	resetn,
						output	miso,
						input	mosi,
						input	ss,
						
						output [15:0]	pad );

wire 						e_pclk	;
wire 						e_presetn  	;
wire	[PADDR_WIDTH-1:0]	e_paddr  	;
wire 						e_pwrite  	;
wire 	[1:0]	 			e_psel 	 	;
wire 						e_penable  	;
wire 	[DATA_WIDTH-1:0] 	e_pwdata	;
reg 						e_pready  	;
reg 	[DATA_WIDTH-1:0] 	e_prdata  	;


reg 	[1:0]				d_penable  	;
wire 	[1:0]				d_pready  	;
wire 	[DATA_WIDTH-1:0]	d_prdata [1:0] ;
reg		[1:0]				d_psel;

wire [15:0] e_oe;
wire [15:0]	e_pu;
wire [15:0]	e_pd;
wire [15:0]	e_a;
wire [15:0]	e_y;


always @(*) begin
	if(!resetn) begin
		d_psel 		<=	'h0;
		d_penable	<=	'h0;
	end else begin
		case(e_psel)
			2'b01 : begin
						d_psel[0] 	<= 1'b1;
						e_prdata 	<= d_prdata[0];
						e_pready	<= d_pready[0];
						d_penable[0] <=	e_penable;
					end
			2'b10 : begin
						d_psel[1] 	<= 1'b1;
						e_prdata 	<= d_prdata[1];
						e_pready	<= d_pready[1];
						d_penable[1] <=	e_penable;
					end
			default : begin
						d_psel	 	<= 1'b0;
						d_penable <=	1'b0;
						e_prdata 	<= 8'h0;
						e_pready	<= 1'b0;
					end
		endcase
	end
end

spi2apb_bridge bridge(	.sclk(sclk),		.resetn(resetn),		.b_pready(e_pready),	.b_prdata(e_prdata),	
						.b_pclk(e_pclk),	.b_presetn(e_presetn), 	.b_paddr(e_paddr),		.b_pwrite(e_pwrite),	
						.b_psel(e_psel),	.b_penable(e_penable),	.b_pwdata(e_pwdata),						
						.mosi(mosi), 		.miso(miso),			.ss(ss));

gbas 			bank0(	.paddr(e_paddr),	.pready(d_pready[0]),	.prdata(d_prdata[0]),	.oe(e_oe[7:0]),
						.pclk(e_pclk),		.pwdata(e_pwdata),		.pwrite(e_pwrite),		.pu(e_pu[7:0]),	.a(e_a[7:0]),
						.pselx(d_psel[0]),	.penable(e_penable),	.presetn(e_presetn), 	.pd(e_pd[7:0]),	.y(e_y[7:0]));

gbas 			bank1(	.paddr(e_paddr),	.pready(d_pready[1]),	.prdata(d_prdata[1]),	.oe(e_oe[15:8]),
						.pclk(e_pclk),		.pwdata(e_pwdata),		.pwrite(e_pwrite),		.pu(e_pu[15:8]),	.a(e_a[15:8]),
						.pselx(d_psel[1]),	.penable(e_penable),	.presetn(e_presetn), 	.pd(e_pd[15:8]),	.y(e_y[15:8]));


gpio_pad 		pin0(	.oe(e_oe[0]),		.a(e_a[0]),				.pd(e_pd[0]),
						.pu(e_pu[0]),		.y(e_y[0]),				.pad(pad[0]));

gpio_pad 		pin1(	.oe(e_oe[1]),		.a(e_a[1]),				.pd(e_pd[1]),
						.pu(e_pu[1]),		.y(e_y[1]),				.pad(pad[1]));

gpio_pad 		pin2(	.oe(e_oe[2]),		.a(e_a[2]),				.pd(e_pd[2]),
						.pu(e_pu[2]),		.y(e_y[2]),				.pad(pad[2]));

gpio_pad 		pin3(	.oe(e_oe[3]),		.a(e_a[3]),				.pd(e_pd[3]),
						.pu(e_pu[3]),		.y(e_y[3]),				.pad(pad[3]));

gpio_pad 		pin4(	.oe(e_oe[4]),		.a(e_a[4]),				.pd(e_pd[4]),
						.pu(e_pu[4]),		.y(e_y[4]),				.pad(pad[4]));

gpio_pad 		pin5(	.oe(e_oe[5]),		.a(e_a[5]),				.pd(e_pd[5]),
						.pu(e_pu[5]),		.y(e_y[5]),				.pad(pad[5]));

gpio_pad 		pin6(	.oe(e_oe[6]),		.a(e_a[6]),				.pd(e_pd[6]),
						.pu(e_pu[6]),		.y(e_y[6]),				.pad(pad[6]));

gpio_pad 		pin7(	.oe(e_oe[7]),		.a(e_a[7]),				.pd(e_pd[7]),
						.pu(e_pu[7]),		.y(e_y[7]),				.pad(pad[7]));


gpio_pad 		pin8(	.oe(e_oe[8]),		.a(e_a[8]),				.pd(e_pd[8]),
						.pu(e_pu[8]),		.y(e_y[8]),				.pad(pad[8]));

gpio_pad 		pin9(	.oe(e_oe[9]),		.a(e_a[9]),				.pd(e_pd[9]),
						.pu(e_pu[9]),		.y(e_y[9]),				.pad(pad[9]));

gpio_pad 		pin10(	.oe(e_oe[10]),		.a(e_a[10]),			.pd(e_pd[10]),
						.pu(e_pu[10]),		.y(e_y[10]),			.pad(pad[10]));

gpio_pad 		pin11(	.oe(e_oe[11]),		.a(e_a[11]),			.pd(e_pd[11]),
						.pu(e_pu[11]),		.y(e_y[11]),			.pad(pad[11]));

gpio_pad 		pin12(	.oe(e_oe[12]),		.a(e_a[12]),			.pd(e_pd[12]),
						.pu(e_pu[12]),		.y(e_y[12]),			.pad(pad[12]));

gpio_pad 		pin13(	.oe(e_oe[13]),		.a(e_a[13]),			.pd(e_pd[13]),
						.pu(e_pu[13]),		.y(e_y[13]),			.pad(pad[13]));

gpio_pad 		pin14(	.oe(e_oe[14]),		.a(e_a[14]),			.pd(e_pd[14]),
						.pu(e_pu[14]),		.y(e_y[14]),			.pad(pad[14]));

gpio_pad 		pin15(	.oe(e_oe[15]),		.a(e_a[15]),			.pd(e_pd[15]),
						.pu(e_pu[15]),		.y(e_y[15]),			.pad(pad[15]));


endmodule

GPIO_Expander/gpio_expander_tb.v
`timescale 1ns/1ps
//`include "gpio_pad.v"
//`include "gbas.v"
//`include "spi2apb_bridge.v"
`include "gpio_expander.v"

module gpio_expander_tb#(
			        		parameter BANK_NUM      = 	2,
							parameter DATA_WIDTH 	= 	16,
                 			parameter PDATA_WIDTH 	=  	8,
							parameter ADDR_WIDTH	=	7,
                  			parameter PADDR_WIDTH   = 	3
				    		)(
				    		);

reg clk;
reg	sclk;
reg	resetn;
wire	miso_tb;
wire    mosi_tb;
reg	ss;
						
wire [15:0]	pad_tb;

reg [15:0] reg_mosi_tb;
reg [15:0] reg_miso_tb;


gpio_expander i0(.sclk(sclk), .resetn(resetn), .miso(miso_tb), .mosi(mosi_tb), .ss(ss), .pad(pad_tb));
//gbas bank();
//gpio_pad pins();

function automatic reg [15:0] spi_xfer;
input 	[DATA_WIDTH-1:0] 	data_in;
reg 	[15:0] 				rd_mosi;
        begin
                reg_mosi_tb = data_in << 1;
                rd_mosi[15:1] = 'h0;
                rd_mosi[0] = miso_tb;
                spi_xfer = rd_mosi;
        end
endfunction


assign mosi_tb = reg_mosi_tb[15];

task write_reg(input [ADDR_WIDTH-1:0] addr, input [PDATA_WIDTH-1:0] data);
integer i;
        begin

             @(posedge clk);
                ss = 0;
                reg_mosi_tb [15] = 1;  
                reg_mosi_tb [14:8] = addr;
                reg_mosi_tb [7:0] = data;  

                for(i = 0; i < 16; i = i + 1) begin
                        @(posedge clk);
                        sclk = !sclk;
                        reg_miso_tb = reg_miso_tb << 1;
                        #10
                        reg_miso_tb =  reg_miso_tb + spi_xfer(reg_mosi_tb);
                        @(posedge clk);
                        sclk = !sclk;
                end
                @(posedge clk);
                ss = 1;
        end
endtask

task read_reg(input [ADDR_WIDTH-1:0] addr);
integer i;
        begin

             @(posedge clk);
                ss = 0;
                reg_mosi_tb [15] = 0;  
                reg_mosi_tb [14:8] = addr;
                reg_mosi_tb [7:0] = 'h0;  

                for(i = 0; i < 16; i = i + 1) begin
                        @(posedge clk);
                        sclk = !sclk;
                        reg_miso_tb = reg_miso_tb << 1;
                        #10
                        reg_miso_tb =  reg_miso_tb + spi_xfer(reg_mosi_tb);
                        @(posedge clk);
                        sclk = !sclk;
                end
                @(posedge clk);
                ss = 1;
        end
endtask

initial begin
        clk = 0;
        sclk = 0;
        resetn = 1;
        ss = 1;
        reg_mosi_tb = 16'h0000;
        reg_miso_tb = 16'h0000;
end

initial begin
        $dumpfile("gpio_expander_tb.vcd");
        $dumpvars(0, gpio_expander_tb);
        $display("Module %m") ;
        #3 resetn = 0;
        #3 resetn = 1;
        #100
        $display("Write: ") ;
        write_reg(7'h20, 8'hff);
        #100
        write_reg(7'h40, 8'hff);
        #100
        $display("Read: ") ;
        read_reg(7'h20);
        #500 $finish;
end

always #10 clk = !clk;
endmodule

GPIO_Expander/gpio_expander_tb.vcd
$date
	Wed Mar 09 20:21:13 2022
$end
$version
	Icarus Verilog
$end
$timescale
	1ps
$end
$scope module gpio_expander_tb $end
$var wire 16 ! pad_tb [15:0] $end
$var wire 1 " mosi_tb $end
$var wire 1 # miso_tb $end
$var reg 1 $ clk $end
$var reg 16 % reg_miso_tb [15:0] $end
$var reg 16 & reg_mosi_tb [15:0] $end
$var reg 1 ' resetn $end
$var reg 1 ( sclk $end
$var reg 1 ) ss $end
$scope function spi_xfer $end
$upscope $end
$scope module i0 $end
$var wire 1 " mosi $end
$var wire 16 * pad [15:0] $end
$var wire 1 ' resetn $end
$var wire 1 ( sclk $end
$var wire 1 ) ss $end
$var wire 1 # miso $end
$var wire 16 + e_y [15:0] $end
$var wire 1 , e_pwrite $end
$var wire 8 - e_pwdata [7:0] $end
$var wire 16 . e_pu [15:0] $end
$var wire 2 / e_psel [1:0] $end
$var wire 1 0 e_presetn $end
$var wire 1 1 e_penable $end
$var wire 16 2 e_pd [15:0] $end
$var wire 1 3 e_pclk $end
$var wire 3 4 e_paddr [2:0] $end
$var wire 16 5 e_oe [15:0] $end
$var wire 16 6 e_a [15:0] $end
$var wire 2 7 d_pready [1:0] $end
$var reg 2 8 d_penable [1:0] $end
$var reg 2 9 d_psel [1:0] $end
$var reg 8 : e_prdata [7:0] $end
$var reg 1 ; e_pready $end
$scope module bank0 $end
$var wire 1 < pready $end
$var wire 1 = pselx $end
$var wire 1 > read_en $end
$var wire 1 ? write_en $end
$var wire 8 @ y [7:0] $end
$var wire 1 , pwrite $end
$var wire 8 A pwdata [7:0] $end
$var wire 8 B pu [7:0] $end
$var wire 1 0 presetn $end
$var wire 1 1 penable $end
$var wire 8 C pd [7:0] $end
$var wire 1 3 pclk $end
$var wire 3 D paddr [2:0] $end
$var wire 8 E oe [7:0] $end
$var wire 8 F a [7:0] $end
$var reg 2 G counter [1:0] $end
$var reg 8 H prdata [7:0] $end
$var reg 1 I pready_reg $end
$var reg 8 J reg_a [7:0] $end
$var reg 8 K reg_oe [7:0] $end
$var reg 8 L reg_pd [7:0] $end
$var reg 8 M reg_pu [7:0] $end
$var reg 8 N reg_y [7:0] $end
$upscope $end
$scope module bank1 $end
$var wire 1 O pready $end
$var wire 1 P pselx $end
$var wire 1 Q read_en $end
$var wire 1 R write_en $end
$var wire 8 S y [7:0] $end
$var wire 1 , pwrite $end
$var wire 8 T pwdata [7:0] $end
$var wire 8 U pu [7:0] $end
$var wire 1 0 presetn $end
$var wire 1 1 penable $end
$var wire 8 V pd [7:0] $end
$var wire 1 3 pclk $end
$var wire 3 W paddr [2:0] $end
$var wire 8 X oe [7:0] $end
$var wire 8 Y a [7:0] $end
$var reg 2 Z counter [1:0] $end
$var reg 8 [ prdata [7:0] $end
$var reg 1 \ pready_reg $end
$var reg 8 ] reg_a [7:0] $end
$var reg 8 ^ reg_oe [7:0] $end
$var reg 8 _ reg_pd [7:0] $end
$var reg 8 ` reg_pu [7:0] $end
$var reg 8 a reg_y [7:0] $end
$upscope $end
$scope module bridge $end
$var wire 1 3 b_pclk $end
$var wire 8 b b_prdata [7:0] $end
$var wire 1 ; b_pready $end
$var wire 1 0 b_presetn $end
$var wire 1 " mosi $end
$var wire 1 ' resetn $end
$var wire 1 ( sclk $end
$var wire 1 ) ss $end
$var wire 1 # miso $end
$var wire 1 c en_reg_psel $end
$var wire 1 d en_pwrite $end
$var wire 1 e en_pwdata $end
$var wire 1 f en_psel_w $end
$var wire 1 g en_psel_r $end
$var wire 1 h en_prdata $end
$var wire 1 i en_penable_w $end
$var wire 1 j en_penable_r $end
$var wire 1 k en_paddr $end
$var wire 2 l b_psel [1:0] $end
$var wire 1 1 b_penable $end
$var reg 3 m b_paddr [2:0] $end
$var reg 8 n b_pwdata [7:0] $end
$var reg 1 , b_pwrite $end
$var reg 4 o counter_spi [3:0] $end
$var reg 1 p off_signal $end
$var reg 16 q reg_miso [15:0] $end
$var reg 16 r reg_mosi [15:0] $end
$var reg 2 s reg_psel [1:0] $end
$var reg 1 t start $end
$upscope $end
$scope module pin0 $end
$var wire 1 u a $end
$var wire 1 v oe $end
$var wire 1 w pad $end
$var wire 1 x pd $end
$var wire 1 y pu $end
$var wire 1 z y $end
$upscope $end
$scope module pin1 $end
$var wire 1 { a $end
$var wire 1 | oe $end
$var wire 1 } pad $end
$var wire 1 ~ pd $end
$var wire 1 !" pu $end
$var wire 1 "" y $end
$upscope $end
$scope module pin10 $end
$var wire 1 #" a $end
$var wire 1 $" oe $end
$var wire 1 %" pad $end
$var wire 1 &" pd $end
$var wire 1 '" pu $end
$var wire 1 (" y $end
$upscope $end
$scope module pin11 $end
$var wire 1 )" a $end
$var wire 1 *" oe $end
$var wire 1 +" pad $end
$var wire 1 ," pd $end
$var wire 1 -" pu $end
$var wire 1 ." y $end
$upscope $end
$scope module pin12 $end
$var wire 1 /" a $end
$var wire 1 0" oe $end
$var wire 1 1" pad $end
$var wire 1 2" pd $end
$var wire 1 3" pu $end
$var wire 1 4" y $end
$upscope $end
$scope module pin13 $end
$var wire 1 5" a $end
$var wire 1 6" oe $end
$var wire 1 7" pad $end
$var wire 1 8" pd $end
$var wire 1 9" pu $end
$var wire 1 :" y $end
$upscope $end
$scope module pin14 $end
$var wire 1 ;" a $end
$var wire 1 <" oe $end
$var wire 1 =" pad $end
$var wire 1 >" pd $end
$var wire 1 ?" pu $end
$var wire 1 @" y $end
$upscope $end
$scope module pin15 $end
$var wire 1 A" a $end
$var wire 1 B" oe $end
$var wire 1 C" pad $end
$var wire 1 D" pd $end
$var wire 1 E" pu $end
$var wire 1 F" y $end
$upscope $end
$scope module pin2 $end
$var wire 1 G" a $end
$var wire 1 H" oe $end
$var wire 1 I" pad $end
$var wire 1 J" pd $end
$var wire 1 K" pu $end
$var wire 1 L" y $end
$upscope $end
$scope module pin3 $end
$var wire 1 M" a $end
$var wire 1 N" oe $end
$var wire 1 O" pad $end
$var wire 1 P" pd $end
$var wire 1 Q" pu $end
$var wire 1 R" y $end
$upscope $end
$scope module pin4 $end
$var wire 1 S" a $end
$var wire 1 T" oe $end
$var wire 1 U" pad $end
$var wire 1 V" pd $end
$var wire 1 W" pu $end
$var wire 1 X" y $end
$upscope $end
$scope module pin5 $end
$var wire 1 Y" a $end
$var wire 1 Z" oe $end
$var wire 1 [" pad $end
$var wire 1 \" pd $end
$var wire 1 ]" pu $end
$var wire 1 ^" y $end
$upscope $end
$scope module pin6 $end
$var wire 1 _" a $end
$var wire 1 `" oe $end
$var wire 1 a" pad $end
$var wire 1 b" pd $end
$var wire 1 c" pu $end
$var wire 1 d" y $end
$upscope $end
$scope module pin7 $end
$var wire 1 e" a $end
$var wire 1 f" oe $end
$var wire 1 g" pad $end
$var wire 1 h" pd $end
$var wire 1 i" pu $end
$var wire 1 j" y $end
$upscope $end
$scope module pin8 $end
$var wire 1 k" a $end
$var wire 1 l" oe $end
$var wire 1 m" pad $end
$var wire 1 n" pd $end
$var wire 1 o" pu $end
$var wire 1 p" y $end
$upscope $end
$scope module pin9 $end
$var wire 1 q" a $end
$var wire 1 r" oe $end
$var wire 1 s" pad $end
$var wire 1 t" pd $end
$var wire 1 u" pu $end
$var wire 1 v" y $end
$upscope $end
$upscope $end
$scope task read_reg $end
$var reg 7 w" addr [6:0] $end
$var integer 32 x" i [31:0] $end
$upscope $end
$scope task write_reg $end
$var reg 7 y" addr [6:0] $end
$var reg 8 z" data [7:0] $end
$var integer 32 {" i [31:0] $end
$upscope $end
$upscope $end
$enddefinitions $end
#0
$dumpvars
bx {"
bx z"
bx y"
bx x"
bx w"
xv"
xu"
xt"
xs"
xr"
xq"
xp"
xo"
xn"
xm"
xl"
xk"
xj"
xi"
xh"
xg"
xf"
xe"
xd"
xc"
xb"
xa"
x`"
x_"
x^"
x]"
x\"
x["
xZ"
xY"
xX"
xW"
xV"
xU"
xT"
xS"
xR"
xQ"
xP"
xO"
xN"
xM"
xL"
xK"
xJ"
xI"
xH"
xG"
xF"
xE"
xD"
xC"
xB"
xA"
x@"
x?"
x>"
x="
x<"
x;"
x:"
x9"
x8"
x7"
x6"
x5"
x4"
x3"
x2"
x1"
x0"
x/"
x."
x-"
x,"
x+"
x*"
x)"
x("
x'"
x&"
x%"
x$"
x#"
x""
x!"
x~
x}
x|
x{
xz
xy
xx
xw
xv
xu
0t
bx s
bx r
bx q
xp
bx o
b0 n
bx m
bx l
xk
xj
0i
xh
xg
0f
0e
xd
xc
b0 b
bx a
bx `
bx _
bx ^
bx ]
x\
b0 [
bx Z
bx Y
bx X
bx W
bx V
bx U
b0 T
bx S
0R
0Q
0P
0O
bx N
bx M
bx L
bx K
bx J
xI
b0 H
bx G
bx F
bx E
bx D
bx C
bx B
b0 A
bx @
0?
0>
0=
0<
0;
b0 :
b0 9
b0 8
b0 7
bx 6
bx 5
bx 4
03
bx 2
x1
10
bx /
bx .
b0 -
x,
bx +
bx *
1)
0(
1'
b0 &
b0 %
0$
x#
0"
bx !
$end
#3000
bz @
bz S
zz
zw
z""
z}
zL"
zI"
zR"
zO"
zX"
zU"
z^"
z["
zd"
za"
zj"
zg"
zp"
zm"
zv"
zs"
z("
z%"
z."
z+"
z4"
z1"
z:"
z7"
z@"
z="
bz +
zF"
zC"
bz !
bz *
01
b0 /
b0 l
0g
0j
0u
0{
0G"
0M"
0S"
0Y"
0_"
0e"
0y
0!"
0K"
0Q"
0W"
0]"
0c"
0i"
0x
0~
0J"
0P"
0V"
0\"
0b"
0h"
0v
0|
0H"
0N"
0T"
0Z"
0`"
0f"
0k"
0q"
0#"
0)"
0/"
05"
0;"
0A"
0o"
0u"
0'"
0-"
03"
09"
0?"
0E"
0n"
0t"
0&"
0,"
02"
08"
0>"
0D"
0l"
0r"
0$"
0*"
00"
06"
0<"
0B"
0#
0d
0k
0h
0c
0I
b0 G
b0 N
0\
b0 Z
b0 a
b0 F
b0 J
b0 B
b0 M
b0 C
b0 L
b0 E
b0 K
b0 6
b0 Y
b0 ]
b0 .
b0 U
b0 `
b0 2
b0 V
b0 _
b0 5
b0 X
b0 ^
0p
b0 s
b0 4
b0 D
b0 W
b0 m
0,
b0 q
b0 o
b0 r
00
0'
#6000
10
1'
#10000
1$
#20000
0$
#30000
1$
#40000
0$
#50000
1$
#60000
0$
#70000
1$
#80000
0$
#90000
1$
#100000
0$
#106000
b11111111 z"
b100000 y"
#110000
1e
1"
b0 {"
b1010000011111111 &
0)
1$
#120000
0$
#130000
0e
1d
bz a
bz N
b1 o
b1 r
13
1(
1$
#140000
0"
b100000111111110 &
0$
#150000
1,
b10 r
b1 {"
03
0(
1$
#160000
0$
#170000
0d
1t
b10 o
13
1(
1$
#180000
1"
b1000001111111100 &
0$
#190000
b100 r
b10 {"
03
0(
1$
#200000
0$
#210000
1c
b11 o
b101 r
13
1(
1$
#220000
0"
b11111111000 &
0$
#230000
b1 s
b1010 r
b11 {"
03
0(
1$
#240000
0$
#250000
0c
b100 o
13
1(
1$
#260000
b111111110000 &
0$
#270000
b10100 r
b100 {"
03
0(
1$
#280000
0$
#290000
b101 o
13
1(
1$
#300000
b1111111100000 &
0$
#310000
b101000 r
b101 {"
03
0(
1$
#320000
0$
#330000
1k
b110 o
13
1(
1$
#340000
b11111111000000 &
0$
#350000
b1010000 r
b110 {"
03
0(
1$
#360000
0$
#370000
0k
b111 o
13
1(
1$
#380000
b111111110000000 &
0$
#390000
b10100000 r
b111 {"
03
0(
1$
#400000
0$
#410000
b1000 o
13
1(
1$
#420000
1"
b1111111100000000 &
0$
#430000
b101000000 r
b1000 {"
03
0(
1$
#440000
0$
#450000
1h
b1001 o
b101000001 r
13
1(
1$
#460000
b1111111000000000 &
0$
#470000
b1010000010 r
b1001 {"
03
0(
1$
#480000
0$
#490000
0h
b1010 o
b1010000011 r
13
1(
1$
#500000
b1111110000000000 &
0$
#510000
b10100000110 r
b1010 {"
03
0(
1$
#520000
0$
#530000
b1011 o
b10100000111 r
13
1(
1$
#540000
b1111100000000000 &
0$
#550000
b101000001110 r
b1011 {"
03
0(
1$
#560000
0$
#570000
b1100 o
b101000001111 r
13
1(
1$
#580000
b1111000000000000 &
0$
#590000
b1010000011110 r
b1100 {"
03
0(
1$
#600000
0$
#610000
b1101 o
b1010000011111 r
13
1(
1$
#620000
b1110000000000000 &
0$
#630000
b10100000111110 r
b1101 {"
03
0(
1$
#640000
0$
#650000
b1110 o
b10100000111111 r
13
1(
1$
#660000
b1100000000000000 &
0$
#670000
b101000001111110 r
b1110 {"
03
0(
1$
#680000
0$
#690000
1?
1=
b1 9
b1 /
b1 l
1f
b1111 o
b101000001111111 r
13
1(
1$
#700000
b1000000000000000 &
0$
#710000
b1010000011111110 r
b1111 {"
03
0(
1$
#720000
0$
#730000
b0 @
0z
0w
0""
0}
0L"
0I"
0R"
0O"
0X"
0U"
0^"
0["
0d"
0a"
bz00000000 +
0j"
0g"
bz00000000 !
bz00000000 *
1v
1|
1H"
1N"
1T"
1Z"
1`"
1f"
1p
b11111111 5
b11111111 E
b11111111 K
1;
b1 8
b11111111 -
b11111111 A
b11111111 T
b11111111 n
b1 7
1<
11
1i
1e
b1 G
1I
b0 o
b1010000011111111 r
13
1(
1$
#740000
0"
b0 &
0$
#750000
b10000 {"
03
0(
1$
#760000
0$
#770000
0?
0=
0;
b0 9
b0 8
0t
b0 /
b0 l
b0 7
0<
01
0f
0i
0e
1)
1$
#780000
0$
#790000
1$
#800000
0$
#810000
1$
#820000
0$
#830000
1$
#840000
0$
#850000
1$
#860000
0$
#870000
1f
1i
1e
1"
b0 {"
b1100000011111111 &
0)
1$
b1000000 y"
#880000
0$
#890000
0f
0i
0e
1d
b0 N
0I
0p
b1 o
13
1(
1$
#900000
b1000000111111110 &
0$
#910000
b100000111111110 r
b1 {"
03
0(
1$
#920000
0$
#930000
0d
1t
b10 o
b100000111111111 r
13
1(
1$
#940000
0"
b1111111100 &
0$
#950000
b1000001111111110 r
b10 {"
03
0(
1$
#960000
0$
#970000
1c
b11 o
13
1(
1$
#980000
b11111111000 &
0$
#990000
b10 s
b11111111100 r
b11 {"
03
0(
1$
#1000000
0$
#1010000
0c
b100 o
13
1(
1$
#1020000
b111111110000 &
0$
#1030000
b111111111000 r
b100 {"
03
0(
1$
#1040000
0$
#1050000
b101 o
13
1(
1$
#1060000
b1111111100000 &
0$
#1070000
b1111111110000 r
b101 {"
03
0(
1$
#1080000
0$
#1090000
1k
b110 o
13
1(
1$
#1100000
b11111111000000 &
0$
#1110000
b11111111100000 r
b110 {"
03
0(
1$
#1120000
0$
#1130000
0k
b111 o
13
1(
1$
