GPIO_Expander/gpio_pad.v
module gpio_pad(
				inout 	pad,	
				input 	a,
				input	oe,				//driver enable signal
				input	pu,				//enabling the built-in resistive power pull-up
				input	pd,				//enabling the built-in resistive pull-up to ground
				output	y				//receiver output
				);			

assign (pull0, pull1) pad = (oe)? a : 1'bz;
assign (weak1, weak0) pad = (pu)? 1'b1 : 1'bz;
assign (weak1, weak0) pad = (pd)? 1'b0 : 1'bz;
assign y = pad;

endmodule

GPIO_Expander/gbas.v
 module gbas#(
 				parameter ADDR_BUNK 	= 1,
				parameter DATA_WIDTH 	= 8,
				parameter ADDR_WIDTH 	= 3,
				parameter PREADY_DEL 	= 0
				)(
				input 							pclk,
				input 							presetn,
				input 		[ADDR_WIDTH-1 : 0]	paddr,
				input 							pwrite,
				input 		[1:0]					pselx,
				input 							penable,
				input 		[DATA_WIDTH-1 : 0]	pwdata,
				output  reg	[DATA_WIDTH-1 : 0]	prdata,
				output 							pready,

				input		[7 : 0]            	y,
				output		[7 : 0]            	oe,
				output		[7 : 0]            	pu,
				output		[7 : 0]            	pd,
				output		[7 : 0]            	a
				);

reg [1:0] addr_bank = ADDR_BUNK;
wire sel_bank;
reg pwrite_reg;

assign sel_bank = (pselx == addr_bank)? 1'b1 : 1'b0;

reg [7:0] reg_oe;
reg [7:0] reg_pu;
reg [7:0] reg_pd;
reg [7:0] reg_a;
reg [7:0] reg_y;


reg 	[1:0] 	 counter;
wire 	[7:0]	 wire_y;
wire 			 r_counter_en;
wire 			 w_counter_en;
reg 			 pready_reg;
wire 			 write_en;
wire 			 read_en;

assign write_en = 	 pwrite & sel_bank;
assign read_en	=	!pwrite & sel_bank;

always @(posedge pclk or negedge presetn) begin
	if(!presetn) begin
		reg_oe	<= 8'h00;
		reg_pd	<= 8'h00;
		reg_pu	<= 8'h00;
		reg_a	<= 8'h00;
	end 
	else begin
		if(write_en & pready) begin
			case (paddr)
				3'h0 : reg_oe	<= pwdata;
				3'h1 : reg_pu	<= pwdata;
				3'h2 : reg_pd	<= pwdata;
				3'h3 : reg_a 	<= pwdata;
			endcase
		end
	end
end

always @(*) begin
	if(read_en & penable & pready) begin
		case (paddr)
			3'h0 : prdata <= reg_oe;
			3'h1 : prdata <= reg_pu;
			3'h2 : prdata <= reg_pd;
			3'h3 : prdata <= reg_a;
			3'h4 : prdata <= reg_y;
			default : prdata <= 8'h00;
		endcase
	end else 
		prdata <= 8'h00;
end

always @(posedge pclk or negedge presetn) begin
	if(!presetn) begin
		counter <= 2'b0;
		pready_reg <= 1'b0;
	end else begin
		if(read_en || write_en) begin
			pready_reg <= (PREADY_DEL == 0)? 1'b1 : (counter == PREADY_DEL)? 1'b1 : 1'b0;
			counter <= (pready_reg)? 2'b00 : counter + 1'b1;
		end else 
			pready_reg <= 1'b0; 
	end
end

always @(posedge pclk or  negedge presetn) begin
	if(!presetn)
		reg_y <= 1'b0;
	else 
		reg_y <= y;
end


assign pready = ((read_en && penable) || (write_en && penable))? pready_reg : 1'b0;

assign oe = reg_oe;
assign pu = reg_pu;
assign pd = reg_pd;
assign a  = reg_a;

endmodule

GPIO_Expander/spi2apb_bridge.v
module spi2apb_bridge #(
						parameter BANK_ADDR		= 	2,
						parameter DATA_WIDTH 	= 	8,
						parameter ADDR_WIDTH	=	3
						)(
                        input 			sclk,
                        input 			resetn,
                        input 			mosi,
                        input 			ss,
                        output 			miso,

                        input		[DATA_WIDTH-1 : 0]		b_prdata,
                        input								b_pready,
                        output								b_pclk,
                        output								b_presetn,
                        output		[DATA_WIDTH-1 : 0]		b_pwdata,
                        output	reg							b_pwrite,
                        output	reg	[BANK_ADDR-1	:	0]	b_psel,
                        output	reg							b_penable,
                        output	reg	[ADDR_WIDTH-1 : 0]		b_paddr
                        );

reg	[15: 0]	reg_mosi;
reg [15: 0]	reg_miso;

reg [3 : 0] counter_spi;
reg	[3 : 0] counter_apb;
reg [BANK_ADDR-1 : 0] reg_psel;
wire en_pwrite;
wire en_paddr;
wire en_psel;
wire en_penable_w;
wire en_penable_r;
wire en_psel_w;
wire en_psel_r;
reg off_signal;
reg en_pwdata;
reg en_sclk;
reg off_penable;

//spi interface
always @(posedge sclk or negedge resetn) begin
	if(!resetn) begin
		reg_mosi	<=	'h0;
        counter_spi	<=  'b00;
	end else begin
		if(!ss) begin
		 	reg_mosi [0] 	<= mosi;
		 	counter_spi 	<= counter_spi + 1'b1;
		end else 
			counter_spi <= 4'b0000;
	end
end

always @(negedge sclk or negedge resetn) begin
	if(!resetn) begin
		reg_miso 	<=	'h0;
	end else begin
		if(!ss && (counter_spi != 4'b0000)) begin
		reg_mosi	<= reg_mosi << 1'b1;
		reg_miso	<= reg_miso << 1'b1;
		end
	end
end

assign miso = reg_miso[15];

// apb interface
always @(negedge sclk or negedge resetn or posedge b_pready) begin
	if(!resetn) begin
		b_pwrite <= 1'b0; 
		b_paddr	 <= 7'h0;
		reg_psel  <= 'h0;
	end else begin
			b_pwrite <= (en_pwrite)? reg_mosi[0] : b_pwrite;
			b_paddr	 <= (en_paddr)?  reg_mosi[2:0] : b_paddr;
			reg_psel <=	(en_reg_psel)?  reg_mosi[1:0] : reg_psel;
	end
end

always @(posedge sclk or negedge resetn or negedge b_pready) begin
	if(!resetn) begin
		b_penable <= 1'b0;
		b_psel	  <= 8'h0;
	end else begin 

		if(ss) begin
			b_penable <= (!b_pready)? 1'b0 : b_penable;
			b_psel <= (!b_pready)? 1'b0 : b_penable;
		end else begin 
			b_penable <= (en_penable_w || en_penable_r)?  1'b1 : (off_signal)? 1'b0 : b_penable;
			b_psel	 <= (en_psel_r || en_psel_w)? reg_psel : (off_signal)? 'h0 : b_psel;
		end
	end
end


always @(posedge sclk or negedge resetn or posedge b_pready) begin
	if(!resetn) begin
		off_signal <= 1'b0;
	end else begin
		off_signal <= (b_pready)? 1'b1 : 1'b0; 
	end
end


assign 	b_pclk			= sclk;
assign	en_pwrite		= (counter_spi == 4'h1)? 1'b1 : 1'b0;
assign  en_paddr		= (counter_spi == 4'h6)? 1'b1 : 1'b0;		
assign  en_prdata		= (counter_spi == 4'h9)? 1'b1 : 1'b0;
assign 	en_reg_psel		= (counter_spi == 4'h3)? 1'b1 : 1'b0;

assign  en_psel_w			= (counter_spi == 4'he && b_pwrite)? 1'b1 : 1'b0;
assign  en_psel_r			= (counter_spi == 4'h6 && !b_pwrite)? 1'b1 : 1'b0;

assign	en_penable_w	= (counter_spi == 4'hf && b_pwrite && !ss)? 1'b1 : 1'b0;
assign	en_penable_r	= ((counter_spi == 4'h7) && !b_pwrite)? 1'b1 : 1'b0;	

assign  b_presetn 	= resetn; 
assign  b_pwdata    = reg_mosi[7:0];


always @(negedge sclk) begin
	if(!b_pwrite && b_penable)
		reg_miso [15:8] <= b_prdata; 
end


endmodule

GPIO_Expander/gpio_expander.v
`include "gpio_pad.v"
`include "gbas.v"
`include "spi2apb_bridge.v"

module gpio_expander#(
						parameter BANK_NUM = 2,
						parameter ADDR_WIDTH = 7,
						parameter PADDR_WIDTH = 3,
						parameter DATA_WIDTH = 8
						)(
						input	sclk,
						input	resetn,
						output	miso,
						input	mosi,
						input	ss,
						
						output [7:0]	pad);

wire 						e_pclk_a 	;
wire 						e_pclk_b 	;
wire 						e_presetn  	;
wire	[PADDR_WIDTH-1:0]	e_paddr  	;
wire 						e_pwrite  	;
wire 	[1:0]	 			e_psel 	 	;
wire 						e_penable  	;
wire 	[DATA_WIDTH-1:0] 	e_pwdata	;
wire 						e_pready  	;
wire 	[DATA_WIDTH-1:0] 	e_prdata  	;


wire [7:0] 	e_oe;
wire [7:0]	e_pu;
wire [7:0]	e_pd;
wire [7:0]	e_a;
wire [7:0]	e_y;

assign e_pclk_b = e_pclk_a;

spi2apb_bridge bridge(	.sclk(sclk),		.resetn(resetn),		.b_pready(e_pready),	.b_prdata(e_prdata),	
						.b_pclk(e_pclk_a),	.b_presetn(e_presetn), 	.b_paddr(e_paddr),		.b_pwrite(e_pwrite),	
						.b_psel(e_psel),	.b_penable(e_penable),	.b_pwdata(e_pwdata),						
						.mosi(mosi), 		.miso(miso),			.ss(ss));

gbas 			bank0(	.paddr(e_paddr),	.pready(e_pready),		.prdata(e_prdata),	
						.pclk(e_pclk_b),	.pwdata(e_pwdata),		.pwrite(e_pwrite),
						.pselx(e_psel[0]),		.penable(e_penable),	.presetn(e_presetn));
/*
gbas 			bank1(	.paddr(e_paddr),	.pready(e_pready),		.prdata(e_prdata),	
						.pclk(e_pclk),	 	.pwdata(e_pwdata),		.pwrite(e_pwrite),
						.pselx(e_psel[1]),		.penable(e_penable),	.presetn(e_presetn));
*/

gpio_pad 		pin0(	.oe(e_oe[0]),		.a(e_a[0]),				.pd(e_pd[0]),
						.pu(e_pu[0]),		.y(e_y[0]),				.pad(pad[0]));

gpio_pad 		pin1(	.oe(e_oe[1]),		.a(e_a[1]),				.pd(e_pd[1]),
						.pu(e_pu[1]),		.y(e_y[1]),				.pad(pad[1]));

gpio_pad 		pin2(	.oe(e_oe[2]),		.a(e_a[2]),				.pd(e_pd[2]),
						.pu(e_pu[2]),		.y(e_y[2]),				.pad(pad[2]));

gpio_pad 		pin3(	.oe(e_oe[3]),		.a(e_a[3]),				.pd(e_pd[3]),
						.pu(e_pu[3]),		.y(e_y[3]),				.pad(pad[3]));

gpio_pad 		pin4(	.oe(e_oe[4]),		.a(e_a[4]),				.pd(e_pd[4]),
						.pu(e_pu[4]),		.y(e_y[4]),				.pad(pad[4]));

gpio_pad 		pin5(	.oe(e_oe[5]),		.a(e_a[5]),				.pd(e_pd[5]),
						.pu(e_pu[5]),		.y(e_y[5]),				.pad(pad[5]));

gpio_pad 		pin6(	.oe(e_oe[6]),		.a(e_a[6]),				.pd(e_pd[6]),
						.pu(e_pu[6]),		.y(e_y[6]),				.pad(pad[6]));

gpio_pad 		pin7(	.oe(e_oe[7]),		.a(e_a[7]),				.pd(e_pd[7]),
						.pu(e_pu[7]),		.y(e_y[7]),				.pad(pad[7]));

/*
gpio_pad 		pin8(	.oe(e_oe[8]),		.a(e_a[8])				.pd(e_pd[8])
						.pu(e_pu[8]),		.y(e_y[8]),				.pad(pad[8]));

gpio_pad 		pin9(	.oe(e_oe[9]),		.a(e_a[9])				.pd(e_pd[9])
						.pu(e_pu[9]),		.y(e_y[9]),				.pad(pad[9]));

gpio_pad 		pin10(	.oe(e_oe[10]),		.a(e_a[10])				.pd(e_pd[10])
						.pu(e_pu[10]),		.y(e_y[10]),			.pad(pad[10]));

gpio_pad 		pin11(	.oe(e_oe[11]),		.a(e_a[11])				.pd(e_pd[11])
						.pu(e_pu[11]),		.y(e_y[11]),			.pad(pad[11]));

gpio_pad 		pin12(	.oe(e_oe[12]),		.a(e_a[12])				.pd(e_pd[12])
						.pu(e_pu[12]),		.y(e_y[12]),			.pad(pad[12]));

gpio_pad 		pin13(	.oe(e_oe[13]),		.a(e_a[13])				.pd(e_pd[13])
						.pu(e_pu[13]),		.y(e_y[13]),			.pad(pad[13]));

gpio_pad 		pin14(	.oe(e_oe[14]),		.a(e_a[14])				.pd(e_pd[14])
						.pu(e_pu[14]),		.y(e_y[14]),			.pad(pad[14]));

gpio_pad 		pin15(	.oe(e_oe[15]),		.a(e_a[15])				.pd(e_pd[15])
						.pu(e_pu[15]),		.y(e_y[15]),			.pad(pad[15]));
*/

endmodule

GPIO_Expander/gpio_expander_tb.v
`timescale 1ns/1ps
//`include "gpio_pad.v"
//`include "gbas.v"
//`include "spi2apb_bridge.v"
`include "gpio_expander.v"

module gpio_expander_tb#(
			        		parameter BANK_NUM      = 	2,
							parameter DATA_WIDTH 	= 	16,
                 			parameter PDATA_WIDTH 	=  	8,
							parameter ADDR_WIDTH	=	7,
                  			parameter PADDR_WIDTH   = 	3
				    		)(
				    		);

reg clk;
reg	sclk;
reg	resetn;
reg	miso;
wire	mosi;
reg	ss;
						
wire [7:0]	pad;

reg [15:0] reg_mosi_tb;
reg [15:0] reg_miso_tb;


gpio_expander bridge(.sclk(sclk), .resetn(resetn), .miso(miso), .mosi(mosi), .ss(ss), .pad(pad));
//gbas bank();
//gpio_pad pins();

function automatic reg [15:0] spi_xfer;
input 	[DATA_WIDTH-1:0] 	data_in;
reg 	[15:0] 				rd_mosi;
        begin
                reg_mosi_tb = data_in << 1;
                rd_mosi[15:1] = 'h0;
                rd_mosi[0] = miso;
                spi_xfer = rd_mosi;
        end
endfunction


assign mosi = reg_mosi_tb[15];

task write_reg(input [ADDR_WIDTH-1:0] addr, input [PDATA_WIDTH-1:0] data);
integer i;
        begin

             @(posedge clk);
                ss = 0;
                reg_mosi_tb [15] = 1;  
                reg_mosi_tb [14:8] = addr;
                reg_mosi_tb [7:0] = data;  

                for(i = 0; i < 16; i = i + 1) begin
                        @(posedge clk);
                        sclk = !sclk;
                        reg_miso_tb = reg_miso_tb << 1;
                        #10
                        reg_miso_tb =  reg_miso_tb + spi_xfer(reg_mosi_tb);
                        @(posedge clk);
                        sclk = !sclk;
                end
                @(posedge clk);
                ss = 1;
        end
endtask

task read_reg(input [ADDR_WIDTH-1:0] addr);
integer i;
        begin

             @(posedge clk);
                ss = 0;
                reg_mosi_tb [15] = 0;  
                reg_mosi_tb [14:8] = addr;
                reg_mosi_tb [7:0] = 'h0;  

                for(i = 0; i < 16; i = i + 1) begin
                        @(posedge clk);
                        sclk = !sclk;
                        reg_miso_tb = reg_miso_tb << 1;
                        #10
                        reg_miso_tb =  reg_miso_tb + spi_xfer(reg_mosi_tb);
                        @(posedge clk);
                        sclk = !sclk;
                end
                @(posedge clk);
                ss = 1;
        end
endtask

initial begin
        clk = 0;
        sclk = 0;
        resetn = 1;
        ss = 1;
        reg_mosi_tb = 16'h0000;
        reg_miso_tb = 16'h0000;
end

initial begin
        $dumpfile("gpio_expander_tb.vcd");
        $dumpvars(0, gpio_expander_tb);
        $display("Module %m") ;
        #3 resetn = 0;
        #3 resetn = 1;
        #100
        $display("Write: ") ;
        write_reg(7'h20, 8'h81);
        #100
        $display("Read: ") ;
        read_reg(7'h55);
        #500 $finish;
end

always #10 clk = !clk;
endmodule

GPIO_Expander/gpio_expander_tb.vcd
$date
	Tue Mar 08 16:44:21 2022
$end
$version
	Icarus Verilog
$end
$timescale
	1ps
$end
$scope module gpio_expander_tb $end
$var wire 8 ! pad [7:0] $end
$var wire 1 " mosi $end
$var reg 1 # clk $end
$var reg 1 $ miso $end
$var reg 16 % reg_miso_tb [15:0] $end
$var reg 16 & reg_mosi_tb [15:0] $end
$var reg 1 ' resetn $end
$var reg 1 ( sclk $end
$var reg 1 ) ss $end
$scope function spi_xfer $end
$upscope $end
$scope module bridge $end
$var wire 8 * e_a [7:0] $end
$var wire 8 + e_oe [7:0] $end
$var wire 1 , e_pclk_b $end
$var wire 8 - e_pd [7:0] $end
$var wire 8 . e_pu [7:0] $end
$var wire 1 / miso $end
$var wire 1 " mosi $end
$var wire 8 0 pad [7:0] $end
$var wire 1 ' resetn $end
$var wire 1 ( sclk $end
$var wire 1 ) ss $end
$var wire 8 1 e_y [7:0] $end
$var wire 1 2 e_pwrite $end
$var wire 8 3 e_pwdata [7:0] $end
$var wire 2 4 e_psel [1:0] $end
$var wire 1 5 e_presetn $end
$var wire 1 6 e_pready $end
$var wire 8 7 e_prdata [7:0] $end
$var wire 1 8 e_penable $end
$var wire 1 9 e_pclk_a $end
$var wire 3 : e_paddr [2:0] $end
$scope module bank0 $end
$var wire 8 ; a [7:0] $end
$var wire 8 < oe [7:0] $end
$var wire 1 , pclk $end
$var wire 8 = pd [7:0] $end
$var wire 8 > pu [7:0] $end
$var wire 1 ? read_en $end
$var wire 1 @ write_en $end
$var wire 8 A y [7:0] $end
$var wire 1 B sel_bank $end
$var wire 1 2 pwrite $end
$var wire 8 C pwdata [7:0] $end
$var wire 2 D pselx [1:0] $end
$var wire 1 5 presetn $end
$var wire 1 6 pready $end
$var wire 1 8 penable $end
$var wire 3 E paddr [2:0] $end
$var reg 2 F addr_bank [1:0] $end
$var reg 2 G counter [1:0] $end
$var reg 8 H prdata [7:0] $end
$var reg 1 I pready_reg $end
$var reg 8 J reg_a [7:0] $end
$var reg 8 K reg_oe [7:0] $end
$var reg 8 L reg_pd [7:0] $end
$var reg 8 M reg_pu [7:0] $end
$var reg 8 N reg_y [7:0] $end
$upscope $end
$scope module bridge $end
$var wire 1 9 b_pclk $end
$var wire 8 O b_prdata [7:0] $end
$var wire 1 6 b_pready $end
$var wire 1 5 b_presetn $end
$var wire 1 / miso $end
$var wire 1 " mosi $end
$var wire 1 ' resetn $end
$var wire 1 ( sclk $end
$var wire 1 ) ss $end
$var wire 1 P en_reg_psel $end
$var wire 1 Q en_pwrite $end
$var wire 1 R en_psel_w $end
$var wire 1 S en_psel_r $end
$var wire 1 T en_prdata $end
$var wire 1 U en_penable_w $end
$var wire 1 V en_penable_r $end
$var wire 1 W en_paddr $end
$var wire 8 X b_pwdata [7:0] $end
$var reg 3 Y b_paddr [2:0] $end
$var reg 1 8 b_penable $end
$var reg 2 Z b_psel [1:0] $end
$var reg 1 2 b_pwrite $end
$var reg 4 [ counter_spi [3:0] $end
$var reg 1 \ off_signal $end
$var reg 16 ] reg_miso [15:0] $end
$var reg 16 ^ reg_mosi [15:0] $end
$var reg 2 _ reg_psel [1:0] $end
$upscope $end
$scope module pin0 $end
$var wire 1 ` a $end
$var wire 1 a oe $end
$var wire 1 b pad $end
$var wire 1 c pd $end
$var wire 1 d pu $end
$var wire 1 e y $end
$upscope $end
$scope module pin1 $end
$var wire 1 f a $end
$var wire 1 g oe $end
$var wire 1 h pad $end
$var wire 1 i pd $end
$var wire 1 j pu $end
$var wire 1 k y $end
$upscope $end
$scope module pin2 $end
$var wire 1 l a $end
$var wire 1 m oe $end
$var wire 1 n pad $end
$var wire 1 o pd $end
$var wire 1 p pu $end
$var wire 1 q y $end
$upscope $end
$scope module pin3 $end
$var wire 1 r a $end
$var wire 1 s oe $end
$var wire 1 t pad $end
$var wire 1 u pd $end
$var wire 1 v pu $end
$var wire 1 w y $end
$upscope $end
$scope module pin4 $end
$var wire 1 x a $end
$var wire 1 y oe $end
$var wire 1 z pad $end
$var wire 1 { pd $end
$var wire 1 | pu $end
$var wire 1 } y $end
$upscope $end
$scope module pin5 $end
$var wire 1 ~ a $end
$var wire 1 !" oe $end
$var wire 1 "" pad $end
$var wire 1 #" pd $end
$var wire 1 $" pu $end
$var wire 1 %" y $end
$upscope $end
$scope module pin6 $end
$var wire 1 &" a $end
$var wire 1 '" oe $end
$var wire 1 (" pad $end
$var wire 1 )" pd $end
$var wire 1 *" pu $end
$var wire 1 +" y $end
$upscope $end
$scope module pin7 $end
$var wire 1 ," a $end
$var wire 1 -" oe $end
$var wire 1 ." pad $end
$var wire 1 /" pd $end
$var wire 1 0" pu $end
$var wire 1 1" y $end
$upscope $end
$upscope $end
$scope task read_reg $end
$var reg 7 2" addr [6:0] $end
$var integer 32 3" i [31:0] $end
$upscope $end
$scope task write_reg $end
$var reg 7 4" addr [6:0] $end
$var reg 8 5" data [7:0] $end
$var integer 32 6" i [31:0] $end
$upscope $end
$upscope $end
$enddefinitions $end
#0
$dumpvars
bx 6"
bx 5"
bx 4"
bx 3"
bx 2"
x1"
z0"
z/"
x."
z-"
z,"
x+"
z*"
z)"
x("
z'"
z&"
x%"
z$"
z#"
x""
z!"
z~
x}
z|
z{
xz
zy
zx
xw
zv
zu
xt
zs
zr
xq
zp
zo
xn
zm
zl
xk
zj
zi
xh
zg
zf
xe
zd
zc
xb
za
z`
bx _
bx ^
bx ]
x\
bx [
bx Z
bx Y
bx X
xW
xV
0U
xT
xS
xR
xQ
xP
bx O
bx N
bx M
bx L
bx K
bx J
xI
bx H
bx G
b1 F
bx E
bx D
bx C
xB
bz A
x@
x?
bx >
bx =
bx <
bx ;
bx :
09
x8
bx 7
x6
15
bx 4
bx 3
x2
bx 1
bx 0
x/
bz .
bz -
0,
bz +
bz *
1)
0(
1'
b0 &
b0 %
x$
0#
0"
bx !
$end
#3000
b0 7
b0 H
b0 O
0?
0R
0S
0V
06
0B
0@
0Q
0W
0T
0P
b0 3
b0 C
b0 X
b0 ;
b0 J
b0 >
b0 M
b0 =
b0 L
b0 <
b0 K
0I
b0 G
b0 N
0\
b0 4
b0 D
b0 Z
08
b0 _
b0 :
b0 E
b0 Y
02
b0 [
b0 ^
b0 ]
05
0'
#6000
15
1'
#10000
1#
#20000
0#
#30000
1#
#40000
0#
#50000
1#
#60000
0#
#70000
1#
#80000
0#
#90000
1#
#100000
0#
#106000
b100000 2"
#110000
b0 3"
b10000000000000 &
0)
1#
#120000
0#
#130000
1Q
bz N
b1 [
1,
19
1(
1#
#140000
bx %
b100000000000000 &
0#
#150000
b1 3"
0,
09
0(
1#
#160000
0#
#170000
0Q
b10 [
bx0 %
1,
19
1(
1#
#180000
1"
bx %
b1000000000000000 &
0#
#190000
b10 3"
0,
09
0(
1#
#200000
0#
#210000
1P
b1 3
b1 C
b1 X
b11 [
b1 ^
bx0 %
1,
19
1(
1#
#220000
0"
bx %
b0 &
0#
#230000
b10 3
b10 C
b10 X
b1 _
b10 ^
b11 3"
0,
09
0(
1#
#240000
0#
#250000
0P
b100 [
bx0 %
1,
19
1(
1#
#260000
bx %
0#
#270000
b100 3
b100 C
b100 X
b100 ^
b100 3"
0,
09
0(
1#
#280000
0#
#290000
b101 [
bx0 %
1,
19
1(
1#
#300000
bx %
0#
#310000
b1000 3
b1000 C
b1000 X
b1000 ^
b101 3"
0,
09
0(
1#
#320000
0#
#330000
1S
1W
b110 [
bx0 %
1,
19
1(
1#
#340000
bx %
0#
#350000
b10000 3
b10000 C
b10000 X
b10000 ^
b110 3"
0,
09
0(
1#
#360000
0#
#370000
1?
0S
1V
1B
0W
b1 4
b1 D
b1 Z
b111 [
bx0 %
1,
19
1(
1#
#380000
bx %
0#
#390000
b100000 3
b100000 C
b100000 X
b100000 ^
b111 3"
0,
09
0(
1#
#400000
0#
#410000
1\
16
0V
b1 G
1I
18
b1000 [
bx0 %
1,
19
1(
1#
#420000
bx %
0#
#430000
b1000000 3
b1000000 C
b1000000 X
b1000000 ^
b1000 3"
0,
09
0(
1#
#440000
0#
#450000
06
0?
0B
1T
b0 G
b0 4
b0 D
b0 Z
08
b1001 [
bx0 %
1,
19
1(
1#
#460000
bx %
0#
#470000
b10000000 3
b10000000 C
b10000000 X
b10000000 ^
b1001 3"
0,
09
0(
1#
#480000
0#
#490000
0T
0I
0\
b1010 [
bx0 %
1,
19
1(
1#
#500000
bx %
0#
#510000
b0 3
b0 C
b0 X
b100000000 ^
b1010 3"
0,
09
0(
1#
#520000
0#
#530000
b1011 [
bx0 %
1,
19
1(
1#
#540000
bx %
0#
#550000
b1000000000 ^
b1011 3"
0,
09
0(
1#
#560000
0#
#570000
b1100 [
bx0 %
1,
19
1(
1#
#580000
bx %
0#
#590000
b10000000000 ^
b1100 3"
0,
09
0(
1#
#600000
0#
#610000
b1101 [
bx0 %
1,
19
1(
1#
#620000
bx %
0#
#630000
b100000000000 ^
b1101 3"
0,
09
0(
1#
#640000
0#
#650000
b1110 [
bx0 %
1,
19
1(
1#
#660000
bx %
0#
#670000
b1000000000000 ^
b1110 3"
0,
09
0(
1#
#680000
0#
#690000
b1111 [
bx0 %
1,
19
1(
1#
#700000
bx %
0#
#710000
b10000000000000 ^
b1111 3"
0,
09
0(
1#
#720000
0#
#730000
b0 [
bx0 %
1,
19
1(
1#
#740000
bx %
0#
#750000
b10000 3"
0,
09
0(
1#
#760000
0#
#770000
1)
1#
