GPIO_Expander/gpio_pad.v
module gpio_pad(
				inout 	pad,	
				input 	a,
				input	oe,				//driver enable signal
				input	pu,				//enabling the built-in resistive power pull-up
				input	pd,				//enabling the built-in resistive pull-up to ground
				output	y				//receiver output
				);			

assign (pull0, pull1) pad = (oe)? a : 1'bz;
assign (weak1, weak0) pad = (pu)? 1'b1 : 1'bz;
assign (weak1, weak0) pad = (pd)? 1'b0 : 1'bz;
assign y = pad;

endmodule

GPIO_Expander/gbas.v
 module gbas#(
 				parameter ADDR_BUNK 	= 1,
				parameter DATA_WIDTH 	= 8,
				parameter ADDR_WIDTH 	= 3,
				parameter PREADY_DEL 	= 0
				)(
				input 							pclk,
				input 							presetn,
				input 		[ADDR_WIDTH-1 : 0]	paddr,
				input 							pwrite,
				input 		[1:0]					pselx,
				input 							penable,
				input 		[DATA_WIDTH-1 : 0]	pwdata,
				output  reg	[DATA_WIDTH-1 : 0]	prdata,
				output 							pready,

				input		[7 : 0]            	y,
				output		[7 : 0]            	oe,
				output		[7 : 0]            	pu,
				output		[7 : 0]            	pd,
				output		[7 : 0]            	a
				);

reg [1:0] addr_bank = ADDR_BUNK;
wire sel_bank;
reg pwrite_reg;

assign sel_bank = (pselx == addr_bank)? 1'b1 : 1'b0;

reg [7:0] reg_oe;
reg [7:0] reg_pu;
reg [7:0] reg_pd;
reg [7:0] reg_a;
reg [7:0] reg_y;


reg 	[1:0] 	 counter;
wire 	[7:0]	 wire_y;
wire 			 r_counter_en;
wire 			 w_counter_en;
reg 			 pready_reg;
wire 			 write_en;
wire 			 read_en;

assign write_en = 	 pwrite & sel_bank;
assign read_en	=	!pwrite & sel_bank;

always @(posedge pclk or negedge presetn) begin
	if(!presetn) begin
		reg_oe	<= 8'h00;
		reg_pd	<= 8'h00;
		reg_pu	<= 8'h00;
		reg_a	<= 8'h00;
	end 
	else begin
		if(write_en & pready) begin
			case (paddr)
				3'h0 : reg_oe	<= pwdata;
				3'h1 : reg_pu	<= pwdata;
				3'h2 : reg_pd	<= pwdata;
				3'h3 : reg_a 	<= pwdata;
			endcase
		end
	end
end

always @(*) begin
	if(read_en & penable & pready) begin
		case (paddr)
			3'h0 : prdata <= reg_oe;
			3'h1 : prdata <= reg_pu;
			3'h2 : prdata <= reg_pd;
			3'h3 : prdata <= reg_a;
			3'h4 : prdata <= reg_y;
			default : prdata <= 8'h00;
		endcase
	end else 
		prdata <= 8'h00;
end

always @(posedge pclk or negedge presetn) begin
	if(!presetn) begin
		counter <= 2'b0;
		pready_reg <= 1'b0;
	end else begin
		if(read_en || write_en) begin
			pready_reg <= (PREADY_DEL == 0)? 1'b1 : (counter == PREADY_DEL)? 1'b1 : 1'b0;
			counter <= (pready_reg)? 2'b00 : counter + 1'b1;
		end else 
			pready_reg <= 1'b0; 
	end
end

always @(posedge pclk or  negedge presetn) begin
	if(!presetn)
		reg_y <= 1'b0;
	else 
		reg_y <= y;
end


assign pready = ((read_en && penable) || (write_en && penable))? pready_reg : 1'b0;

assign oe = reg_oe;
assign pu = reg_pu;
assign pd = reg_pd;
assign a  = reg_a;

endmodule

GPIO_Expander/spi2apb_bridge.v
module spi2apb_bridge #(
						parameter BANK_ADDR		= 	2,
						parameter DATA_WIDTH 	= 	8,
						parameter ADDR_WIDTH	=	3
						)(
                        input 			sclk,
                        input 			resetn,
                        input 			mosi,
                        input 			ss,
                        output 			miso,

                        input		[DATA_WIDTH-1 : 0]		b_prdata,
                        input								b_pready,
                        output								b_pclk,
                        output								b_presetn,
                        output		[DATA_WIDTH-1 : 0]		b_pwdata,
                        output	reg							b_pwrite,
                        output	reg	[BANK_ADDR-1	:	0]	b_psel,
                        output	reg							b_penable,
                        output	reg	[ADDR_WIDTH-1 : 0]		b_paddr
                        );

reg	[15: 0]	reg_mosi;
reg [15: 0]	reg_miso;

reg [3 : 0] counter_spi;
reg	[3 : 0] counter_apb;
reg [BANK_ADDR-1 : 0] reg_psel;
wire en_pwrite;
wire en_paddr;
wire en_psel;
wire en_penable_w;
wire en_penable_r;
wire en_psel_w;
wire en_psel_r;
reg off_signal;
reg en_pwdata;
reg en_sclk;
reg off_penable;

//spi interface
always @(posedge sclk or negedge resetn) begin
	if(!resetn) begin
		reg_mosi	<=	'h0;
        counter_spi	<=  'b00;
	end else begin
		if(!ss) begin
		 	reg_mosi [0] 	<= mosi;
		 	counter_spi 	<= counter_spi + 1'b1;
		end else 
			counter_spi <= 4'b0000;
	end
end

always @(negedge sclk or negedge resetn) begin
	if(!resetn) begin
		reg_miso 	<=	'h0;
	end else begin
		if(!ss && (counter_spi != 4'b0000)) begin
		reg_mosi	<= reg_mosi << 1'b1;
		reg_miso	<= reg_miso << 1'b1;
		end
	end
end

assign miso = reg_miso[15];

// apb interface
always @(negedge sclk or negedge resetn or posedge b_pready) begin
	if(!resetn) begin
		b_pwrite <= 1'b0; 
		b_paddr	 <= 7'h0;
		reg_psel  <= 'h0;
	end else begin
			b_pwrite <= (en_pwrite)? reg_mosi[0] : b_pwrite;
			b_paddr	 <= (en_paddr)?  reg_mosi[2:0] : b_paddr;
			reg_psel <=	(en_reg_psel)?  reg_mosi[1:0] : reg_psel;
	end
end

always @(posedge sclk or negedge resetn or negedge b_pready) begin
	if(!resetn) begin
		b_penable <= 1'b0;
		b_psel	  <= 8'h0;
	end else begin 

		if(ss) begin
			b_penable <= (!b_pready)? 1'b0 : b_penable;
			b_psel <= (!b_pready)? 1'b0 : b_penable;
		end else begin 
			b_penable <= (en_penable_w || en_penable_r)?  1'b1 : (off_signal)? 1'b0 : b_penable;
			b_psel	 <= (en_psel_r || en_psel_w)? reg_psel : (off_signal)? 'h0 : b_psel;
		end
	end
end


always @(posedge sclk or negedge resetn or posedge b_pready) begin
	if(!resetn) begin
		off_signal <= 1'b0;
	end else begin
		off_signal <= (b_pready)? 1'b1 : 1'b0; 
	end
end


assign 	b_pclk			= sclk;
assign	en_pwrite		= (counter_spi == 4'h1)? 1'b1 : 1'b0;
assign  en_paddr		= (counter_spi == 4'h6)? 1'b1 : 1'b0;		
assign  en_prdata		= (counter_spi == 4'h9)? 1'b1 : 1'b0;
assign 	en_reg_psel		= (counter_spi == 4'h3)? 1'b1 : 1'b0;

assign  en_psel_w			= (counter_spi == 4'he && b_pwrite)? 1'b1 : 1'b0;
assign  en_psel_r			= (counter_spi == 4'h6 && !b_pwrite)? 1'b1 : 1'b0;

assign	en_penable_w	= (counter_spi == 4'hf && b_pwrite && !ss)? 1'b1 : 1'b0;
assign	en_penable_r	= ((counter_spi == 4'h7) && !b_pwrite)? 1'b1 : 1'b0;	

assign  b_presetn 	= resetn; 
assign  b_pwdata    = reg_mosi[7:0];


always @(negedge sclk) begin
	if(!b_pwrite && b_penable)
		reg_miso [15:8] <= b_prdata; 
end


endmodule

GPIO_Expander/gpio_expander.v
`include "gpio_pad.v"
`include "gbas.v"
`include "spi2apb_bridge.v"

module gpio_expander#(
						parameter BANK_NUM = 2,
						parameter ADDR_WIDTH = 7,
						parameter PADDR_WIDTH = 3,
						parameter DATA_WIDTH = 8
						)(
						input	sclk,
						input	resetn,
						output	miso,
						input	mosi,
						input	ss,
						
						output [7:0]	pad);

wire 						e_pclk_a 	;
wire 						e_pclk_b 	;
wire 						e_presetn  	;
wire	[PADDR_WIDTH-1:0]	e_paddr  	;
wire 						e_pwrite  	;
wire 	[1:0]	 			e_psel 	 	;
wire 						e_penable  	;
wire 	[DATA_WIDTH-1:0] 	e_pwdata	;
wire 						e_pready  	;
wire 	[DATA_WIDTH-1:0] 	e_prdata  	;


wire [7:0] 	e_oe;
wire [7:0]	e_pu;
wire [7:0]	e_pd;
wire [7:0]	e_a;
wire [7:0]	e_y;

assign #(0) e_pclk_b = e_pclk_a;

spi2apb_bridge bridge(	.sclk(sclk),		.resetn(resetn),		.b_pready(e_pready),	.b_prdata(e_prdata),	
						.b_pclk(e_pclk_a),	.b_presetn(e_presetn), 	.b_paddr(e_paddr),		.b_pwrite(e_pwrite),	
						.b_psel(e_psel),	.b_penable(e_penable),	.b_pwdata(e_pwdata),						
						.mosi(mosi), 		.miso(miso),			.ss(ss));

gbas 			bank0(	.paddr(e_paddr),	.pready(e_pready),		.prdata(e_prdata),	
						.pclk(e_pclk_b),	.pwdata(e_pwdata),		.pwrite(e_pwrite),
						.pselx(e_psel),		.penable(e_penable),	.presetn(e_presetn));

gbas 			bank1(	.paddr(e_paddr),	.pready(e_pready),		.prdata(e_prdata),	
						.pclk(e_pclk),	 	.pwdata(e_pwdata),		.pwrite(e_pwrite),
						.pselx(e_psel),		.penable(e_penable),	.presetn(e_presetn));


gpio_pad 		pin0(	.oe(e_oe[0]),		.a(e_a[0]),				.pd(e_pd[0]),
						.pu(e_pu[0]),		.y(e_y[0]),				.pad(pad[0]));

gpio_pad 		pin1(	.oe(e_oe[1]),		.a(e_a[1]),				.pd(e_pd[1]),
						.pu(e_pu[1]),		.y(e_y[1]),				.pad(pad[1]));

gpio_pad 		pin2(	.oe(e_oe[2]),		.a(e_a[2]),				.pd(e_pd[2]),
						.pu(e_pu[2]),		.y(e_y[2]),				.pad(pad[2]));

gpio_pad 		pin3(	.oe(e_oe[3]),		.a(e_a[3]),				.pd(e_pd[3]),
						.pu(e_pu[3]),		.y(e_y[3]),				.pad(pad[3]));

gpio_pad 		pin4(	.oe(e_oe[4]),		.a(e_a[4]),				.pd(e_pd[4]),
						.pu(e_pu[4]),		.y(e_y[4]),				.pad(pad[4]));

gpio_pad 		pin5(	.oe(e_oe[5]),		.a(e_a[5]),				.pd(e_pd[5]),
						.pu(e_pu[5]),		.y(e_y[5]),				.pad(pad[5]));

gpio_pad 		pin6(	.oe(e_oe[6]),		.a(e_a[6]),				.pd(e_pd[6]),
						.pu(e_pu[6]),		.y(e_y[6]),				.pad(pad[6]));

gpio_pad 		pin7(	.oe(e_oe[7]),		.a(e_a[7]),				.pd(e_pd[7]),
						.pu(e_pu[7]),		.y(e_y[7]),				.pad(pad[7]));

/*
gpio_pad 		pin8(	.oe(e_oe[8]),		.a(e_a[8])				.pd(e_pd[8])
						.pu(e_pu[8]),		.y(e_y[8]),				.pad(pad[8]));

gpio_pad 		pin9(	.oe(e_oe[9]),		.a(e_a[9])				.pd(e_pd[9])
						.pu(e_pu[9]),		.y(e_y[9]),				.pad(pad[9]));

gpio_pad 		pin10(	.oe(e_oe[10]),		.a(e_a[10])				.pd(e_pd[10])
						.pu(e_pu[10]),		.y(e_y[10]),			.pad(pad[10]));

gpio_pad 		pin11(	.oe(e_oe[11]),		.a(e_a[11])				.pd(e_pd[11])
						.pu(e_pu[11]),		.y(e_y[11]),			.pad(pad[11]));

gpio_pad 		pin12(	.oe(e_oe[12]),		.a(e_a[12])				.pd(e_pd[12])
						.pu(e_pu[12]),		.y(e_y[12]),			.pad(pad[12]));

gpio_pad 		pin13(	.oe(e_oe[13]),		.a(e_a[13])				.pd(e_pd[13])
						.pu(e_pu[13]),		.y(e_y[13]),			.pad(pad[13]));

gpio_pad 		pin14(	.oe(e_oe[14]),		.a(e_a[14])				.pd(e_pd[14])
						.pu(e_pu[14]),		.y(e_y[14]),			.pad(pad[14]));

gpio_pad 		pin15(	.oe(e_oe[15]),		.a(e_a[15])				.pd(e_pd[15])
						.pu(e_pu[15]),		.y(e_y[15]),			.pad(pad[15]));
*/

endmodule

GPIO_Expander/gpio_expander_tb.v
`timescale 1ns/1ps
//`include "gpio_pad.v"
//`include "gbas.v"
//`include "spi2apb_bridge.v"
`include "gpio_expander.v"

module gpio_expander_tb#(
			        		parameter BANK_NUM      = 	2,
							parameter DATA_WIDTH 	= 	16,
                 			parameter PDATA_WIDTH 	=  	8,
							parameter ADDR_WIDTH	=	7,
                  			parameter PADDR_WIDTH   = 	3
				    		)(
				    		);

reg clk;
reg	sclk;
reg	resetn;
wire	miso_tb;
wire    mosi_tb;
reg	ss;
						
wire [7:0]	pad_tb;

reg [15:0] reg_mosi_tb;
reg [15:0] reg_miso_tb;


gpio_expander i0(.sclk(sclk), .resetn(resetn), .miso(miso_tb), .mosi(mosi_tb), .ss(ss), .pad(pad_tb));
//gbas bank();
//gpio_pad pins();

function automatic reg [15:0] spi_xfer;
input 	[DATA_WIDTH-1:0] 	data_in;
reg 	[15:0] 				rd_mosi;
        begin
                reg_mosi_tb = data_in << 1;
                rd_mosi[15:1] = 'h0;
                rd_mosi[0] = miso_tb;
                spi_xfer = rd_mosi;
        end
endfunction


assign mosi_tb = reg_mosi_tb[15];

task write_reg(input [ADDR_WIDTH-1:0] addr, input [PDATA_WIDTH-1:0] data);
integer i;
        begin

             @(posedge clk);
                ss = 0;
                reg_mosi_tb [15] = 1;  
                reg_mosi_tb [14:8] = addr;
                reg_mosi_tb [7:0] = data;  

                for(i = 0; i < 16; i = i + 1) begin
                        @(posedge clk);
                        sclk = !sclk;
                        reg_miso_tb = reg_miso_tb << 1;
                        #10
                        reg_miso_tb =  reg_miso_tb + spi_xfer(reg_mosi_tb);
                        @(posedge clk);
                        sclk = !sclk;
                end
                @(posedge clk);
                ss = 1;
        end
endtask

task read_reg(input [ADDR_WIDTH-1:0] addr);
integer i;
        begin

             @(posedge clk);
                ss = 0;
                reg_mosi_tb [15] = 0;  
                reg_mosi_tb [14:8] = addr;
                reg_mosi_tb [7:0] = 'h0;  

                for(i = 0; i < 16; i = i + 1) begin
                        @(posedge clk);
                        sclk = !sclk;
                        reg_miso_tb = reg_miso_tb << 1;
                        #10
                        reg_miso_tb =  reg_miso_tb + spi_xfer(reg_mosi_tb);
                        @(posedge clk);
                        sclk = !sclk;
                end
                @(posedge clk);
                ss = 1;
        end
endtask

initial begin
        clk = 0;
        sclk = 0;
        resetn = 1;
        ss = 1;
        reg_mosi_tb = 16'h0000;
        reg_miso_tb = 16'h0000;
end

initial begin
        $dumpfile("gpio_expander_tb.vcd");
        $dumpvars(0, gpio_expander_tb);
        $display("Module %m") ;
        #3 resetn = 0;
        #3 resetn = 1;
        #100
        $display("Write: ") ;
        write_reg(7'h20, 8'h81);
        #100
        $display("Read: ") ;
        read_reg(7'h20);
        #500 $finish;
end

always #10 clk = !clk;
endmodule

GPIO_Expander/gpio_expander_tb.vcd
$date
	Wed Mar 09 10:42:10 2022
$end
$version
	Icarus Verilog
$end
$timescale
	1ps
$end
$scope module gpio_expander_tb $end
$var wire 8 ! pad_tb [7:0] $end
$var wire 1 " mosi_tb $end
$var wire 1 # miso_tb $end
$var reg 1 $ clk $end
$var reg 16 % reg_miso_tb [15:0] $end
$var reg 16 & reg_mosi_tb [15:0] $end
$var reg 1 ' resetn $end
$var reg 1 ( sclk $end
$var reg 1 ) ss $end
$scope function spi_xfer $end
$upscope $end
$scope module i0 $end
$var wire 8 * e_a [7:0] $end
$var wire 8 + e_oe [7:0] $end
$var wire 1 , e_pclk $end
$var wire 1 - e_pclk_b $end
$var wire 8 . e_pd [7:0] $end
$var wire 8 / e_prdata [7:0] $end
$var wire 1 0 e_pready $end
$var wire 8 1 e_pu [7:0] $end
$var wire 1 " mosi $end
$var wire 8 2 pad [7:0] $end
$var wire 1 ' resetn $end
$var wire 1 ( sclk $end
$var wire 1 ) ss $end
$var wire 1 # miso $end
$var wire 8 3 e_y [7:0] $end
$var wire 1 4 e_pwrite $end
$var wire 8 5 e_pwdata [7:0] $end
$var wire 2 6 e_psel [1:0] $end
$var wire 1 7 e_presetn $end
$var wire 1 8 e_penable $end
$var wire 1 9 e_pclk_a $end
$var wire 3 : e_paddr [2:0] $end
$scope module bank0 $end
$var wire 8 ; a [7:0] $end
$var wire 8 < oe [7:0] $end
$var wire 1 - pclk $end
$var wire 8 = pd [7:0] $end
$var wire 1 0 pready $end
$var wire 8 > pu [7:0] $end
$var wire 1 ? read_en $end
$var wire 1 @ write_en $end
$var wire 8 A y [7:0] $end
$var wire 1 B sel_bank $end
$var wire 1 4 pwrite $end
$var wire 8 C pwdata [7:0] $end
$var wire 2 D pselx [1:0] $end
$var wire 1 7 presetn $end
$var wire 1 8 penable $end
$var wire 3 E paddr [2:0] $end
$var reg 2 F addr_bank [1:0] $end
$var reg 2 G counter [1:0] $end
$var reg 8 H prdata [7:0] $end
$var reg 1 I pready_reg $end
$var reg 8 J reg_a [7:0] $end
$var reg 8 K reg_oe [7:0] $end
$var reg 8 L reg_pd [7:0] $end
$var reg 8 M reg_pu [7:0] $end
$var reg 8 N reg_y [7:0] $end
$upscope $end
$scope module bank1 $end
$var wire 8 O a [7:0] $end
$var wire 8 P oe [7:0] $end
$var wire 1 , pclk $end
$var wire 8 Q pd [7:0] $end
$var wire 1 0 pready $end
$var wire 8 R pu [7:0] $end
$var wire 1 S read_en $end
$var wire 1 T write_en $end
$var wire 8 U y [7:0] $end
$var wire 1 V sel_bank $end
$var wire 1 4 pwrite $end
$var wire 8 W pwdata [7:0] $end
$var wire 2 X pselx [1:0] $end
$var wire 1 7 presetn $end
$var wire 1 8 penable $end
$var wire 3 Y paddr [2:0] $end
$var reg 2 Z addr_bank [1:0] $end
$var reg 2 [ counter [1:0] $end
$var reg 8 \ prdata [7:0] $end
$var reg 1 ] pready_reg $end
$var reg 8 ^ reg_a [7:0] $end
$var reg 8 _ reg_oe [7:0] $end
$var reg 8 ` reg_pd [7:0] $end
$var reg 8 a reg_pu [7:0] $end
$var reg 8 b reg_y [7:0] $end
$upscope $end
$scope module bridge $end
$var wire 1 9 b_pclk $end
$var wire 8 c b_prdata [7:0] $end
$var wire 1 0 b_pready $end
$var wire 1 7 b_presetn $end
$var wire 1 " mosi $end
$var wire 1 ' resetn $end
$var wire 1 ( sclk $end
$var wire 1 ) ss $end
$var wire 1 # miso $end
$var wire 1 d en_reg_psel $end
$var wire 1 e en_pwrite $end
$var wire 1 f en_psel_w $end
$var wire 1 g en_psel_r $end
$var wire 1 h en_prdata $end
$var wire 1 i en_penable_w $end
$var wire 1 j en_penable_r $end
$var wire 1 k en_paddr $end
$var wire 8 l b_pwdata [7:0] $end
$var reg 3 m b_paddr [2:0] $end
$var reg 1 8 b_penable $end
$var reg 2 n b_psel [1:0] $end
$var reg 1 4 b_pwrite $end
$var reg 4 o counter_spi [3:0] $end
$var reg 1 p off_signal $end
$var reg 16 q reg_miso [15:0] $end
$var reg 16 r reg_mosi [15:0] $end
$var reg 2 s reg_psel [1:0] $end
$upscope $end
$scope module pin0 $end
$var wire 1 t a $end
$var wire 1 u oe $end
$var wire 1 v pad $end
$var wire 1 w pd $end
$var wire 1 x pu $end
$var wire 1 y y $end
$upscope $end
$scope module pin1 $end
$var wire 1 z a $end
$var wire 1 { oe $end
$var wire 1 | pad $end
$var wire 1 } pd $end
$var wire 1 ~ pu $end
$var wire 1 !" y $end
$upscope $end
$scope module pin2 $end
$var wire 1 "" a $end
$var wire 1 #" oe $end
$var wire 1 $" pad $end
$var wire 1 %" pd $end
$var wire 1 &" pu $end
$var wire 1 '" y $end
$upscope $end
$scope module pin3 $end
$var wire 1 (" a $end
$var wire 1 )" oe $end
$var wire 1 *" pad $end
$var wire 1 +" pd $end
$var wire 1 ," pu $end
$var wire 1 -" y $end
$upscope $end
$scope module pin4 $end
$var wire 1 ." a $end
$var wire 1 /" oe $end
$var wire 1 0" pad $end
$var wire 1 1" pd $end
$var wire 1 2" pu $end
$var wire 1 3" y $end
$upscope $end
$scope module pin5 $end
$var wire 1 4" a $end
$var wire 1 5" oe $end
$var wire 1 6" pad $end
$var wire 1 7" pd $end
$var wire 1 8" pu $end
$var wire 1 9" y $end
$upscope $end
$scope module pin6 $end
$var wire 1 :" a $end
$var wire 1 ;" oe $end
$var wire 1 <" pad $end
$var wire 1 =" pd $end
$var wire 1 >" pu $end
$var wire 1 ?" y $end
$upscope $end
$scope module pin7 $end
$var wire 1 @" a $end
$var wire 1 A" oe $end
$var wire 1 B" pad $end
$var wire 1 C" pd $end
$var wire 1 D" pu $end
$var wire 1 E" y $end
$upscope $end
$upscope $end
$scope task read_reg $end
$var reg 7 F" addr [6:0] $end
$var integer 32 G" i [31:0] $end
$upscope $end
$scope task write_reg $end
$var reg 7 H" addr [6:0] $end
$var reg 8 I" data [7:0] $end
$var integer 32 J" i [31:0] $end
$upscope $end
$upscope $end
$enddefinitions $end
#0
$dumpvars
bx J"
bx I"
bx H"
bx G"
bx F"
xE"
zD"
zC"
xB"
zA"
z@"
x?"
z>"
z="
x<"
z;"
z:"
x9"
z8"
z7"
x6"
z5"
z4"
x3"
z2"
z1"
x0"
z/"
z."
x-"
z,"
z+"
x*"
z)"
z("
x'"
z&"
z%"
x$"
z#"
z""
x!"
z~
z}
x|
z{
zz
xy
zx
zw
xv
zu
zt
bx s
bx r
bx q
xp
bx o
bx n
bx m
bx l
xk
xj
0i
xh
xg
xf
xe
xd
bx c
bx b
bx a
bx `
bx _
bx ^
x]
bx \
bx [
b1 Z
bx Y
bx X
bx W
xV
bz U
xT
xS
bx R
bx Q
bx P
bx O
bx N
bx M
bx L
bx K
bx J
xI
bx H
bx G
b1 F
bx E
bx D
bx C
xB
bz A
x@
x?
bx >
bx =
bx <
bx ;
bx :
09
x8
17
bx 6
bx 5
x4
bx 3
bx 2
bz 1
x0
bx /
bz .
0-
z,
bz +
bz *
1)
0(
1'
b0 &
b0 %
0$
x#
0"
bx !
$end
#3000
b0 /
b0 c
b0 H
b0 \
0S
0?
0f
0g
0j
00
0V
0B
0T
0@
0#
0e
0k
0h
0d
b0 5
b0 C
b0 W
b0 l
b0 ;
b0 J
b0 >
b0 M
b0 =
b0 L
b0 <
b0 K
0I
b0 G
b0 N
b0 O
b0 ^
b0 R
b0 a
b0 Q
b0 `
b0 P
b0 _
0]
b0 [
b0 b
0p
b0 6
b0 D
b0 X
b0 n
08
b0 s
b0 :
b0 E
b0 Y
b0 m
04
b0 q
b0 o
b0 r
07
0'
#6000
17
1'
#10000
1$
#20000
0$
#30000
1$
#40000
0$
#50000
1$
#60000
0$
#70000
1$
#80000
0$
#90000
1$
#100000
0$
#106000
b10000001 I"
b100000 H"
#110000
1"
b0 J"
b1010000010000001 &
0)
1$
#120000
0$
#130000
1e
b1 5
b1 C
b1 W
b1 l
bz N
b1 o
b1 r
1-
19
1(
1$
#140000
0"
b100000100000010 &
0$
#150000
b10 5
b10 C
b10 W
b10 l
14
b10 r
b1 J"
0-
09
0(
1$
#160000
0$
#170000
0e
b10 o
1-
19
1(
1$
#180000
1"
b1000001000000100 &
0$
#190000
b100 5
b100 C
b100 W
b100 l
b100 r
b10 J"
0-
09
0(
1$
#200000
0$
#210000
1d
b101 5
b101 C
b101 W
b101 l
b11 o
b101 r
1-
19
1(
1$
#220000
0"
b10000001000 &
0$
#230000
b1010 5
b1010 C
b1010 W
b1010 l
b1 s
b1010 r
b11 J"
0-
09
0(
1$
#240000
0$
#250000
0d
b100 o
1-
19
1(
1$
#260000
b100000010000 &
0$
#270000
b10100 5
b10100 C
b10100 W
b10100 l
b10100 r
b100 J"
0-
09
0(
1$
#280000
0$
#290000
b101 o
1-
19
1(
1$
#300000
b1000000100000 &
0$
#310000
b101000 5
b101000 C
b101000 W
b101000 l
b101000 r
b101 J"
0-
09
0(
1$
#320000
0$
#330000
1k
b110 o
1-
19
1(
1$
#340000
b10000001000000 &
0$
#350000
b1010000 5
b1010000 C
b1010000 W
b1010000 l
b1010000 r
b110 J"
0-
09
0(
1$
#360000
0$
#370000
0k
b111 o
1-
19
1(
1$
#380000
b100000010000000 &
0$
#390000
b10100000 5
b10100000 C
b10100000 W
b10100000 l
b10100000 r
b111 J"
0-
09
0(
1$
#400000
0$
#410000
b1000 o
1-
19
1(
1$
#420000
1"
b1000000100000000 &
0$
#430000
b1000000 5
b1000000 C
b1000000 W
b1000000 l
b101000000 r
b1000 J"
0-
09
0(
1$
#440000
0$
#450000
1h
b1000001 5
b1000001 C
b1000001 W
b1000001 l
b1001 o
b101000001 r
1-
19
1(
1$
#460000
0"
b1000000000 &
0$
#470000
b10000010 5
b10000010 C
b10000010 W
b10000010 l
b1010000010 r
b1001 J"
0-
09
0(
1$
#480000
0$
#490000
0h
b1010 o
1-
19
1(
1$
#500000
b10000000000 &
0$
#510000
b100 5
b100 C
b100 W
b100 l
b10100000100 r
b1010 J"
0-
09
0(
1$
#520000
0$
#530000
b1011 o
1-
19
1(
1$
#540000
b100000000000 &
0$
#550000
b1000 5
b1000 C
b1000 W
b1000 l
b101000001000 r
b1011 J"
0-
09
0(
1$
#560000
0$
#570000
b1100 o
1-
19
1(
1$
#580000
b1000000000000 &
0$
#590000
b10000 5
b10000 C
b10000 W
b10000 l
b1010000010000 r
b1100 J"
0-
09
0(
1$
#600000
0$
#610000
b1101 o
1-
19
1(
1$
#620000
b10000000000000 &
0$
#630000
b100000 5
b100000 C
b100000 W
b100000 l
b10100000100000 r
b1101 J"
0-
09
0(
1$
#640000
0$
#650000
1f
b1110 o
1-
19
1(
1$
#660000
b100000000000000 &
0$
#670000
b1000000 5
b1000000 C
b1000000 W
b1000000 l
b101000001000000 r
b1110 J"
0-
09
0(
1$
#680000
0$
#690000
1i
1T
1@
0f
1V
1B
b1 6
b1 D
b1 X
b1 n
b1111 o
1-
19
1(
1$
#700000
1"
b1000000000000000 &
0$
#710000
b10000000 5
b10000000 C
b10000000 W
b10000000 l
b1010000010000000 r
b1111 J"
0-
09
0(
1$
#720000
0$
#730000
xp
x0
0i
b10000001 5
b10000001 C
b10000001 W
b10000001 l
b1 G
1I
18
b0 o
b1010000010000001 r
1-
19
1(
1$
#740000
0"
b0 &
0$
#750000
b10000 J"
0-
09
0(
1$
#760000
0$
#770000
1)
1$
#780000
0$
#790000
1$
#800000
0$
#810000
1$
#820000
0$
#830000
1$
#840000
0$
#850000
1$
#860000
0$
#870000
b0 G"
b10000000000000 &
0)
1$
b100000 F"
#880000
0$
#890000
xT
x@
xV
xB
1e
b10000000 5
b10000000 C
b10000000 W
b10000000 l
b0 G
b0x 6
b0x D
b0x X
b0x n
x8
b1 o
b1010000010000000 r
1-
19
1(
1$
#900000
b100000000000000 &
0$
#910000
xS
0T
x?
0@
b0 5
b0 C
b0 W
b0 l
04
b100000100000000 r
b1 G"
0-
09
0(
1$
#920000
0$
#930000
00
0e
0I
b10 o
1-
19
1(
1$
#940000
1"
b1000000000000000 &
0$
#950000
b1000001000000000 r
b10 G"
0-
09
0(
1$
#960000
0$
#970000
1d
b1 5
b1 C
b1 W
b1 l
0p
b11 o
b1000001000000001 r
1-
19
1(
1$
#980000
0"
b0 &
0$
#990000
b10 5
b10 C
b10 W
b10 l
b10000000010 r
b11 G"
0-
09
0(
1$
#1000000
0$
#1010000
0d
b100 o
1-
19
1(
1$
#1020000
0$
#1030000
b100 5
b100 C
b100 W
b100 l
b100000000100 r
b100 G"
0-
09
0(
1$
#1040000
0$
#1050000
b101 o
1-
19
1(
1$
#1060000
0$
#1070000
b1000 5
b1000 C
b1000 W
b1000 l
b1000000001000 r
b101 G"
0-
09
0(
1$
#1080000
0$
#1090000
1g
1k
b110 o
1-
19
1(
1$
#1100000
0$
#1110000
b10000 5
b10000 C
b10000 W
b10000 l
b10000000010000 r
b110 G"
0-
09
0(
1$
#1120000
0$
#1130000
1S
1?
0g
1j
1V
1B
0k
b1 6
b1 D
b1 X
b1 n
b111 o
1-
19
1(
1$
#1140000
0$
#1150000
b100000 5
b100000 C
b100000 W
b100000 l
b100000000100000 r
b111 G"
0-
09
0(
1$
#1160000
0$
#1170000
xp
0j
x0
b1 G
1I
18
b1000 o
1-
19
1(
1$
#1180000
0$
#1190000
b1000000 5
b1000000 C
b1000000 W
b1000000 l
b1000000001000000 r
b1000 G"
0-
09
0(
1$
#1200000
0$
#1210000
xS
x?
xV
xB
1h
b0 G
b0x 6
b0x D
b0x X
b0x n
x8
b1001 o
1-
19
1(
1$
#1220000
0$
#1230000
b10000000 5
b10000000 C
b10000000 W
b10000000 l
b10000000 r
b1001 G"
0-
09
0(
1$
#1240000
0$
#1250000
00
0h
0I
b1010 o
1-
19
1(
1$
#1260000
0$
#1270000
b0 5
b0 C
b0 W
b0 l
b100000000 r
b1010 G"
0-
09
0(
1$
#1280000
0$
#1290000
0p
b1011 o
1-
19
1(
1$
#1300000
0$
#1310000
b1000000000 r
b1011 G"
0-
09
0(
1$
#1320000
0$
#1330000
b1100 o
1-
19
1(
1$
#1340000
0$
#1350000
b10000000000 r
b1100 G"
0-
09
0(
1$
#1360000
0$
#1370000
b1101 o
1-
19
1(
1$
#1380000
0$
#1390000
b100000000000 r
b1101 G"
0-
09
0(
1$
#1400000
0$
#1410000
b1110 o
1-
19
1(
1$
#1420000
0$
#1430000
b1000000000000 r
b1110 G"
0-
09
0(
1$
#1440000
0$
#1450000
b1111 o
1-
19
1(
1$
#1460000
0$
#1470000
b10000000000000 r
b1111 G"
0-
09
0(
1$
#1480000
0$
#1490000
b0 o
1-
19
1(
1$
#1500000
0$
#1510000
b10000 G"
0-
09
0(
1$
#1520000
0$
#1530000
1)
1$
