GPIO_PAD/GPIO_PAD.v
module GPIO_PAD(
				inout 	pad,	
				input 	a,
				input	oe,				//driver enable signal
				input	pu,				//enabling the built-in resistive power pull-up
				input	pd,				//enabling the built-in resistive pull-up to ground
				output	y				//receiver output
				);			

assign (pull0, pull1) pad = (oe)? a : 1'bz;
assign (weak1, weak0) pad = (pu)? 1'b1 : 1'bz;
assign (weak1, weak0) pad = (pd)? 1'b0 : 1'bz;
assign y = pad;

endmodule

GPIO_PAD/GPIO_PAD_tb.v
`timescale 1ns/1ps
`include "GPIO_PAD.v"

module GPIO_PAD_tb();
wire	[1:0] pad;
reg    padi;   	

reg 	[1:0] a;
reg	    [1:0] oe;			
reg	    [1:0] pu;				
reg	    [1:0] pd;				
wire    [1:0] y;

assign (strong0, strong1) pad[1] = (padi)? 1'b1: 1'b0;

GPIO_PAD n_driver(  .pad(pad[0]), .a(a[0]), .oe(oe[0]),
                .pu(pu[0]), .pd(pd[0]), .y(y[0]));

GPIO_PAD with_driver(  .pad(pad[1]), .a(a[1]), .oe(oe[1]),
                .pu(pu[1]), .pd(pd[1]), .y(y[1]));

task no_drive();
    reg [3:0] tb_reg;
    integer i;
	begin 

        tb_reg = 4'b0000;

        for(i = 0; i < 16; i = i + 1) begin
            #30
            tb_reg = tb_reg + 1'b1;

            a[0] = tb_reg[3];
            oe[0] = tb_reg[2];
            pu[0] = tb_reg[1];
            pd[0] = tb_reg[0];
            
            $display($time, " ns pad = %v y = %v a = %v oe = %v pu = %v pd = %v ", pad[0], a[0], oe[0], pu[0], pd[0], y[0]);
        end
	end
endtask

task drive();
    reg [4:0] tb_reg;
    integer i;
	begin 

        tb_reg = 5'b00000;

        for(i = 0; i < 32; i = i + 1) begin
            #30
            tb_reg = tb_reg + 1'b1;
            
            a[1] = tb_reg[4];
            oe[1] = tb_reg[3];
            pu[1] = tb_reg[2];
            pd[1] = tb_reg[1];
            padi = tb_reg[0];
            
             $display($time, " ns pad = %v y = %v a = %v oe = %v pu = %v pd = %v", pad[1], a[1], oe[1], pu[1], pd[1], y[1]);

        end
	end
endtask

initial begin
    $dumpfile("hello_tb.vcd");
    $dumpvars(0, GPIO_PAD_tb);
    $display("Module %m") ;
        a = 0;
        oe = 0;
        pu = 0;
        pd = 0;
        padi = 0;
     $display("no drive:") ;
        no_drive();
    #100;
    $display("with drive:") ;
        drive();

    $display("Test complet");
end

endmodule

GPIO_PAD/hello_tb.vcd
$date
	Mon Feb 21 12:58:44 2022
$end
$version
	Icarus Verilog
$end
$timescale
	1ps
$end
$scope module GPIO_PAD_tb $end
$var wire 2 ! pad [1:0] $end
$var wire 2 " y [1:0] $end
$var reg 2 # a [1:0] $end
$var reg 2 $ oe [1:0] $end
$var reg 1 % padi $end
$var reg 2 & pd [1:0] $end
$var reg 2 ' pu [1:0] $end
$scope module n_driver $end
$var wire 1 ( a $end
$var wire 1 ) oe $end
$var wire 1 * pad $end
$var wire 1 + pd $end
$var wire 1 , pu $end
$var wire 1 - y $end
$upscope $end
$scope module with_driver $end
$var wire 1 . a $end
$var wire 1 / oe $end
$var wire 1 0 pad $end
$var wire 1 1 pd $end
$var wire 1 2 pu $end
$var wire 1 3 y $end
$upscope $end
$scope task drive $end
$var reg 5 4 tb_reg [4:0] $end
$var integer 32 5 i [31:0] $end
$upscope $end
$scope task no_drive $end
$var reg 4 6 tb_reg [3:0] $end
$var integer 32 7 i [31:0] $end
$upscope $end
$upscope $end
$enddefinitions $end
#0
$dumpvars
b0 7
b0 6
bx 5
bx 4
03
02
01
00
0/
0.
z-
0,
0+
z*
0)
0(
b0 '
b0 &
0%
b0 $
b0 #
b0z "
b0z !
$end
#30000
b0 "
0-
0*
b0 !
1+
b1 7
b1 &
b1 6
#60000
b1 "
1-
1*
b1 !
0+
1,
b10 7
b0 &
b1 '
b10 6
#90000
b0x "
x-
x*
b0x !
1+
b11 7
b1 &
b11 6
#120000
b0 "
0-
0*
b0 !
0+
0,
1)
b100 7
b0 &
b0 '
b1 $
b100 6
#150000
1+
b101 7
b1 &
b101 6
#180000
0+
1,
b110 7
b0 &
b1 '
b110 6
#210000
1+
b111 7
b1 &
b111 6
#240000
b0z "
z-
z*
b0z !
0+
0,
0)
1(
b1000 7
b0 &
b0 '
b0 $
b1 #
b1000 6
#270000
b0 "
0-
0*
b0 !
1+
b1001 7
b1 &
b1001 6
#300000
b1 "
1-
1*
b1 !
0+
1,
b1010 7
b0 &
b1 '
b1010 6
#330000
b0x "
x-
x*
b0x !
1+
b1011 7
b1 &
b1011 6
#360000
b1 "
1-
1*
b1 !
0+
0,
1)
b1100 7
b0 &
b0 '
b1 $
b1100 6
#390000
1+
b1101 7
b1 &
b1101 6
#420000
0+
1,
b1110 7
b0 &
b1 '
b1110 6
#450000
1+
b1111 7
b1 &
b1111 6
#480000
b0z "
z-
z*
b0z !
0+
0,
0)
0(
b10000 7
b0 &
b0 '
b0 $
b0 #
b0 6
#580000
b0 5
b0 4
#610000
b1z "
13
10
b1z !
b1 5
1%
b1 4
#640000
b0z "
03
00
b0z !
11
b10 5
0%
b10 &
b10 4
#670000
b1z "
13
10
b1z !
b11 5
1%
b11 4
#700000
b0z "
03
00
b0z !
01
12
b100 5
0%
b0 &
b10 '
b100 4
#730000
b1z "
13
10
b1z !
b101 5
1%
b101 4
#760000
b0z "
03
00
b0z !
11
b110 5
0%
b10 &
b110 4
#790000
b1z "
13
10
b1z !
b111 5
1%
b111 4
#820000
b0z "
03
00
b0z !
01
02
1/
b1000 5
0%
b0 &
b0 '
b10 $
b1000 4
#850000
b1z "
13
10
b1z !
b1001 5
1%
b1001 4
#880000
b0z "
03
00
b0z !
11
b1010 5
0%
b10 &
b1010 4
#910000
b1z "
13
10
b1z !
b1011 5
1%
b1011 4
#940000
b0z "
03
00
b0z !
01
12
b1100 5
0%
b0 &
b10 '
b1100 4
#970000
b1z "
13
10
b1z !
b1101 5
1%
b1101 4
#1000000
b0z "
03
00
b0z !
11
b1110 5
0%
b10 &
b1110 4
#1030000
b1z "
13
10
b1z !
b1111 5
1%
b1111 4
#1060000
b0z "
03
00
b0z !
01
02
0/
1.
b10000 5
0%
b0 &
b0 '
b0 $
b10 #
b10000 4
#1090000
b1z "
13
10
b1z !
b10001 5
1%
b10001 4
#1120000
b0z "
03
00
b0z !
11
b10010 5
0%
b10 &
b10010 4
#1150000
b1z "
13
10
b1z !
b10011 5
1%
b10011 4
#1180000
b0z "
03
00
b0z !
01
12
b10100 5
0%
b0 &
b10 '
b10100 4
#1210000
b1z "
13
10
b1z !
b10101 5
1%
b10101 4
#1240000
b0z "
03
00
b0z !
11
b10110 5
0%
b10 &
b10110 4
#1270000
b1z "
13
10
b1z !
b10111 5
1%
b10111 4
#1300000
b0z "
03
00
b0z !
01
02
1/
b11000 5
0%
b0 &
b0 '
b10 $
b11000 4
#1330000
b1z "
13
10
b1z !
b11001 5
1%
b11001 4
#1360000
b0z "
03
00
b0z !
11
b11010 5
0%
b10 &
b11010 4
#1390000
b1z "
13
10
b1z !
b11011 5
1%
b11011 4
#1420000
b0z "
03
00
b0z !
01
12
b11100 5
0%
b0 &
b10 '
b11100 4
#1450000
b1z "
13
10
b1z !
b11101 5
1%
b11101 4
#1480000
b0z "
03
00
b0z !
11
b11110 5
0%
b10 &
b11110 4
#1510000
b1z "
13
10
b1z !
b11111 5
1%
b11111 4
#1540000
b0z "
03
00
b0z !
01
02
0/
0.
b100000 5
0%
b0 &
b0 '
b0 $
b0 #
b0 4
